Workbook

Sheet Homologación Estados
A1: Llave | B1: Estados Consolidados
A2: No Vigente00 | B2: No Vigente
A3: No Vigente0Ing No RecibidaAs Built No Recibido00 | B3: No Vigente
A4: No VigenteAs Built No Recibido00 | B4: No Vigente
A5: No VigenteIng No Recibida00 | B5: No Vigente
A6: No VigenteIng No RecibidaAs Built No Recibido00 | B6: No Vigente
A7: No VigenteTSS Aprobado con observacionesIng No RecibidaAs Built No Recibido00 | B7: No Vigente
A8: No VigenteTSS AprobadoIng Aprobada con ObservacionesAs Built Detenido00 | B8: No Vigente
A9: No VigenteTSS AprobadoIng Aprobada con ObservacionesAs Built No Recibido00 | B9: No Vigente
A10: No VigenteTSS AprobadoIng AprobadaAs Built Detenido00 | B10: No Vigente
A11: No VigenteTSS AprobadoIng AprobadaAs Built En Revisión00 | B11: No Vigente
A12: No VigenteTSS AprobadoIng AprobadaAs Built No Recibido00 | B12: No Vigente
... A90: VigenteTSS RechazadoIng No RecibidaAs Built No Recibido00 | B90: En Etapa de TSS 4G

Sheet Tracker
B2: =SUBTOTAL(3,B4:B1448) -> 1
A3: Busqueda | B3: ID Sitio | C3: Nombre Sitio | D3: N Region | E3: LAT | F3: LONG | G3: Region | H3: Comuna | I3: Dirección | J3: Proyecto | K3: Vigencia | L3: Concurso 5G | M3: Forecast Inmobiliaria | N3: Etapa Subtel | O3: Operador | P3: Colo/BTS | Q3: Comentario | R3: Tipo Estructura | S3: RF ALTURA (m) | T3: ID OOII | U3: Asignación TSS | V3: W Asignación TSS | W3: Presentación TSS | X3: Presentación Correcciones TSS Observado | Y3: W Presentación TSS | Z3: Fecha de Solicitud de Revisión PMO | AA3: Fecha Máxima Respuesta | AB3: SLA Revisión_1 | AC3: Status TSS RF | AD3: Comentarios TSS RF | AE3: TSS Fecha de Aprobación/obs RF | AF3: W TSS Aprobación RF | AG3: Status TSS OOCC | AH3: Comentarios TSS OOCC | AI3: TSS Fecha de Aprobación/Obs OOCC | AJ3: W TSS Aprobación OOCC | AK3: Status TSS Implementación | AL3: Comentarios TSS Implementación | AM3: TSS Fecha de Aprobación/obs Implementación | AN3: W TSS Aprobación Implementación | AO3: Status TSS ECE | AP3: Comentarios TSS ECE | AQ3: TSS Fecha de Aprobación/Obs ECE | AR3: W TSS Aprobación ECE | AS3: Status TSS MMOO | AT3: Comentarios TSS MMOO | AU3: TSS Fecha de Aprobación/Obs MMOO | AV3: W TSS Aprobación MMOO | AW3: Fecha TSS Aprobación/Obs | AX3: W TSS Aprobación | AY3: Status TSS | AZ3: Status FC | BA3: Status Contrato | BB3: Presentación Ingeniería OOII | BC3: Presentación Correcciones Ing OOII | BD3: Fecha de envio Ing de PMO a Áreas | BE3: Week de Envio Ing | BF3: Fecha Maxima Respuesta Ing | BG3: Week Respuesta Ing | BH3: SLA Revisión2 | BI3: Status Ing OOCC | BJ3: Comentarios Ing OOCC | BK3: Ing Fecha de Aprobación/Obs OOCC | BL3: W Ing Aprobación OOCC | BM3: Status Ing RF | BN3: Comentarios Ing RF | BO3: Ing Fecha de Aprobación/Obs RF | BP3: W Ing Aprobación RF | BQ3: Status Ing Implementación | BR3: Comentarios Ing Implementación | BS3: Ing Fecha de Aprobación/Obs Implementación | BT3: W Ing Aprobación Implementación | BU3: Status Ing ECE | BV3: Comentarios Ing ECE | BW3: Ing Fecha de Aprobación/Obs ECE | BX3: W Ing Aprobación ECE | BY3: Fecha Ing Aprobación/Obs | BZ3: W Ing Aprobación | CA3: Status Ing | CB3: Estado OOCC | CC3: Estado OOEE | CD3: Disponibilidad Energía Provisoria | CE3: Disponibilidad Empalme | CF3: Presentación As built OOII | CG3: Presentación Correcciones As built OOII | CH3: Fecha de envio Asbuilt de PMO a Áreas | CI3: Week de Envio As built | CJ3: Fecha Respuesta As built | CK3: Week Respuesta As built | CL3: SLA Revisión3 | CM3: Status Asbuilt OOCC | CN3: Comentarios As built OOCC | CO3: As Built Fecha de Aprobación/Obs OOCC | CP3: W Asbuilt Aprobación OOCC | CQ3: Status As Built RF | CR3: Comentarios As built RF | CS3: As built Fecha de Aprobación/Obs RF | CT3: W Asbuilt Aprobación RF | CU3: Status As Built Implementación | CV3: Comentarios As built Implementación | CW3: Fecha de Aprobación/Obs Implementación | CX3: W Asbuilt Aprobación Implementación | CY3: Status As built ECE | CZ3: Comentarios Asbuilt ECE | DA3: As Built Fecha de Aprobación/Obs ECE | DB3: W Asbuilt Aprobación ECE | DC3: Fecha Asbuilt Aprobación/Obs | DD3: W Asbuilt Aprobación/Obs | DE3: Status Asbuilt | DF3: API Firmada | DG3: Responsable Gabinete | DH3: Rectificador Instalado | DI3: Fecha de Inicio Gestión DOM | DJ3: Status DOM | DK3: Tipo Tx | DL3: Status Tx | DM3: Forecast Entrega Tx | DN3: Fecha Real de Entrega | DO3: Fecha Entrega Certficado | DP3: Observación | DQ3: Proveedor UAN | DR3: Forecast Instalación UAN | DS3: Fecha Real Inst. UAN | DT3: Status IPRAN | DU3: Fecha de Envio a Equipo Implementador RF | DV3: Fecha Sitio On Air | DW3: Sitios On air | DX3: Fecha de recepción de llaves | DY3: Recibida por | DZ3: Observación4 | EA3: OC Inmobiliaria | EB3: Status Sitio | EC3: Plan 2024 | ED3: Plan 2025 (90) | EE3: Plan 290 | EF3: Forecast OOII | EG3: Frorecast OOII W | EH3: Riesgo | EI3: Comentario Riesgo | EJ3: Llave
A4: =IFERROR(IF(VLOOKUP(B4,SEARCH!A:A,1,0)=B4,"OK",""),"") | B4: 06_732 | C4: Graneros Luis Cruz Martinez | D4: 6 | E4: -34.06658 | F4: -70.72095 | G4: Libertador General Bernardo O'Higgins | H4: Graneros | I4: Nemesio Antunes, vereda frente a la casa N° 0306 | J4: Fase 1 - On Hold RF | K4: No Vigente | L4: No aplica | M4: 3 | O4: 0 | P4: BTS | Q4: 5-2-2025 Se informa por RF que sitios salen de plan 2024 (Correo Delfos) | R4: POSTE METALICO | S4: 18 | U4: 0 | V4: =IF(U4="","",IF(U4="TBD","TBD",IF(U4="N/A","N/A","W"&TEXT(WEEKNUM(U4,21),"00")&" "&YEAR(U4)))) -> W52 1900 | Y4: =IF(X4="","",IF(X4="TBD","TBD",IF(X4="N/A","N/A","W"&TEXT(WEEKNUM(X4,21),"00")&" "&YEAR(X4)))) | AB4: =+IF(Z4="",0,AA4-Z4) -> 0 | AC4: TSS No Recibido | AF4: =IF(AE4="","",IF(AE4="TBD","TBD",IF(AE4="N/A","N/A","W"&TEXT(WEEKNUM(AE4,21),"00")&" "&YEAR(AE4)))) | AG4: TSS No Recibido | AJ4: =IF(AI4="","",IF(AI4="TBD","TBD",IF(AI4="N/A","N/A","W"&TEXT(WEEKNUM(AI4,21),"00")&" "&YEAR(AI4)))) | AK4: TSS No Recibido | AN4: =IF(AM4="","",IF(AM4="TBD","TBD",IF(AM4="N/A","N/A","W"&TEXT(WEEKNUM(AM4,21),"00")&" "&YEAR(AM4)))) | AO4: TSS No Recibido | AR4: =IF(AQ4="","",IF(AQ4="TBD","TBD",IF(AQ4="N/A","N/A","W"&TEXT(WEEKNUM(AQ4,21),"00")&" "&YEAR(AQ4)))) | AX4: =IF(AW4="","",IF(AW4="TBD","TBD",IF(AW4="N/A","N/A","W"&TEXT(WEEKNUM(AW4,21),"00")&" "&YEAR(AW4)))) | AY4: TSS No Recibido 4G | AZ4: Pendiente FC | BA4: Contrato No Firmado | BE4: =IF(BD4="","",IF(BD4="TBD","TBD",IF(BD4="N/A","N/A","W"&TEXT(WEEKNUM(BD4,21),"00")&" "&YEAR(BD4)))) | BG4: =IF(BF4="","",IF(BF4="TBD","TBD",IF(BF4="N/A","N/A","W"&TEXT(WEEKNUM(BF4,21),"00")&" "&YEAR(BF4)))) | BH4: =+IF(BF4="",0,(BF4-BD4)) -> 0 | BI4: Ing No Recibida | BL4: =IF(BK4="","",IF(BK4="TBD","TBD",IF(BK4="N/A","N/A","W"&TEXT(WEEKNUM(BK4,21),"00")&" "&YEAR(BK4)))) | BM4: Ing No Recibida | BP4: =IF(BO4="","",IF(BO4="TBD","TBD",IF(BO4="N/A","N/A","W"&TEXT(WEEKNUM(BO4,21),"00")&" "&YEAR(BO4)))) | BQ4: Ing No Recibida | BT4: =IF(BS4="","",IF(BS4="TBD","TBD",IF(BS4="N/A","N/A","W"&TEXT(WEEKNUM(BS4,21),"00")&" "&YEAR(BS4)))) | BU4: Ing No Recibida | BX4: =IF(BW4="","",IF(BW4="TBD","TBD",IF(BW4="N/A","N/A","W"&TEXT(WEEKNUM(BW4,21),"00")&" "&YEAR(BW4)))) | BZ4: =IF(BY4="","",IF(BY4="TBD","TBD",IF(BY4="N/A","N/A","W"&TEXT(WEEKNUM(BY4,21),"00")&" "&YEAR(BY4)))) | CA4: Ing No Recibida 4G | CB4: 0 | CI4: =IF(CH4="","",IF(CH4="TBD","TBD",IF(CH4="N/A","N/A","W"&TEXT(WEEKNUM(CH4,21),"00")&" "&YEAR(CH4)))) | CK4: =IF(CJ4="","",IF(CJ4="TBD","TBD",IF(CJ4="N/A","N/A","W"&TEXT(WEEKNUM(CJ4,21),"00")&" "&YEAR(CJ4)))) | CL4: =+IF(CJ4="",0,(CJ4-CH4)) -> 0 | CM4: As Built No Recibido | CP4: =IF(CO4="","",IF(CO4="TBD","TBD",IF(CO4="N/A","N/A","W"&TEXT(WEEKNUM(CO4,21),"00")&" "&YEAR(CO4)))) | CQ4: As Built No Recibido | CT4: =IF(CS4="","",IF(CS4="TBD","TBD",IF(CS4="N/A","N/A","W"&TEXT(WEEKNUM(CS4,21),"00")&" "&YEAR(CS4)))) | CU4: As Built No Recibido | CX4: =IF(CW4="","",IF(CW4="TBD","TBD",IF(CW4="N/A","N/A","W"&TEXT(WEEKNUM(CW4,21),"00")&" "&YEAR(CW4)))) | CY4: As Built No Recibido | DB4: =IF(DA4="","",IF(DA4="TBD","TBD",IF(DA4="N/A","N/A","W"&TEXT(WEEKNUM(DA4,21),"00")&" "&YEAR(DA4)))) | DD4: =IF(DC4="","",IF(DC4="TBD","TBD",IF(DC4="N/A","N/A","W"&TEXT(WEEKNUM(DC4,21),"00")&" "&YEAR(DC4)))) | DE4: As Built No Recibido | DG4: Gabinete Huawei | DK4: FO | DL4: Poste | DQ4: Huawei | EB4: En Etapa de TSS 4G | EI4: 0 | EJ4: =K4&AY4&CA4&DE4&DT4&DW4 -> No VigenteTSS No Recibido 4GIng No Recibida 4GAs Built No Recibido
A5: =IFERROR(IF(VLOOKUP(B5,SEARCH!A:A,1,0)=B5,"OK",""),"") | B5: 07_168 | C5: Curico Rauquen | D5: 7 | E5: -34.951722 | F5: -71.192639 | G5: Maule | H5: Curicó | I5: Av. Los Carros, esquina Av Rauquén | J5: No Vigente | K5: No Vigente | L5: No aplica | O5: 0 | P5: BTS | Q5: 5-2-2025 Se informa por RF que sitios salen de plan 2024 (Correo Delfos) | R5: POSTE METALICO | S5: 18 | U5: 0 | V5: =IF(U5="","",IF(U5="TBD","TBD",IF(U5="N/A","N/A","W"&TEXT(WEEKNUM(U5,21),"00")&" "&YEAR(U5)))) -> W52 1900 | Y5: =IF(X5="","",IF(X5="TBD","TBD",IF(X5="N/A","N/A","W"&TEXT(WEEKNUM(X5,21),"00")&" "&YEAR(X5)))) | AB5: =+IF(Z5="",0,AA5-Z5) -> 0 | AC5: TSS No Recibido | AF5: =IF(AE5="","",IF(AE5="TBD","TBD",IF(AE5="N/A","N/A","W"&TEXT(WEEKNUM(AE5,21),"00")&" "&YEAR(AE5)))) | AG5: TSS No Recibido | AJ5: =IF(AI5="","",IF(AI5="TBD","TBD",IF(AI5="N/A","N/A","W"&TEXT(WEEKNUM(AI5,21),"00")&" "&YEAR(AI5)))) | AK5: TSS No Recibido | AN5: =IF(AM5="","",IF(AM5="TBD","TBD",IF(AM5="N/A","N/A","W"&TEXT(WEEKNUM(AM5,21),"00")&" "&YEAR(AM5)))) | AO5: TSS No Recibido | AR5: =IF(AQ5="","",IF(AQ5="TBD","TBD",IF(AQ5="N/A","N/A","W"&TEXT(WEEKNUM(AQ5,21),"00")&" "&YEAR(AQ5)))) | AX5: =IF(AW5="","",IF(AW5="TBD","TBD",IF(AW5="N/A","N/A","W"&TEXT(WEEKNUM(AW5,21),"00")&" "&YEAR(AW5)))) | AY5: TSS No Recibido 4G | AZ5: Pendiente FC | BA5: Contrato No Firmado | BE5: =IF(BD5="","",IF(BD5="TBD","TBD",IF(BD5="N/A","N/A","W"&TEXT(WEEKNUM(BD5,21),"00")&" "&YEAR(BD5)))) | BG5: =IF(BF5="","",IF(BF5="TBD","TBD",IF(BF5="N/A","N/A","W"&TEXT(WEEKNUM(BF5,21),"00")&" "&YEAR(BF5)))) | BH5: =+IF(BF5="",0,(BF5-BD5)) -> 0 | BI5: Ing No Recibida | BL5: =IF(BK5="","",IF(BK5="TBD","TBD",IF(BK5="N/A","N/A","W"&TEXT(WEEKNUM(BK5,21),"00")&" "&YEAR(BK5)))) | BM5: Ing No Recibida | BP5: =IF(BO5="","",IF(BO5="TBD","TBD",IF(BO5="N/A","N/A","W"&TEXT(WEEKNUM(BO5,21),"00")&" "&YEAR(BO5)))) | BQ5: Ing No Recibida | BT5: =IF(BS5="","",IF(BS5="TBD","TBD",IF(BS5="N/A","N/A","W"&TEXT(WEEKNUM(BS5,21),"00")&" "&YEAR(BS5)))) | BU5: Ing No Recibida | BX5: =IF(BW5="","",IF(BW5="TBD","TBD",IF(BW5="N/A","N/A","W"&TEXT(WEEKNUM(BW5,21),"00")&" "&YEAR(BW5)))) | BZ5: =IF(BY5="","",IF(BY5="TBD","TBD",IF(BY5="N/A","N/A","W"&TEXT(WEEKNUM(BY5,21),"00")&" "&YEAR(BY5)))) | CA5: Ing No Recibida 4G | CB5: 0 | CI5: =IF(CH5="","",IF(CH5="TBD","TBD",IF(CH5="N/A","N/A","W"&TEXT(WEEKNUM(CH5,21),"00")&" "&YEAR(CH5)))) | CK5: =IF(CJ5="","",IF(CJ5="TBD","TBD",IF(CJ5="N/A","N/A","W"&TEXT(WEEKNUM(CJ5,21),"00")&" "&YEAR(CJ5)))) | CL5: =+IF(CJ5="",0,(CJ5-CH5)) -> 0 | CM5: As Built No Recibido | CP5: =IF(CO5="","",IF(CO5="TBD","TBD",IF(CO5="N/A","N/A","W"&TEXT(WEEKNUM(CO5,21),"00")&" "&YEAR(CO5)))) | CQ5: As Built No Recibido | CT5: =IF(CS5="","",IF(CS5="TBD","TBD",IF(CS5="N/A","N/A","W"&TEXT(WEEKNUM(CS5,21),"00")&" "&YEAR(CS5)))) | CU5: As Built No Recibido | CX5: =IF(CW5="","",IF(CW5="TBD","TBD",IF(CW5="N/A","N/A","W"&TEXT(WEEKNUM(CW5,21),"00")&" "&YEAR(CW5)))) | CY5: As Built No Recibido | DB5: =IF(DA5="","",IF(DA5="TBD","TBD",IF(DA5="N/A","N/A","W"&TEXT(WEEKNUM(DA5,21),"00")&" "&YEAR(DA5)))) | DD5: =IF(DC5="","",IF(DC5="TBD","TBD",IF(DC5="N/A","N/A","W"&TEXT(WEEKNUM(DC5,21),"00")&" "&YEAR(DC5)))) | DE5: As Built No Recibido | DG5: Gabinete Huawei | DK5: FO | DL5: Poste | DQ5: Huawei | EB5: En Etapa de TSS 4G | EI5: 0 | EJ5: =K5&AY5&CA5&DE5&DT5&DW5 -> No VigenteTSS No Recibido 4GIng No Recibida 4GAs Built No Recibido
A6: =IFERROR(IF(VLOOKUP(B6,SEARCH!A:A,1,0)=B6,"OK",""),"") | B6: 53i_390 | C6: Banco Bci - Seguros Generales | D6: 13 | E6: -33.405994 | F6: -70.568975 | G6: Metropolitana de Santiago | H6: LAS CONDES | J6: Indoor | K6: No Vigente | L6: No aplica | O6: 0 | P6: 0 | R6: Indoor - B2B | V6: =IF(U6="","",IF(U6="TBD","TBD",IF(U6="N/A","N/A","W"&TEXT(WEEKNUM(U6,21),"00")&" "&YEAR(U6)))) | Y6: =IF(X6="","",IF(X6="TBD","TBD",IF(X6="N/A","N/A","W"&TEXT(WEEKNUM(X6,21),"00")&" "&YEAR(X6)))) | AB6: =+IF(Z6="",0,AA6-Z6) -> 0 | AC6: TSS No Recibido | AF6: =IF(AE6="","",IF(AE6="TBD","TBD",IF(AE6="N/A","N/A","W"&TEXT(WEEKNUM(AE6,21),"00")&" "&YEAR(AE6)))) | AG6: TSS No Recibido | AJ6: =IF(AI6="","",IF(AI6="TBD","TBD",IF(AI6="N/A","N/A","W"&TEXT(WEEKNUM(AI6,21),"00")&" "&YEAR(AI6)))) | AK6: TSS No Recibido | AN6: =IF(AM6="","",IF(AM6="TBD","TBD",IF(AM6="N/A","N/A","W"&TEXT(WEEKNUM(AM6,21),"00")&" "&YEAR(AM6)))) | AO6: TSS No Recibido | AR6: =IF(AQ6="","",IF(AQ6="TBD","TBD",IF(AQ6="N/A","N/A","W"&TEXT(WEEKNUM(AQ6,21),"00")&" "&YEAR(AQ6)))) | AX6: =IF(AW6="","",IF(AW6="TBD","TBD",IF(AW6="N/A","N/A","W"&TEXT(WEEKNUM(AW6,21),"00")&" "&YEAR(AW6)))) | AY6: TSS No Recibido 4G | AZ6: Pendiente FC | BA6: Contrato No Firmado | BE6: =IF(BD6="","",IF(BD6="TBD","TBD",IF(BD6="N/A","N/A","W"&TEXT(WEEKNUM(BD6,21),"00")&" "&YEAR(BD6)))) | BG6: =IF(BF6="","",IF(BF6="TBD","TBD",IF(BF6="N/A","N/A","W"&TEXT(WEEKNUM(BF6,21),"00")&" "&YEAR(BF6)))) | BH6: =+IF(BF6="",0,(BF6-BD6)) -> 0 | BI6: Ing No Recibida | BL6: =IF(BK6="","",IF(BK6="TBD","TBD",IF(BK6="N/A","N/A","W"&TEXT(WEEKNUM(BK6,21),"00")&" "&YEAR(BK6)))) | BM6: Ing No Recibida | BP6: =IF(BO6="","",IF(BO6="TBD","TBD",IF(BO6="N/A","N/A","W"&TEXT(WEEKNUM(BO6,21),"00")&" "&YEAR(BO6)))) | BQ6: Ing No Recibida | BT6: =IF(BS6="","",IF(BS6="TBD","TBD",IF(BS6="N/A","N/A","W"&TEXT(WEEKNUM(BS6,21),"00")&" "&YEAR(BS6)))) | BU6: Ing No Recibida | BX6: =IF(BW6="","",IF(BW6="TBD","TBD",IF(BW6="N/A","N/A","W"&TEXT(WEEKNUM(BW6,21),"00")&" "&YEAR(BW6)))) | BZ6: =IF(BY6="","",IF(BY6="TBD","TBD",IF(BY6="N/A","N/A","W"&TEXT(WEEKNUM(BY6,21),"00")&" "&YEAR(BY6)))) | CA6: Ing No Recibida 4G | CB6: 0 | CI6: =IF(CH6="","",IF(CH6="TBD","TBD",IF(CH6="N/A","N/A","W"&TEXT(WEEKNUM(CH6,21),"00")&" "&YEAR(CH6)))) | CK6: =IF(CJ6="","",IF(CJ6="TBD","TBD",IF(CJ6="N/A","N/A","W"&TEXT(WEEKNUM(CJ6,21),"00")&" "&YEAR(CJ6)))) | CL6: =+IF(CJ6="",0,(CJ6-CH6)) -> 0 | CM6: As Built No Recibido | CP6: =IF(CO6="","",IF(CO6="TBD","TBD",IF(CO6="N/A","N/A","W"&TEXT(WEEKNUM(CO6,21),"00")&" "&YEAR(CO6)))) | CQ6: As Built No Recibido | CT6: =IF(CS6="","",IF(CS6="TBD","TBD",IF(CS6="N/A","N/A","W"&TEXT(WEEKNUM(CS6,21),"00")&" "&YEAR(CS6)))) | CU6: As Built No Recibido | CX6: =IF(CW6="","",IF(CW6="TBD","TBD",IF(CW6="N/A","N/A","W"&TEXT(WEEKNUM(CW6,21),"00")&" "&YEAR(CW6)))) | CY6: As Built No Recibido | DB6: =IF(DA6="","",IF(DA6="TBD","TBD",IF(DA6="N/A","N/A","W"&TEXT(WEEKNUM(DA6,21),"00")&" "&YEAR(DA6)))) | DD6: =IF(DC6="","",IF(DC6="TBD","TBD",IF(DC6="N/A","N/A","W"&TEXT(WEEKNUM(DC6,21),"00")&" "&YEAR(DC6)))) | DE6: As Built No Recibido | DG6: Por Definir | DK6: FO | DL6: Pendiente | DQ6: ZTE | DY6: 0 | DZ6: 0 | EA6: 0 | EB6: En Etapa de TSS 4G | EI6: 0 | EJ6: =K6&AY6&CA6&DE6&DT6&DW6 -> No VigenteTSS No Recibido 4GIng No Recibida 4GAs Built No Recibido
A7: =IFERROR(IF(VLOOKUP(B7,SEARCH!A:A,1,0)=B7,"OK",""),"") | B7: 53i_393 | C7: Holding Laboratorio Ballerina | D7: 13 | E7: -33.422743 | F7: -70.621951 | G7: Metropolitana de Santiago | H7: PROVIDENCIA | J7: Indoor | K7: No Vigente | L7: No aplica | O7: 0 | P7: 0 | Q7: Sitio descartado por B2B | R7: Indoor - B2B | U7: 0 | V7: =IF(U7="","",IF(U7="TBD","TBD",IF(U7="N/A","N/A","W"&TEXT(WEEKNUM(U7,21),"00")&" "&YEAR(U7)))) -> W52 1900 | Y7: =IF(X7="","",IF(X7="TBD","TBD",IF(X7="N/A","N/A","W"&TEXT(WEEKNUM(X7,21),"00")&" "&YEAR(X7)))) | AB7: =+IF(Z7="",0,AA7-Z7) -> 0 | AC7: TSS No Recibido | AF7: =IF(AE7="","",IF(AE7="TBD","TBD",IF(AE7="N/A","N/A","W"&TEXT(WEEKNUM(AE7,21),"00")&" "&YEAR(AE7)))) | AG7: TSS No Recibido | AJ7: =IF(AI7="","",IF(AI7="TBD","TBD",IF(AI7="N/A","N/A","W"&TEXT(WEEKNUM(AI7,21),"00")&" "&YEAR(AI7)))) | AK7: TSS No Recibido | AN7: =IF(AM7="","",IF(AM7="TBD","TBD",IF(AM7="N/A","N/A","W"&TEXT(WEEKNUM(AM7,21),"00")&" "&YEAR(AM7)))) | AO7: TSS No Recibido | AR7: =IF(AQ7="","",IF(AQ7="TBD","TBD",IF(AQ7="N/A","N/A","W"&TEXT(WEEKNUM(AQ7,21),"00")&" "&YEAR(AQ7)))) | AX7: =IF(AW7="","",IF(AW7="TBD","TBD",IF(AW7="N/A","N/A","W"&TEXT(WEEKNUM(AW7,21),"00")&" "&YEAR(AW7)))) | AY7: TSS No Recibido 4G | AZ7: Pendiente FC | BA7: Contrato No Firmado | BE7: =IF(BD7="","",IF(BD7="TBD","TBD",IF(BD7="N/A","N/A","W"&TEXT(WEEKNUM(BD7,21),"00")&" "&YEAR(BD7)))) | BG7: =IF(BF7="","",IF(BF7="TBD","TBD",IF(BF7="N/A","N/A","W"&TEXT(WEEKNUM(BF7,21),"00")&" "&YEAR(BF7)))) | BH7: =+IF(BF7="",0,(BF7-BD7)) -> 0 | BI7: Ing No Recibida | BL7: =IF(BK7="","",IF(BK7="TBD","TBD",IF(BK7="N/A","N/A","W"&TEXT(WEEKNUM(BK7,21),"00")&" "&YEAR(BK7)))) | BM7: Ing No Recibida | BP7: =IF(BO7="","",IF(BO7="TBD","TBD",IF(BO7="N/A","N/A","W"&TEXT(WEEKNUM(BO7,21),"00")&" "&YEAR(BO7)))) | BQ7: Ing No Recibida | BT7: =IF(BS7="","",IF(BS7="TBD","TBD",IF(BS7="N/A","N/A","W"&TEXT(WEEKNUM(BS7,21),"00")&" "&YEAR(BS7)))) | BU7: Ing No Recibida | BX7: =IF(BW7="","",IF(BW7="TBD","TBD",IF(BW7="N/A","N/A","W"&TEXT(WEEKNUM(BW7,21),"00")&" "&YEAR(BW7)))) | BZ7: =IF(BY7="","",IF(BY7="TBD","TBD",IF(BY7="N/A","N/A","W"&TEXT(WEEKNUM(BY7,21),"00")&" "&YEAR(BY7)))) | CA7: Ing No Recibida 4G | CB7: 0 | CI7: =IF(CH7="","",IF(CH7="TBD","TBD",IF(CH7="N/A","N/A","W"&TEXT(WEEKNUM(CH7,21),"00")&" "&YEAR(CH7)))) | CK7: =IF(CJ7="","",IF(CJ7="TBD","TBD",IF(CJ7="N/A","N/A","W"&TEXT(WEEKNUM(CJ7,21),"00")&" "&YEAR(CJ7)))) | CL7: =+IF(CJ7="",0,(CJ7-CH7)) -> 0 | CM7: As Built No Recibido | CP7: =IF(CO7="","",IF(CO7="TBD","TBD",IF(CO7="N/A","N/A","W"&TEXT(WEEKNUM(CO7,21),"00")&" "&YEAR(CO7)))) | CQ7: As Built No Recibido | CT7: =IF(CS7="","",IF(CS7="TBD","TBD",IF(CS7="N/A","N/A","W"&TEXT(WEEKNUM(CS7,21),"00")&" "&YEAR(CS7)))) | CU7: As Built No Recibido | CX7: =IF(CW7="","",IF(CW7="TBD","TBD",IF(CW7="N/A","N/A","W"&TEXT(WEEKNUM(CW7,21),"00")&" "&YEAR(CW7)))) | CY7: As Built No Recibido | DB7: =IF(DA7="","",IF(DA7="TBD","TBD",IF(DA7="N/A","N/A","W"&TEXT(WEEKNUM(DA7,21),"00")&" "&YEAR(DA7)))) | DD7: =IF(DC7="","",IF(DC7="TBD","TBD",IF(DC7="N/A","N/A","W"&TEXT(WEEKNUM(DC7,21),"00")&" "&YEAR(DC7)))) | DE7: As Built No Recibido | DG7: Por Definir | DK7: FO | DL7: Pendiente | DQ7: ZTE | DY7: 0 | DZ7: 0 | EA7: 0 | EB7: En Etapa de TSS 4G | EI7: 0 | EJ7: =K7&AY7&CA7&DE7&DT7&DW7 -> No VigenteTSS No Recibido 4GIng No Recibida 4GAs Built No Recibido
A8: =IFERROR(IF(VLOOKUP(B8,SEARCH!A:A,1,0)=B8,"OK",""),"") | B8: 53i_396 | C8: INVERSIONES QUILAPILUN S.A. | D8: 13 | E8: -33.378032 | F8: -70.742595 | G8: Metropolitana de Santiago | H8: QUILICURA | J8: Indoor | K8: No Vigente | L8: No aplica | O8: 0 | P8: 0 | Q8: Sitio descartado por B2B | R8: Indoor - B2B | U8: 0 | V8: =IF(U8="","",IF(U8="TBD","TBD",IF(U8="N/A","N/A","W"&TEXT(WEEKNUM(U8,21),"00")&" "&YEAR(U8)))) -> W52 1900 | Y8: =IF(X8="","",IF(X8="TBD","TBD",IF(X8="N/A","N/A","W"&TEXT(WEEKNUM(X8,21),"00")&" "&YEAR(X8)))) | AB8: =+IF(Z8="",0,AA8-Z8) -> 0 | AC8: TSS No Recibido | AF8: =IF(AE8="","",IF(AE8="TBD","TBD",IF(AE8="N/A","N/A","W"&TEXT(WEEKNUM(AE8,21),"00")&" "&YEAR(AE8)))) | AG8: TSS No Recibido | AJ8: =IF(AI8="","",IF(AI8="TBD","TBD",IF(AI8="N/A","N/A","W"&TEXT(WEEKNUM(AI8,21),"00")&" "&YEAR(AI8)))) | AK8: TSS No Recibido | AN8: =IF(AM8="","",IF(AM8="TBD","TBD",IF(AM8="N/A","N/A","W"&TEXT(WEEKNUM(AM8,21),"00")&" "&YEAR(AM8)))) | AO8: TSS No Recibido | AR8: =IF(AQ8="","",IF(AQ8="TBD","TBD",IF(AQ8="N/A","N/A","W"&TEXT(WEEKNUM(AQ8,21),"00")&" "&YEAR(AQ8)))) | AX8: =IF(AW8="","",IF(AW8="TBD","TBD",IF(AW8="N/A","N/A","W"&TEXT(WEEKNUM(AW8,21),"00")&" "&YEAR(AW8)))) | AY8: TSS No Recibido 4G | AZ8: Pendiente FC | BA8: Contrato No Firmado | BE8: =IF(BD8="","",IF(BD8="TBD","TBD",IF(BD8="N/A","N/A","W"&TEXT(WEEKNUM(BD8,21),"00")&" "&YEAR(BD8)))) | BG8: =IF(BF8="","",IF(BF8="TBD","TBD",IF(BF8="N/A","N/A","W"&TEXT(WEEKNUM(BF8,21),"00")&" "&YEAR(BF8)))) | BH8: =+IF(BF8="",0,(BF8-BD8)) -> 0 | BI8: Ing No Recibida | BL8: =IF(BK8="","",IF(BK8="TBD","TBD",IF(BK8="N/A","N/A","W"&TEXT(WEEKNUM(BK8,21),"00")&" "&YEAR(BK8)))) | BM8: Ing No Recibida | BP8: =IF(BO8="","",IF(BO8="TBD","TBD",IF(BO8="N/A","N/A","W"&TEXT(WEEKNUM(BO8,21),"00")&" "&YEAR(BO8)))) | BQ8: Ing No Recibida | BT8: =IF(BS8="","",IF(BS8="TBD","TBD",IF(BS8="N/A","N/A","W"&TEXT(WEEKNUM(BS8,21),"00")&" "&YEAR(BS8)))) | BU8: Ing No Recibida | BX8: =IF(BW8="","",IF(BW8="TBD","TBD",IF(BW8="N/A","N/A","W"&TEXT(WEEKNUM(BW8,21),"00")&" "&YEAR(BW8)))) | BZ8: =IF(BY8="","",IF(BY8="TBD","TBD",IF(BY8="N/A","N/A","W"&TEXT(WEEKNUM(BY8,21),"00")&" "&YEAR(BY8)))) | CA8: Ing No Recibida 4G | CB8: 0 | CI8: =IF(CH8="","",IF(CH8="TBD","TBD",IF(CH8="N/A","N/A","W"&TEXT(WEEKNUM(CH8,21),"00")&" "&YEAR(CH8)))) | CK8: =IF(CJ8="","",IF(CJ8="TBD","TBD",IF(CJ8="N/A","N/A","W"&TEXT(WEEKNUM(CJ8,21),"00")&" "&YEAR(CJ8)))) | CL8: =+IF(CJ8="",0,(CJ8-CH8)) -> 0 | CM8: As Built No Recibido | CP8: =IF(CO8="","",IF(CO8="TBD","TBD",IF(CO8="N/A","N/A","W"&TEXT(WEEKNUM(CO8,21),"00")&" "&YEAR(CO8)))) | CQ8: As Built No Recibido | CT8: =IF(CS8="","",IF(CS8="TBD","TBD",IF(CS8="N/A","N/A","W"&TEXT(WEEKNUM(CS8,21),"00")&" "&YEAR(CS8)))) | CU8: As Built No Recibido | CX8: =IF(CW8="","",IF(CW8="TBD","TBD",IF(CW8="N/A","N/A","W"&TEXT(WEEKNUM(CW8,21),"00")&" "&YEAR(CW8)))) | CY8: As Built No Recibido | DB8: =IF(DA8="","",IF(DA8="TBD","TBD",IF(DA8="N/A","N/A","W"&TEXT(WEEKNUM(DA8,21),"00")&" "&YEAR(DA8)))) | DD8: =IF(DC8="","",IF(DC8="TBD","TBD",IF(DC8="N/A","N/A","W"&TEXT(WEEKNUM(DC8,21),"00")&" "&YEAR(DC8)))) | DE8: As Built No Recibido | DG8: Por Definir | DK8: FO | DL8: Pendiente | DQ8: ZTE | DY8: 0 | DZ8: 0 | EA8: 0 | EB8: En Etapa de TSS 4G | EI8: 0 | EJ8: =K8&AY8&CA8&DE8&DT8&DW8 -> No VigenteTSS No Recibido 4GIng No Recibida 4GAs Built No Recibido
A9: =IFERROR(IF(VLOOKUP(B9,SEARCH!A:A,1,0)=B9,"OK",""),"") | B9: 16i_121 | C9: Jumbo - Longitudinal Chillán | D9: 16 | E9: -36.595668 | F9: -72.107283 | G9: Ñuble | H9: Chillan | J9: Indoor | K9: No Vigente | L9: No aplica | O9: 0 | P9: 0 | R9: Indoor - B2B | U9: 0 | V9: =IF(U9="","",IF(U9="TBD","TBD",IF(U9="N/A","N/A","W"&TEXT(WEEKNUM(U9,21),"00")&" "&YEAR(U9)))) -> W52 1900 | Y9: =IF(X9="","",IF(X9="TBD","TBD",IF(X9="N/A","N/A","W"&TEXT(WEEKNUM(X9,21),"00")&" "&YEAR(X9)))) | AB9: =+IF(Z9="",0,AA9-Z9) -> 0 | AC9: TSS No Recibido | AF9: =IF(AE9="","",IF(AE9="TBD","TBD",IF(AE9="N/A","N/A","W"&TEXT(WEEKNUM(AE9,21),"00")&" "&YEAR(AE9)))) | AG9: TSS No Recibido | AJ9: =IF(AI9="","",IF(AI9="TBD","TBD",IF(AI9="N/A","N/A","W"&TEXT(WEEKNUM(AI9,21),"00")&" "&YEAR(AI9)))) | AK9: TSS No Recibido | AN9: =IF(AM9="","",IF(AM9="TBD","TBD",IF(AM9="N/A","N/A","W"&TEXT(WEEKNUM(AM9,21),"00")&" "&YEAR(AM9)))) | AO9: TSS No Recibido | AR9: =IF(AQ9="","",IF(AQ9="TBD","TBD",IF(AQ9="N/A","N/A","W"&TEXT(WEEKNUM(AQ9,21),"00")&" "&YEAR(AQ9)))) | AX9: =IF(AW9="","",IF(AW9="TBD","TBD",IF(AW9="N/A","N/A","W"&TEXT(WEEKNUM(AW9,21),"00")&" "&YEAR(AW9)))) | AY9: TSS No Recibido 4G | AZ9: Pendiente FC | BA9: Contrato No Firmado | BE9: =IF(BD9="","",IF(BD9="TBD","TBD",IF(BD9="N/A","N/A","W"&TEXT(WEEKNUM(BD9,21),"00")&" "&YEAR(BD9)))) | BG9: =IF(BF9="","",IF(BF9="TBD","TBD",IF(BF9="N/A","N/A","W"&TEXT(WEEKNUM(BF9,21),"00")&" "&YEAR(BF9)))) | BH9: =+IF(BF9="",0,(BF9-BD9)) -> 0 | BI9: Ing No Recibida | BL9: =IF(BK9="","",IF(BK9="TBD","TBD",IF(BK9="N/A","N/A","W"&TEXT(WEEKNUM(BK9,21),"00")&" "&YEAR(BK9)))) | BM9: Ing No Recibida | BP9: =IF(BO9="","",IF(BO9="TBD","TBD",IF(BO9="N/A","N/A","W"&TEXT(WEEKNUM(BO9,21),"00")&" "&YEAR(BO9)))) | BQ9: Ing No Recibida | BT9: =IF(BS9="","",IF(BS9="TBD","TBD",IF(BS9="N/A","N/A","W"&TEXT(WEEKNUM(BS9,21),"00")&" "&YEAR(BS9)))) | BU9: Ing No Recibida | BX9: =IF(BW9="","",IF(BW9="TBD","TBD",IF(BW9="N/A","N/A","W"&TEXT(WEEKNUM(BW9,21),"00")&" "&YEAR(BW9)))) | BZ9: =IF(BY9="","",IF(BY9="TBD","TBD",IF(BY9="N/A","N/A","W"&TEXT(WEEKNUM(BY9,21),"00")&" "&YEAR(BY9)))) | CA9: Ing No Recibida 4G | CB9: 0 | CI9: =IF(CH9="","",IF(CH9="TBD","TBD",IF(CH9="N/A","N/A","W"&TEXT(WEEKNUM(CH9,21),"00")&" "&YEAR(CH9)))) | CK9: =IF(CJ9="","",IF(CJ9="TBD","TBD",IF(CJ9="N/A","N/A","W"&TEXT(WEEKNUM(CJ9,21),"00")&" "&YEAR(CJ9)))) | CL9: =+IF(CJ9="",0,(CJ9-CH9)) -> 0 | CM9: As Built No Recibido | CP9: =IF(CO9="","",IF(CO9="TBD","TBD",IF(CO9="N/A","N/A","W"&TEXT(WEEKNUM(CO9,21),"00")&" "&YEAR(CO9)))) | CQ9: As Built No Recibido | CT9: =IF(CS9="","",IF(CS9="TBD","TBD",IF(CS9="N/A","N/A","W"&TEXT(WEEKNUM(CS9,21),"00")&" "&YEAR(CS9)))) | CU9: As Built No Recibido | CX9: =IF(CW9="","",IF(CW9="TBD","TBD",IF(CW9="N/A","N/A","W"&TEXT(WEEKNUM(CW9,21),"00")&" "&YEAR(CW9)))) | CY9: As Built No Recibido | DB9: =IF(DA9="","",IF(DA9="TBD","TBD",IF(DA9="N/A","N/A","W"&TEXT(WEEKNUM(DA9,21),"00")&" "&YEAR(DA9)))) | DD9: =IF(DC9="","",IF(DC9="TBD","TBD",IF(DC9="N/A","N/A","W"&TEXT(WEEKNUM(DC9,21),"00")&" "&YEAR(DC9)))) | DE9: As Built No Recibido | DG9: Por Definir | DK9: FO | DL9: Pendiente | DQ9: Huawei | DY9: 0 | DZ9: 0 | EA9: 0 | EB9: En Etapa de TSS 4G | EI9: 0 | EJ9: =K9&AY9&CA9&DE9&DT9&DW9 -> No VigenteTSS No Recibido 4GIng No Recibida 4GAs Built No Recibido
A10: =IFERROR(IF(VLOOKUP(B10,SEARCH!A:A,1,0)=B10,"OK",""),"") | B10: 53i_405 | C10: Polytex S.A | D10: 13 | E10: -33.283105 | F10: -70.736448 | G10: Metropolitana de Santiago | H10: COLINA | I10: Panamericana Norte 21000, Colina | J10: Indoor | K10: No Vigente | L10: No aplica | O10: 0 | P10: 0 | Q10: Sitio descartado por B2B | R10: Indoor - B2B | U10: 0 | V10: =IF(U10="","",IF(U10="TBD","TBD",IF(U10="N/A","N/A","W"&TEXT(WEEKNUM(U10,21),"00")&" "&YEAR(U10)))) -> W52 1900 | Y10: =IF(X10="","",IF(X10="TBD","TBD",IF(X10="N/A","N/A","W"&TEXT(WEEKNUM(X10,21),"00")&" "&YEAR(X10)))) | AB10: =+IF(Z10="",0,AA10-Z10) -> 0 | AC10: TSS No Recibido | AF10: =IF(AE10="","",IF(AE10="TBD","TBD",IF(AE10="N/A","N/A","W"&TEXT(WEEKNUM(AE10,21),"00")&" "&YEAR(AE10)))) | AG10: TSS No Recibido | AJ10: =IF(AI10="","",IF(AI10="TBD","TBD",IF(AI10="N/A","N/A","W"&TEXT(WEEKNUM(AI10,21),"00")&" "&YEAR(AI10)))) | AK10: TSS No Recibido | AN10: =IF(AM10="","",IF(AM10="TBD","TBD",IF(AM10="N/A","N/A","W"&TEXT(WEEKNUM(AM10,21),"00")&" "&YEAR(AM10)))) | AO10: TSS No Recibido | AR10: =IF(AQ10="","",IF(AQ10="TBD","TBD",IF(AQ10="N/A","N/A","W"&TEXT(WEEKNUM(AQ10,21),"00")&" "&YEAR(AQ10)))) | AX10: =IF(AW10="","",IF(AW10="TBD","TBD",IF(AW10="N/A","N/A","W"&TEXT(WEEKNUM(AW10,21),"00")&" "&YEAR(AW10)))) | AY10: TSS No Recibido 4G | AZ10: Pendiente FC | BA10: Contrato No Firmado | BE10: =IF(BD10="","",IF(BD10="TBD","TBD",IF(BD10="N/A","N/A","W"&TEXT(WEEKNUM(BD10,21),"00")&" "&YEAR(BD10)))) | BG10: =IF(BF10="","",IF(BF10="TBD","TBD",IF(BF10="N/A","N/A","W"&TEXT(WEEKNUM(BF10,21),"00")&" "&YEAR(BF10)))) | BH10: =+IF(BF10="",0,(BF10-BD10)) -> 0 | BI10: Ing No Recibida | BL10: =IF(BK10="","",IF(BK10="TBD","TBD",IF(BK10="N/A","N/A","W"&TEXT(WEEKNUM(BK10,21),"00")&" "&YEAR(BK10)))) | BM10: Ing No Recibida | BP10: =IF(BO10="","",IF(BO10="TBD","TBD",IF(BO10="N/A","N/A","W"&TEXT(WEEKNUM(BO10,21),"00")&" "&YEAR(BO10)))) | BQ10: Ing No Recibida | BT10: =IF(BS10="","",IF(BS10="TBD","TBD",IF(BS10="N/A","N/A","W"&TEXT(WEEKNUM(BS10,21),"00")&" "&YEAR(BS10)))) | BU10: Ing No Recibida | BX10: =IF(BW10="","",IF(BW10="TBD","TBD",IF(BW10="N/A","N/A","W"&TEXT(WEEKNUM(BW10,21),"00")&" "&YEAR(BW10)))) | BZ10: =IF(BY10="","",IF(BY10="TBD","TBD",IF(BY10="N/A","N/A","W"&TEXT(WEEKNUM(BY10,21),"00")&" "&YEAR(BY10)))) | CA10: Ing No Recibida 4G | CB10: 0 | CI10: =IF(CH10="","",IF(CH10="TBD","TBD",IF(CH10="N/A","N/A","W"&TEXT(WEEKNUM(CH10,21),"00")&" "&YEAR(CH10)))) | CK10: =IF(CJ10="","",IF(CJ10="TBD","TBD",IF(CJ10="N/A","N/A","W"&TEXT(WEEKNUM(CJ10,21),"00")&" "&YEAR(CJ10)))) | CL10: =+IF(CJ10="",0,(CJ10-CH10)) -> 0 | CM10: As Built No Recibido | CP10: =IF(CO10="","",IF(CO10="TBD","TBD",IF(CO10="N/A","N/A","W"&TEXT(WEEKNUM(CO10,21),"00")&" "&YEAR(CO10)))) | CQ10: As Built No Recibido | CT10: =IF(CS10="","",IF(CS10="TBD","TBD",IF(CS10="N/A","N/A","W"&TEXT(WEEKNUM(CS10,21),"00")&" "&YEAR(CS10)))) | CU10: As Built No Recibido | CX10: =IF(CW10="","",IF(CW10="TBD","TBD",IF(CW10="N/A","N/A","W"&TEXT(WEEKNUM(CW10,21),"00")&" "&YEAR(CW10)))) | CY10: As Built No Recibido | DB10: =IF(DA10="","",IF(DA10="TBD","TBD",IF(DA10="N/A","N/A","W"&TEXT(WEEKNUM(DA10,21),"00")&" "&YEAR(DA10)))) | DD10: =IF(DC10="","",IF(DC10="TBD","TBD",IF(DC10="N/A","N/A","W"&TEXT(WEEKNUM(DC10,21),"00")&" "&YEAR(DC10)))) | DE10: As Built No Recibido | DG10: Por Definir | DK10: FO | DL10: Pendiente | DQ10: ZTE | DY10: 0 | DZ10: 0 | EA10: 0 | EB10: En Etapa de TSS 4G | EI10: 0 | EJ10: =K10&AY10&CA10&DE10&DT10&DW10 -> No VigenteTSS No Recibido 4GIng No Recibida 4GAs Built No Recibido
A11: =IFERROR(IF(VLOOKUP(B11,SEARCH!A:A,1,0)=B11,"OK",""),"") | B11: 07_856 | C11: Villa Los Niches Ruta J-65 | D11: 7 | E11: -35.074722 | F11: -71.151778 | G11: Maule | H11: Curicó | I11: Ruta J-65, Km 11.8 | J11: Fase 1 - On Hold RF | K11: No Vigente | L11: No aplica | M11: TBD | O11: 0 | P11: BTS | Q11: 5-2-2025 Se informa por RF que sitios salen de plan 2024 (Correo Delfos) | R11: POSTE METALICO | S11: 18 | U11: 0 | V11: =IF(U11="","",IF(U11="TBD","TBD",IF(U11="N/A","N/A","W"&TEXT(WEEKNUM(U11,21),"00")&" "&YEAR(U11)))) -> W52 1900 | Y11: =IF(X11="","",IF(X11="TBD","TBD",IF(X11="N/A","N/A","W"&TEXT(WEEKNUM(X11,21),"00")&" "&YEAR(X11)))) | AB11: =+IF(Z11="",0,AA11-Z11) -> 0 | AC11: TSS No Recibido | AF11: =IF(AE11="","",IF(AE11="TBD","TBD",IF(AE11="N/A","N/A","W"&TEXT(WEEKNUM(AE11,21),"00")&" "&YEAR(AE11)))) | AG11: TSS No Recibido | AJ11: =IF(AI11="","",IF(AI11="TBD","TBD",IF(AI11="N/A","N/A","W"&TEXT(WEEKNUM(AI11,21),"00")&" "&YEAR(AI11)))) | AK11: TSS No Recibido | AN11: =IF(AM11="","",IF(AM11="TBD","TBD",IF(AM11="N/A","N/A","W"&TEXT(WEEKNUM(AM11,21),"00")&" "&YEAR(AM11)))) | AO11: TSS No Recibido | AR11: =IF(AQ11="","",IF(AQ11="TBD","TBD",IF(AQ11="N/A","N/A","W"&TEXT(WEEKNUM(AQ11,21),"00")&" "&YEAR(AQ11)))) | AX11: =IF(AW11="","",IF(AW11="TBD","TBD",IF(AW11="N/A","N/A","W"&TEXT(WEEKNUM(AW11,21),"00")&" "&YEAR(AW11)))) | AY11: TSS No Recibido 4G | AZ11: Pendiente FC | BA11: Contrato No Firmado | BE11: =IF(BD11="","",IF(BD11="TBD","TBD",IF(BD11="N/A","N/A","W"&TEXT(WEEKNUM(BD11,21),"00")&" "&YEAR(BD11)))) | BG11: =IF(BF11="","",IF(BF11="TBD","TBD",IF(BF11="N/A","N/A","W"&TEXT(WEEKNUM(BF11,21),"00")&" "&YEAR(BF11)))) | BH11: =+IF(BF11="",0,(BF11-BD11)) -> 0 | BI11: Ing No Recibida | BL11: =IF(BK11="","",IF(BK11="TBD","TBD",IF(BK11="N/A","N/A","W"&TEXT(WEEKNUM(BK11,21),"00")&" "&YEAR(BK11)))) | BM11: Ing No Recibida | BP11: =IF(BO11="","",IF(BO11="TBD","TBD",IF(BO11="N/A","N/A","W"&TEXT(WEEKNUM(BO11,21),"00")&" "&YEAR(BO11)))) | BQ11: Ing No Recibida | BT11: =IF(BS11="","",IF(BS11="TBD","TBD",IF(BS11="N/A","N/A","W"&TEXT(WEEKNUM(BS11,21),"00")&" "&YEAR(BS11)))) | BU11: Ing No Recibida | BX11: =IF(BW11="","",IF(BW11="TBD","TBD",IF(BW11="N/A","N/A","W"&TEXT(WEEKNUM(BW11,21),"00")&" "&YEAR(BW11)))) | BZ11: =IF(BY11="","",IF(BY11="TBD","TBD",IF(BY11="N/A","N/A","W"&TEXT(WEEKNUM(BY11,21),"00")&" "&YEAR(BY11)))) | CA11: Ing No Recibida 4G | CB11: 0 | CI11: =IF(CH11="","",IF(CH11="TBD","TBD",IF(CH11="N/A","N/A","W"&TEXT(WEEKNUM(CH11,21),"00")&" "&YEAR(CH11)))) | CK11: =IF(CJ11="","",IF(CJ11="TBD","TBD",IF(CJ11="N/A","N/A","W"&TEXT(WEEKNUM(CJ11,21),"00")&" "&YEAR(CJ11)))) | CL11: =+IF(CJ11="",0,(CJ11-CH11)) -> 0 | CM11: As Built No Recibido | CP11: =IF(CO11="","",IF(CO11="TBD","TBD",IF(CO11="N/A","N/A","W"&TEXT(WEEKNUM(CO11,21),"00")&" "&YEAR(CO11)))) | CQ11: As Built No Recibido | CT11: =IF(CS11="","",IF(CS11="TBD","TBD",IF(CS11="N/A","N/A","W"&TEXT(WEEKNUM(CS11,21),"00")&" "&YEAR(CS11)))) | CU11: As Built No Recibido | CX11: =IF(CW11="","",IF(CW11="TBD","TBD",IF(CW11="N/A","N/A","W"&TEXT(WEEKNUM(CW11,21),"00")&" "&YEAR(CW11)))) | CY11: As Built No Recibido | DB11: =IF(DA11="","",IF(DA11="TBD","TBD",IF(DA11="N/A","N/A","W"&TEXT(WEEKNUM(DA11,21),"00")&" "&YEAR(DA11)))) | DD11: =IF(DC11="","",IF(DC11="TBD","TBD",IF(DC11="N/A","N/A","W"&TEXT(WEEKNUM(DC11,21),"00")&" "&YEAR(DC11)))) | DE11: As Built No Recibido | DG11: Gabinete Huawei | DK11: MMOO | DL11: Pendiente | DQ11: Huawei | EB11: En Etapa de TSS 4G | EI11: 0 | EJ11: =K11&AY11&CA11&DE11&DT11&DW11 -> No VigenteTSS No Recibido 4GIng No Recibida 4GAs Built No Recibido
A12: =IFERROR(IF(VLOOKUP(B12,SEARCH!A:A,1,0)=B12,"OK",""),"") | B12: 29_027 | C12: Cajon El Olivillo | D12: 9 | E12: -38.680417 | F12: -72.842889 | G12: La Araucanía | H12: Vilcún | I12: Pasaje los Coigues frente casa 288 | J12: Fase 1 - On Hold RF | K12: No Vigente | L12: No aplica | M12: 12 | O12: 0 | P12: BTS | Q12: 5-2-2025 Se informa por RF que sitios salen de plan 2024 (Correo Delfos) | R12: POSTE METALICO | S12: 12 | U12: 0 | V12: =IF(U12="","",IF(U12="TBD","TBD",IF(U12="N/A","N/A","W"&TEXT(WEEKNUM(U12,21),"00")&" "&YEAR(U12)))) -> W52 1900 | Y12: =IF(X12="","",IF(X12="TBD","TBD",IF(X12="N/A","N/A","W"&TEXT(WEEKNUM(X12,21),"00")&" "&YEAR(X12)))) | AB12: =+IF(Z12="",0,AA12-Z12) -> 0 | AC12: TSS No Recibido | AF12: =IF(AE12="","",IF(AE12="TBD","TBD",IF(AE12="N/A","N/A","W"&TEXT(WEEKNUM(AE12,21),"00")&" "&YEAR(AE12)))) | AG12: TSS No Recibido | AJ12: =IF(AI12="","",IF(AI12="TBD","TBD",IF(AI12="N/A","N/A","W"&TEXT(WEEKNUM(AI12,21),"00")&" "&YEAR(AI12)))) | AK12: TSS No Recibido | AN12: =IF(AM12="","",IF(AM12="TBD","TBD",IF(AM12="N/A","N/A","W"&TEXT(WEEKNUM(AM12,21),"00")&" "&YEAR(AM12)))) | AO12: TSS No Recibido | AR12: =IF(AQ12="","",IF(AQ12="TBD","TBD",IF(AQ12="N/A","N/A","W"&TEXT(WEEKNUM(AQ12,21),"00")&" "&YEAR(AQ12)))) | AX12: =IF(AW12="","",IF(AW12="TBD","TBD",IF(AW12="N/A","N/A","W"&TEXT(WEEKNUM(AW12,21),"00")&" "&YEAR(AW12)))) | AY12: TSS No Recibido 4G | AZ12: Pendiente FC | BA12: Contrato No Firmado | BE12: =IF(BD12="","",IF(BD12="TBD","TBD",IF(BD12="N/A","N/A","W"&TEXT(WEEKNUM(BD12,21),"00")&" "&YEAR(BD12)))) | BG12: =IF(BF12="","",IF(BF12="TBD","TBD",IF(BF12="N/A","N/A","W"&TEXT(WEEKNUM(BF12,21),"00")&" "&YEAR(BF12)))) | BH12: =+IF(BF12="",0,(BF12-BD12)) -> 0 | BI12: Ing No Recibida | BL12: =IF(BK12="","",IF(BK12="TBD","TBD",IF(BK12="N/A","N/A","W"&TEXT(WEEKNUM(BK12,21),"00")&" "&YEAR(BK12)))) | BM12: Ing No Recibida | BP12: =IF(BO12="","",IF(BO12="TBD","TBD",IF(BO12="N/A","N/A","W"&TEXT(WEEKNUM(BO12,21),"00")&" "&YEAR(BO12)))) | BQ12: Ing No Recibida | BT12: =IF(BS12="","",IF(BS12="TBD","TBD",IF(BS12="N/A","N/A","W"&TEXT(WEEKNUM(BS12,21),"00")&" "&YEAR(BS12)))) | BU12: Ing No Recibida | BX12: =IF(BW12="","",IF(BW12="TBD","TBD",IF(BW12="N/A","N/A","W"&TEXT(WEEKNUM(BW12,21),"00")&" "&YEAR(BW12)))) | BZ12: =IF(BY12="","",IF(BY12="TBD","TBD",IF(BY12="N/A","N/A","W"&TEXT(WEEKNUM(BY12,21),"00")&" "&YEAR(BY12)))) | CA12: Ing No Recibida 4G | CB12: 0 | CI12: =IF(CH12="","",IF(CH12="TBD","TBD",IF(CH12="N/A","N/A","W"&TEXT(WEEKNUM(CH12,21),"00")&" "&YEAR(CH12)))) | CK12: =IF(CJ12="","",IF(CJ12="TBD","TBD",IF(CJ12="N/A","N/A","W"&TEXT(WEEKNUM(CJ12,21),"00")&" "&YEAR(CJ12)))) | CL12: =+IF(CJ12="",0,(CJ12-CH12)) -> 0 | CM12: As Built No Recibido | CP12: =IF(CO12="","",IF(CO12="TBD","TBD",IF(CO12="N/A","N/A","W"&TEXT(WEEKNUM(CO12,21),"00")&" "&YEAR(CO12)))) | CQ12: As Built No Recibido | CT12: =IF(CS12="","",IF(CS12="TBD","TBD",IF(CS12="N/A","N/A","W"&TEXT(WEEKNUM(CS12,21),"00")&" "&YEAR(CS12)))) | CU12: As Built No Recibido | CX12: =IF(CW12="","",IF(CW12="TBD","TBD",IF(CW12="N/A","N/A","W"&TEXT(WEEKNUM(CW12,21),"00")&" "&YEAR(CW12)))) | CY12: As Built No Recibido | DB12: =IF(DA12="","",IF(DA12="TBD","TBD",IF(DA12="N/A","N/A","W"&TEXT(WEEKNUM(DA12,21),"00")&" "&YEAR(DA12)))) | DD12: =IF(DC12="","",IF(DC12="TBD","TBD",IF(DC12="N/A","N/A","W"&TEXT(WEEKNUM(DC12,21),"00")&" "&YEAR(DC12)))) | DE12: As Built No Recibido | DG12: Gabinete Huawei | DK12: MMOO | DL12: Pendiente | DQ12: Huawei | EB12: En Etapa de TSS 4G | EI12: 0 | EJ12: =K12&AY12&CA12&DE12&DT12&DW12 -> No VigenteTSS No Recibido 4GIng No Recibida 4GAs Built No Recibido
A13: =IFERROR(IF(VLOOKUP(B13,SEARCH!A:A,1,0)=B13,"OK",""),"") | B13: EE_049 | C13: Comp FEMSA SALUD SPA | D13: 13 | E13: -33.417326 | F13: -70.667056 | G13: Metropolitana de Santiago | H13: INDEPENDENCIA | I13: Nueva Andres Bello 1940 Independencia | J13: Indoor | K13: No Vigente | L13: No aplica | O13: 0 | P13: 0 | R13: Indoor - B2B | V13: =IF(U13="","",IF(U13="TBD","TBD",IF(U13="N/A","N/A","W"&TEXT(WEEKNUM(U13,21),"00")&" "&YEAR(U13)))) | Y13: =IF(X13="","",IF(X13="TBD","TBD",IF(X13="N/A","N/A","W"&TEXT(WEEKNUM(X13,21),"00")&" "&YEAR(X13)))) | AB13: =+IF(Z13="",0,AA13-Z13) -> 0 | AC13: TSS No Recibido | AF13: =IF(AE13="","",IF(AE13="TBD","TBD",IF(AE13="N/A","N/A","W"&TEXT(WEEKNUM(AE13,21),"00")&" "&YEAR(AE13)))) | AG13: TSS No Recibido | AJ13: =IF(AI13="","",IF(AI13="TBD","TBD",IF(AI13="N/A","N/A","W"&TEXT(WEEKNUM(AI13,21),"00")&" "&YEAR(AI13)))) | AK13: TSS No Recibido | AN13: =IF(AM13="","",IF(AM13="TBD","TBD",IF(AM13="N/A","N/A","W"&TEXT(WEEKNUM(AM13,21),"00")&" "&YEAR(AM13)))) | AO13: TSS No Recibido | AR13: =IF(AQ13="","",IF(AQ13="TBD","TBD",IF(AQ13="N/A","N/A","W"&TEXT(WEEKNUM(AQ13,21),"00")&" "&YEAR(AQ13)))) | AX13: =IF(AW13="","",IF(AW13="TBD","TBD",IF(AW13="N/A","N/A","W"&TEXT(WEEKNUM(AW13,21),"00")&" "&YEAR(AW13)))) | AY13: TSS No Recibido 4G | AZ13: Pendiente FC | BA13: Contrato No Firmado | BE13: =IF(BD13="","",IF(BD13="TBD","TBD",IF(BD13="N/A","N/A","W"&TEXT(WEEKNUM(BD13,21),"00")&" "&YEAR(BD13)))) | BG13: =IF(BF13="","",IF(BF13="TBD","TBD",IF(BF13="N/A","N/A","W"&TEXT(WEEKNUM(BF13,21),"00")&" "&YEAR(BF13)))) | BH13: =+IF(BF13="",0,(BF13-BD13)) -> 0 | BI13: Ing No Recibida | BL13: =IF(BK13="","",IF(BK13="TBD","TBD",IF(BK13="N/A","N/A","W"&TEXT(WEEKNUM(BK13,21),"00")&" "&YEAR(BK13)))) | BM13: Ing No Recibida | BP13: =IF(BO13="","",IF(BO13="TBD","TBD",IF(BO13="N/A","N/A","W"&TEXT(WEEKNUM(BO13,21),"00")&" "&YEAR(BO13)))) | BQ13: Ing No Recibida | BT13: =IF(BS13="","",IF(BS13="TBD","TBD",IF(BS13="N/A","N/A","W"&TEXT(WEEKNUM(BS13,21),"00")&" "&YEAR(BS13)))) | BU13: Ing No Recibida | BX13: =IF(BW13="","",IF(BW13="TBD","TBD",IF(BW13="N/A","N/A","W"&TEXT(WEEKNUM(BW13,21),"00")&" "&YEAR(BW13)))) | BZ13: =IF(BY13="","",IF(BY13="TBD","TBD",IF(BY13="N/A","N/A","W"&TEXT(WEEKNUM(BY13,21),"00")&" "&YEAR(BY13)))) | CA13: Ing No Recibida 4G | CB13: 0 | CI13: =IF(CH13="","",IF(CH13="TBD","TBD",IF(CH13="N/A","N/A","W"&TEXT(WEEKNUM(CH13,21),"00")&" "&YEAR(CH13)))) | CK13: =IF(CJ13="","",IF(CJ13="TBD","TBD",IF(CJ13="N/A","N/A","W"&TEXT(WEEKNUM(CJ13,21),"00")&" "&YEAR(CJ13)))) | CL13: =+IF(CJ13="",0,(CJ13-CH13)) -> 0 | CM13: As Built No Recibido | CP13: =IF(CO13="","",IF(CO13="TBD","TBD",IF(CO13="N/A","N/A","W"&TEXT(WEEKNUM(CO13,21),"00")&" "&YEAR(CO13)))) | CQ13: As Built No Recibido | CT13: =IF(CS13="","",IF(CS13="TBD","TBD",IF(CS13="N/A","N/A","W"&TEXT(WEEKNUM(CS13,21),"00")&" "&YEAR(CS13)))) | CU13: As Built No Recibido | CX13: =IF(CW13="","",IF(CW13="TBD","TBD",IF(CW13="N/A","N/A","W"&TEXT(WEEKNUM(CW13,21),"00")&" "&YEAR(CW13)))) | CY13: As Built No Recibido | DB13: =IF(DA13="","",IF(DA13="TBD","TBD",IF(DA13="N/A","N/A","W"&TEXT(WEEKNUM(DA13,21),"00")&" "&YEAR(DA13)))) | DD13: =IF(DC13="","",IF(DC13="TBD","TBD",IF(DC13="N/A","N/A","W"&TEXT(WEEKNUM(DC13,21),"00")&" "&YEAR(DC13)))) | DE13: As Built No Recibido | DG13: Por Definir | DK13: TBD | DL13: Pendiente | DQ13: ZTE | DY13: 0 | DZ13: 0 | EA13: 0 | EB13: En Etapa de TSS 4G | EI13: 0 | EJ13: =K13&AY13&CA13&DE13&DT13&DW13 -> No VigenteTSS No Recibido 4GIng No Recibida 4GAs Built No Recibido
A14: =IFERROR(IF(VLOOKUP(B14,SEARCH!A:A,1,0)=B14,"OK",""),"") | B14: 33i_968 | C14: Difarma Independencia | D14: 13 | E14: -33.417363 | F14: -70.667033 | G14: Metropolitana de Santiago | H14: INDEPENDENCIA | I14: Nueva Andres Bello 1940 | J14: Indoor | K14: No Vigente | O14: 0 | P14: 0 | R14: Indoor - B2B | U14: 0 | V14: =IF(U14="","",IF(U14="TBD","TBD",IF(U14="N/A","N/A","W"&TEXT(WEEKNUM(U14,21),"00")&" "&YEAR(U14)))) -> W52 1900 | Y14: =IF(X14="","",IF(X14="TBD","TBD",IF(X14="N/A","N/A","W"&TEXT(WEEKNUM(X14,21),"00")&" "&YEAR(X14)))) | AB14: =+IF(Z14="",0,AA14-Z14) -> 0 | AC14: TSS No Recibido | AF14: =IF(AE14="","",IF(AE14="TBD","TBD",IF(AE14="N/A","N/A","W"&TEXT(WEEKNUM(AE14,21),"00")&" "&YEAR(AE14)))) | AG14: TSS No Recibido | AJ14: =IF(AI14="","",IF(AI14="TBD","TBD",IF(AI14="N/A","N/A","W"&TEXT(WEEKNUM(AI14,21),"00")&" "&YEAR(AI14)))) | AK14: TSS No Recibido | AN14: =IF(AM14="","",IF(AM14="TBD","TBD",IF(AM14="N/A","N/A","W"&TEXT(WEEKNUM(AM14,21),"00")&" "&YEAR(AM14)))) | AO14: TSS No Recibido | AR14: =IF(AQ14="","",IF(AQ14="TBD","TBD",IF(AQ14="N/A","N/A","W"&TEXT(WEEKNUM(AQ14,21),"00")&" "&YEAR(AQ14)))) | AX14: =IF(AW14="","",IF(AW14="TBD","TBD",IF(AW14="N/A","N/A","W"&TEXT(WEEKNUM(AW14,21),"00")&" "&YEAR(AW14)))) | AY14: TSS No Recibido 4G | AZ14: Pendiente FC | BA14: Contrato No Firmado | BE14: =IF(BD14="","",IF(BD14="TBD","TBD",IF(BD14="N/A","N/A","W"&TEXT(WEEKNUM(BD14,21),"00")&" "&YEAR(BD14)))) | BG14: =IF(BF14="","",IF(BF14="TBD","TBD",IF(BF14="N/A","N/A","W"&TEXT(WEEKNUM(BF14,21),"00")&" "&YEAR(BF14)))) | BH14: =+IF(BF14="",0,(BF14-BD14)) -> 0 | BI14: Ing No Recibida | BL14: =IF(BK14="","",IF(BK14="TBD","TBD",IF(BK14="N/A","N/A","W"&TEXT(WEEKNUM(BK14,21),"00")&" "&YEAR(BK14)))) | BM14: Ing No Recibida | BP14: =IF(BO14="","",IF(BO14="TBD","TBD",IF(BO14="N/A","N/A","W"&TEXT(WEEKNUM(BO14,21),"00")&" "&YEAR(BO14)))) | BQ14: Ing No Recibida | BT14: =IF(BS14="","",IF(BS14="TBD","TBD",IF(BS14="N/A","N/A","W"&TEXT(WEEKNUM(BS14,21),"00")&" "&YEAR(BS14)))) | BU14: Ing No Recibida | BX14: =IF(BW14="","",IF(BW14="TBD","TBD",IF(BW14="N/A","N/A","W"&TEXT(WEEKNUM(BW14,21),"00")&" "&YEAR(BW14)))) | BZ14: =IF(BY14="","",IF(BY14="TBD","TBD",IF(BY14="N/A","N/A","W"&TEXT(WEEKNUM(BY14,21),"00")&" "&YEAR(BY14)))) | CA14: Ing No Recibida 4G | CB14: 0 | CI14: =IF(CH14="","",IF(CH14="TBD","TBD",IF(CH14="N/A","N/A","W"&TEXT(WEEKNUM(CH14,21),"00")&" "&YEAR(CH14)))) | CK14: =IF(CJ14="","",IF(CJ14="TBD","TBD",IF(CJ14="N/A","N/A","W"&TEXT(WEEKNUM(CJ14,21),"00")&" "&YEAR(CJ14)))) | CL14: =+IF(CJ14="",0,(CJ14-CH14)) -> 0 | CM14: As Built No Recibido | CP14: =IF(CO14="","",IF(CO14="TBD","TBD",IF(CO14="N/A","N/A","W"&TEXT(WEEKNUM(CO14,21),"00")&" "&YEAR(CO14)))) | CQ14: As Built No Recibido | CT14: =IF(CS14="","",IF(CS14="TBD","TBD",IF(CS14="N/A","N/A","W"&TEXT(WEEKNUM(CS14,21),"00")&" "&YEAR(CS14)))) | CU14: As Built No Recibido | CX14: =IF(CW14="","",IF(CW14="TBD","TBD",IF(CW14="N/A","N/A","W"&TEXT(WEEKNUM(CW14,21),"00")&" "&YEAR(CW14)))) | CY14: As Built No Recibido | DB14: =IF(DA14="","",IF(DA14="TBD","TBD",IF(DA14="N/A","N/A","W"&TEXT(WEEKNUM(DA14,21),"00")&" "&YEAR(DA14)))) | DD14: =IF(DC14="","",IF(DC14="TBD","TBD",IF(DC14="N/A","N/A","W"&TEXT(WEEKNUM(DC14,21),"00")&" "&YEAR(DC14)))) | DE14: As Built No Recibido | DG14: Por Definir | DK14: TBD | DL14: Pendiente | EB14: En Etapa de TSS 4G | EI14: 0 | EJ14: =K14&AY14&CA14&DE14&DT14&DW14 -> No VigenteTSS No Recibido 4GIng No Recibida 4GAs Built No Recibido
A15: =IFERROR(IF(VLOOKUP(B15,SEARCH!A:A,1,0)=B15,"OK",""),"") | B15: 53_394 | C15: Aeropuerto Santiago - Pista de Aterrizaje | D15: 13 | E15: -33.3822 | F15: -70.798 | G15: Metropolitana de Santiago | H15: SANTIAGO | I15: 0 | J15: Indoor | K15: No Vigente | O15: 0 | P15: 0 | Q15: Correo Delfos 8-4-2025: Informa que sitios salen de plan 290. Se pide formalizar con Inmobiliaria esta gestión | R15: Indoor - B2C | U15: 0 | V15: =IF(U15="","",IF(U15="TBD","TBD",IF(U15="N/A","N/A","W"&TEXT(WEEKNUM(U15,21),"00")&" "&YEAR(U15)))) -> W52 1900 | Y15: =IF(X15="","",IF(X15="TBD","TBD",IF(X15="N/A","N/A","W"&TEXT(WEEKNUM(X15,21),"00")&" "&YEAR(X15)))) | AB15: =+IF(Z15="",0,AA15-Z15) -> 0 | AC15: TSS No Recibido | AF15: =IF(AE15="","",IF(AE15="TBD","TBD",IF(AE15="N/A","N/A","W"&TEXT(WEEKNUM(AE15,21),"00")&" "&YEAR(AE15)))) | AG15: TSS No Recibido | AJ15: =IF(AI15="","",IF(AI15="TBD","TBD",IF(AI15="N/A","N/A","W"&TEXT(WEEKNUM(AI15,21),"00")&" "&YEAR(AI15)))) | AK15: TSS No Recibido | AN15: =IF(AM15="","",IF(AM15="TBD","TBD",IF(AM15="N/A","N/A","W"&TEXT(WEEKNUM(AM15,21),"00")&" "&YEAR(AM15)))) | AO15: TSS No Recibido | AR15: =IF(AQ15="","",IF(AQ15="TBD","TBD",IF(AQ15="N/A","N/A","W"&TEXT(WEEKNUM(AQ15,21),"00")&" "&YEAR(AQ15)))) | AX15: =IF(AW15="","",IF(AW15="TBD","TBD",IF(AW15="N/A","N/A","W"&TEXT(WEEKNUM(AW15,21),"00")&" "&YEAR(AW15)))) | AY15: TSS No Recibido 4G | AZ15: Pendiente FC | BA15: Contrato No Firmado | BE15: =IF(BD15="","",IF(BD15="TBD","TBD",IF(BD15="N/A","N/A","W"&TEXT(WEEKNUM(BD15,21),"00")&" "&YEAR(BD15)))) | BG15: =IF(BF15="","",IF(BF15="TBD","TBD",IF(BF15="N/A","N/A","W"&TEXT(WEEKNUM(BF15,21),"00")&" "&YEAR(BF15)))) | BH15: =+IF(BF15="",0,(BF15-BD15)) -> 0 | BI15: Ing No Recibida | BL15: =IF(BK15="","",IF(BK15="TBD","TBD",IF(BK15="N/A","N/A","W"&TEXT(WEEKNUM(BK15,21),"00")&" "&YEAR(BK15)))) | BM15: Ing No Recibida | BP15: =IF(BO15="","",IF(BO15="TBD","TBD",IF(BO15="N/A","N/A","W"&TEXT(WEEKNUM(BO15,21),"00")&" "&YEAR(BO15)))) | BQ15: Ing No Recibida | BT15: =IF(BS15="","",IF(BS15="TBD","TBD",IF(BS15="N/A","N/A","W"&TEXT(WEEKNUM(BS15,21),"00")&" "&YEAR(BS15)))) | BU15: Ing No Recibida | BX15: =IF(BW15="","",IF(BW15="TBD","TBD",IF(BW15="N/A","N/A","W"&TEXT(WEEKNUM(BW15,21),"00")&" "&YEAR(BW15)))) | BZ15: =IF(BY15="","",IF(BY15="TBD","TBD",IF(BY15="N/A","N/A","W"&TEXT(WEEKNUM(BY15,21),"00")&" "&YEAR(BY15)))) | CA15: Ing No Recibida 4G | CB15: 0 | CI15: =IF(CH15="","",IF(CH15="TBD","TBD",IF(CH15="N/A","N/A","W"&TEXT(WEEKNUM(CH15,21),"00")&" "&YEAR(CH15)))) | CK15: =IF(CJ15="","",IF(CJ15="TBD","TBD",IF(CJ15="N/A","N/A","W"&TEXT(WEEKNUM(CJ15,21),"00")&" "&YEAR(CJ15)))) | CL15: =+IF(CJ15="",0,(CJ15-CH15)) -> 0 | CM15: As Built No Recibido | CP15: =IF(CO15="","",IF(CO15="TBD","TBD",IF(CO15="N/A","N/A","W"&TEXT(WEEKNUM(CO15,21),"00")&" "&YEAR(CO15)))) | CQ15: As Built No Recibido | CT15: =IF(CS15="","",IF(CS15="TBD","TBD",IF(CS15="N/A","N/A","W"&TEXT(WEEKNUM(CS15,21),"00")&" "&YEAR(CS15)))) | CU15: As Built No Recibido | CX15: =IF(CW15="","",IF(CW15="TBD","TBD",IF(CW15="N/A","N/A","W"&TEXT(WEEKNUM(CW15,21),"00")&" "&YEAR(CW15)))) | CY15: As Built No Recibido | DB15: =IF(DA15="","",IF(DA15="TBD","TBD",IF(DA15="N/A","N/A","W"&TEXT(WEEKNUM(DA15,21),"00")&" "&YEAR(DA15)))) | DD15: =IF(DC15="","",IF(DC15="TBD","TBD",IF(DC15="N/A","N/A","W"&TEXT(WEEKNUM(DC15,21),"00")&" "&YEAR(DC15)))) | DE15: As Built No Recibido | DG15: Por Definir | DK15: TBD | DL15: Pendiente | EB15: En Etapa de TSS 4G | EI15: 0 | EJ15: =K15&AY15&CA15&DE15&DT15&DW15 -> No VigenteTSS No Recibido 4GIng No Recibida 4GAs Built No Recibido
A16: =IFERROR(IF(VLOOKUP(B16,SEARCH!A:A,1,0)=B16,"OK",""),"") | B16: 23_790 | C16: Barrio Industrial de Quilicura | D16: 13 | E16: -33.326931 | F16: -70.717026 | G16: Metropolitana de Santiago | H16: Quilicura | I16: Eduardo Frei Montalva 9951 | J16: Fase 2 | K16: Vigente | L16: No aplica | M16: Sitio Recibido | O16: ANTYL | P16: 0 | R16: MONOPOSTE | S16: 14 | T16: ANT230_13 | U16: 45527 | V16: =IF(U16="","",IF(U16="TBD","TBD",IF(U16="N/A","N/A","W"&TEXT(WEEKNUM(U16,21),"00")&" "&YEAR(U16)))) -> W34 2024 | W16: 45531 | Y16: =IF(X16="","",IF(X16="TBD","TBD",IF(X16="N/A","N/A","W"&TEXT(WEEKNUM(X16,21),"00")&" "&YEAR(X16)))) | Z16: 45531 | AA16: 45534 | AB16: =+IF(Z16="",0,AA16-Z16) -> 3 | AC16: TSS Aprobado | AE16: 45534 | AF16: =IF(AE16="","",IF(AE16="TBD","TBD",IF(AE16="N/A","N/A","W"&TEXT(WEEKNUM(AE16,21),"00")&" "&YEAR(AE16)))) -> W35 2024 | AG16: TSS Aprobado | AH16: Rev.2 09-09: Aprobado 1. Area en piso: 3x2m 2. Soporte RF: 3 soportes H. | AI16: 45544 | AJ16: =IF(AI16="","",IF(AI16="TBD","TBD",IF(AI16="N/A","N/A","W"&TEXT(WEEKNUM(AI16,21),"00")&" "&YEAR(AI16)))) -> W37 2024 | AK16: TSS Aprobado | AL16: Distribución de equipos se verificará en ingenieria. | AM16: 45544 | AN16: =IF(AM16="","",IF(AM16="TBD","TBD",IF(AM16="N/A","N/A","W"&TEXT(WEEKNUM(AM16,21),"00")&" "&YEAR(AM16)))) -> W37 2024 | AO16: TSS Aprobado | AQ16: 45545 | AR16: =IF(AQ16="","",IF(AQ16="TBD","TBD",IF(AQ16="N/A","N/A","W"&TEXT(WEEKNUM(AQ16,21),"00")&" "&YEAR(AQ16)))) -> W37 2024 | AW16: 45545 | AX16: =IF(AW16="","",IF(AW16="TBD","TBD",IF(AW16="N/A","N/A","W"&TEXT(WEEKNUM(AW16,21),"00")&" "&YEAR(AW16)))) -> W37 2024 | AY16: TSS Aprobado 4G | AZ16: FC Enviado a OOII | BA16: Contrato Firmado | BB16: 45588 | BC16: 45607 | BD16: 45608 | BE16: =IF(BD16="","",IF(BD16="TBD","TBD",IF(BD16="N/A","N/A","W"&TEXT(WEEKNUM(BD16,21),"00")&" "&YEAR(BD16)))) -> W46 2024 | BF16: 45610 | BG16: =IF(BF16="","",IF(BF16="TBD","TBD",IF(BF16="N/A","N/A","W"&TEXT(WEEKNUM(BF16,21),"00")&" "&YEAR(BF16)))) -> W46 2024 | BH16: =+IF(BF16="",0,(BF16-BD16)) -> 2 | BI16: Ing Aprobada | BJ16: 21-11: Aprobado Se levantan las observaciones indicadas en revisiones anteriores. 13-11: Observado 1. Si se va a destinar los soportes de RF para instalar la MMOO, 1 de estos debe ser de 3", ya que el diametro minimo solicitado por el equipo de ing. MMOO es de 3" y maximo 4". | BK16: 45617 | BL16: =IF(BK16="","",IF(BK16="TBD","TBD",IF(BK16="N/A","N/A","W"&TEXT(WEEKNUM(BK16,21),"00")&" "&YEAR(BK16)))) -> W47 2024 | BM16: Ing Aprobada | BN16: 08/11: Observaciones corregidas a nivel de RF, solo aclarar porque no se considerar 2 soporte x sector | BO16: 45604 | BP16: =IF(BO16="","",IF(BO16="TBD","TBD",IF(BO16="N/A","N/A","W"&TEXT(WEEKNUM(BO16,21),"00")&" "&YEAR(BO16)))) -> W45 2024 | BQ16: Ing Aprobada | BR16: 08-11-2024: Observado V3 - Soporte MMOO: Proyectado: NO-OK - Dimensiones soporte MMOO: L=1 : D=4": NO-OK | BS16: 45629 | BT16: =IF(BS16="","",IF(BS16="TBD","TBD",IF(BS16="N/A","N/A","W"&TEXT(WEEKNUM(BS16,21),"00")&" "&YEAR(BS16)))) -> W49 2024 | BU16: Ing Aprobada | BV16: REV2 24-10-2024 Área proyectada 3x2 mts Empalme aéreo trifásico independiente proyectado desde poste referencia # 728180 Acometida eléctrica aérea trifásica proyectada ( L=5 mts ) Línea eléctrica subterránea proyectada (L=40 mts) (6AWG) TDAyF + Medidor Trifásico Proyectado Tierra proyectada (Conexión a malla existente) | BW16: 45589 | BX16: =IF(BW16="","",IF(BW16="TBD","TBD",IF(BW16="N/A","N/A","W"&TEXT(WEEKNUM(BW16,21),"00")&" "&YEAR(BW16)))) -> W43 2024 | BY16: 45629 | BZ16: =IF(BY16="","",IF(BY16="TBD","TBD",IF(BY16="N/A","N/A","W"&TEXT(WEEKNUM(BY16,21),"00")&" "&YEAR(BY16)))) -> W49 2024 | CA16: Ing Aprobada 4G | CB16: Finalizadas | CC16: Finalizadas | CD16: Sin Energía Provisoria | CE16: Si | CF16: 45714 | CG16: 45744 | CH16: 45727 | CI16: =IF(CH16="","",IF(CH16="TBD","TBD",IF(CH16="N/A","N/A","W"&TEXT(WEEKNUM(CH16,21),"00")&" "&YEAR(CH16)))) -> W11 2025 | CJ16: 45730 | CK16: =IF(CJ16="","",IF(CJ16="TBD","TBD",IF(CJ16="N/A","N/A","W"&TEXT(WEEKNUM(CJ16,21),"00")&" "&YEAR(CJ16)))) -> W11 2025 | CL16: =+IF(CJ16="",0,(CJ16-CH16)) -> 3 | CM16: As Built Aprobado | CN16: 0 | CO16: 45747 | CP16: =IF(CO16="","",IF(CO16="TBD","TBD",IF(CO16="N/A","N/A","W"&TEXT(WEEKNUM(CO16,21),"00")&" "&YEAR(CO16)))) -> W14 2025 | CQ16: As Built Aprobado | CS16: 45756 | CT16: =IF(CS16="","",IF(CS16="TBD","TBD",IF(CS16="N/A","N/A","W"&TEXT(WEEKNUM(CS16,21),"00")&" "&YEAR(CS16)))) -> W15 2025 | CU16: As Built Aprobado | CW16: 45747 | CX16: =IF(CW16="","",IF(CW16="TBD","TBD",IF(CW16="N/A","N/A","W"&TEXT(WEEKNUM(CW16,21),"00")&" "&YEAR(CW16)))) -> W14 2025 | CY16: As Built Aprobado | DA16: 45747 | DB16: =IF(DA16="","",IF(DA16="TBD","TBD",IF(DA16="N/A","N/A","W"&TEXT(WEEKNUM(DA16,21),"00")&" "&YEAR(DA16)))) -> W14 2025 | DC16: 45756 | DD16: =IF(DC16="","",IF(DC16="TBD","TBD",IF(DC16="N/A","N/A","W"&TEXT(WEEKNUM(DC16,21),"00")&" "&YEAR(DC16)))) -> W15 2025 | DE16: As Built Aprobado 4G | DF16: 45769 | DG16: Gabinete Huawei | DK16: FO | DL16: ODF Instalado | DN16: 45833 | DO16: 45833 | DQ16: ZTE | DV16: 45848 | DW16: On Air | EB16: On Air 4G | ED16: Plan 2025 | EI16: 0 | EJ16: =K16&AY16&CA16&DE16&DT16&DW16 -> VigenteTSS Aprobado 4GIng Aprobada 4GAs Built Aprobado 4GOn Air
A17: =IFERROR(IF(VLOOKUP(B17,SEARCH!A:A,1,0)=B17,"OK",""),"") | B17: 25_214 | C17: Isla Negra | D17: 5 | E17: -33.427078 | F17: -71.688067 | G17: Valparaíso | I17: Pendiente TSS | J17: No Vigente | K17: No Vigente | L17: No aplica | O17: ANTYL | P17: BTS | R17: POSTE METALICO | S17: #N/A | T17: PENDIENTE | U17: 45161 | V17: =IF(U17="","",IF(U17="TBD","TBD",IF(U17="N/A","N/A","W"&TEXT(WEEKNUM(U17,21),"00")&" "&YEAR(U17)))) -> W34 2023 | Y17: =IF(X17="","",IF(X17="TBD","TBD",IF(X17="N/A","N/A","W"&TEXT(WEEKNUM(X17,21),"00")&" "&YEAR(X17)))) | AB17: =+IF(Z17="",0,AA17-Z17) -> 0 | AC17: TSS No Recibido | AD17: 0 | AF17: =IF(AE17="","",IF(AE17="TBD","TBD",IF(AE17="N/A","N/A","W"&TEXT(WEEKNUM(AE17,21),"00")&" "&YEAR(AE17)))) | AG17: TSS No Recibido | AJ17: =IF(AI17="","",IF(AI17="TBD","TBD",IF(AI17="N/A","N/A","W"&TEXT(WEEKNUM(AI17,21),"00")&" "&YEAR(AI17)))) | AK17: TSS No Recibido | AN17: =IF(AM17="","",IF(AM17="TBD","TBD",IF(AM17="N/A","N/A","W"&TEXT(WEEKNUM(AM17,21),"00")&" "&YEAR(AM17)))) | AO17: TSS No Recibido | AR17: =IF(AQ17="","",IF(AQ17="TBD","TBD",IF(AQ17="N/A","N/A","W"&TEXT(WEEKNUM(AQ17,21),"00")&" "&YEAR(AQ17)))) | AX17: =IF(AW17="","",IF(AW17="TBD","TBD",IF(AW17="N/A","N/A","W"&TEXT(WEEKNUM(AW17,21),"00")&" "&YEAR(AW17)))) | AY17: TSS No Recibido 4G | AZ17: FC Enviado a OOII | BA17: Contrato No Firmado | BE17: =IF(BD17="","",IF(BD17="TBD","TBD",IF(BD17="N/A","N/A","W"&TEXT(WEEKNUM(BD17,21),"00")&" "&YEAR(BD17)))) | BG17: =IF(BF17="","",IF(BF17="TBD","TBD",IF(BF17="N/A","N/A","W"&TEXT(WEEKNUM(BF17,21),"00")&" "&YEAR(BF17)))) | BH17: =+IF(BF17="",0,(BF17-BD17)) -> 0 | BI17: Ing No Recibida | BL17: =IF(BK17="","",IF(BK17="TBD","TBD",IF(BK17="N/A","N/A","W"&TEXT(WEEKNUM(BK17,21),"00")&" "&YEAR(BK17)))) | BM17: Ing No Recibida | BP17: =IF(BO17="","",IF(BO17="TBD","TBD",IF(BO17="N/A","N/A","W"&TEXT(WEEKNUM(BO17,21),"00")&" "&YEAR(BO17)))) | BQ17: Ing No Recibida | BT17: =IF(BS17="","",IF(BS17="TBD","TBD",IF(BS17="N/A","N/A","W"&TEXT(WEEKNUM(BS17,21),"00")&" "&YEAR(BS17)))) | BU17: Ing No Recibida | BX17: =IF(BW17="","",IF(BW17="TBD","TBD",IF(BW17="N/A","N/A","W"&TEXT(WEEKNUM(BW17,21),"00")&" "&YEAR(BW17)))) | BZ17: =IF(BY17="","",IF(BY17="TBD","TBD",IF(BY17="N/A","N/A","W"&TEXT(WEEKNUM(BY17,21),"00")&" "&YEAR(BY17)))) | CA17: Ing No Recibida 4G | CB17: No Iniciadas | CC17: No iniciadas | CI17: =IF(CH17="","",IF(CH17="TBD","TBD",IF(CH17="N/A","N/A","W"&TEXT(WEEKNUM(CH17,21),"00")&" "&YEAR(CH17)))) | CK17: =IF(CJ17="","",IF(CJ17="TBD","TBD",IF(CJ17="N/A","N/A","W"&TEXT(WEEKNUM(CJ17,21),"00")&" "&YEAR(CJ17)))) | CL17: =+IF(CJ17="",0,(CJ17-CH17)) -> 0 | CM17: As Built No Recibido | CP17: =IF(CO17="","",IF(CO17="TBD","TBD",IF(CO17="N/A","N/A","W"&TEXT(WEEKNUM(CO17,21),"00")&" "&YEAR(CO17)))) | CQ17: As Built No Recibido | CT17: =IF(CS17="","",IF(CS17="TBD","TBD",IF(CS17="N/A","N/A","W"&TEXT(WEEKNUM(CS17,21),"00")&" "&YEAR(CS17)))) | CU17: As Built No Recibido | CX17: =IF(CW17="","",IF(CW17="TBD","TBD",IF(CW17="N/A","N/A","W"&TEXT(WEEKNUM(CW17,21),"00")&" "&YEAR(CW17)))) | CY17: As Built No Recibido | DB17: =IF(DA17="","",IF(DA17="TBD","TBD",IF(DA17="N/A","N/A","W"&TEXT(WEEKNUM(DA17,21),"00")&" "&YEAR(DA17)))) | DD17: =IF(DC17="","",IF(DC17="TBD","TBD",IF(DC17="N/A","N/A","W"&TEXT(WEEKNUM(DC17,21),"00")&" "&YEAR(DC17)))) | DE17: As Built No Recibido | DG17: Gabinete Huawei | DK17: FO | DL17: Pendiente | DQ17: ZTE | EB17: En Etapa de TSS 4G | EI17: 0 | EJ17: =K17&AY17&CA17&DE17&DT17&DW17 -> No VigenteTSS No Recibido 4GIng No Recibida 4GAs Built No Recibido
A18: =IFERROR(IF(VLOOKUP(B18,SEARCH!A:A,1,0)=B18,"OK",""),"") | B18: 06_379 | C18: San Fuentes | D18: 6 | E18: -34.191167 | F18: -70.678194 | G18: Libertador General Bernardo O'Higgins | H18: Machalí | I18: Av. Alto Palermo N° 1807, Condominio Los Poleros, a un costado del acceo principal | J18: Plan 2025-2026 | K18: Vigente | L18: No aplica | M18: 46264 | O18: ANTYL | P18: COLO | R18: MONOPOSTE | S18: 25 | T18: CL-01-06-02632-23 | U18: 45106 | V18: =IF(U18="","",IF(U18="TBD","TBD",IF(U18="N/A","N/A","W"&TEXT(WEEKNUM(U18,21),"00")&" "&YEAR(U18)))) -> W26 2023 | W18: 45636 | Y18: =IF(X18="","",IF(X18="TBD","TBD",IF(X18="N/A","N/A","W"&TEXT(WEEKNUM(X18,21),"00")&" "&YEAR(X18)))) | Z18: 45160 | AA18: 45163 | AB18: =+IF(Z18="",0,AA18-Z18) -> 3 | AC18: TSS Aprobado | AD18: Se valida considerando la condición de corte de los árboles indiciado en TSS según lo cordado, esto debe quedar especificados en contrato | AE18: 45673 | AF18: =IF(AE18="","",IF(AE18="TBD","TBD",IF(AE18="N/A","N/A","W"&TEXT(WEEKNUM(AE18,21),"00")&" "&YEAR(AE18)))) -> W03 2025 | AG18: TSS Aprobado | AH18: 17-01: Aprobado 1. Area en piso 3x2m. 2. 6 Soportes simples de L: 4m. 3. Canalización a sistema radiante se verificará en proyecto de ingenieria | AI18: 45674 | AJ18: =IF(AI18="","",IF(AI18="TBD","TBD",IF(AI18="N/A","N/A","W"&TEXT(WEEKNUM(AI18,21),"00")&" "&YEAR(AI18)))) -> W03 2025 | AK18: TSS Aprobado | AL18: 17-01-2025: APROBADO V1. - Monoposte (Palmera). - Radier 3x2m. - (6) Soportes Simples de L=4m: SI-OK (Planos) (3) Antena HUAWEI AQU4518R24V18 (3) RRU 5513 (2) 2 RRU 5512 TX= FO / ROUTER=HUAWEI | AM18: 45674 | AN18: =IF(AM18="","",IF(AM18="TBD","TBD",IF(AM18="N/A","N/A","W"&TEXT(WEEKNUM(AM18,21),"00")&" "&YEAR(AM18)))) -> W03 2025 | AO18: TSS Aprobado | AP18: REV3 20-01-2025 Sitio Macro proyectado Área proyectada 3x2 mts Empalme Trifásico BT proyectado dese poste referencia # 849163 (Sujeto a factibilidad de compañía) Acometida aérea proyectada L=35 mts app Linea eléctrica aérea trifásica proyectada L=90mts app | AQ18: 45677 | AR18: =IF(AQ18="","",IF(AQ18="TBD","TBD",IF(AQ18="N/A","N/A","W"&TEXT(WEEKNUM(AQ18,21),"00")&" "&YEAR(AQ18)))) -> W04 2025 | AW18: 45677 | AX18: =IF(AW18="","",IF(AW18="TBD","TBD",IF(AW18="N/A","N/A","W"&TEXT(WEEKNUM(AW18,21),"00")&" "&YEAR(AW18)))) -> W04 2025 | AY18: TSS Aprobado 4G | AZ18: FC Enviado a OOII | BA18: Contrato Firmado | BB18: 45882 | BC18: 45930 | BD18: 45930 | BE18: =IF(BD18="","",IF(BD18="TBD","TBD",IF(BD18="N/A","N/A","W"&TEXT(WEEKNUM(BD18,21),"00")&" "&YEAR(BD18)))) -> W40 2025 | BF18: 45933 | BG18: =IF(BF18="","",IF(BF18="TBD","TBD",IF(BF18="N/A","N/A","W"&TEXT(WEEKNUM(BF18,21),"00")&" "&YEAR(BF18)))) -> W40 2025 | BH18: =+IF(BF18="",0,(BF18-BD18)) -> 3 | BI18: Ing Aprobada | BK18: 45931 | BL18: =IF(BK18="","",IF(BK18="TBD","TBD",IF(BK18="N/A","N/A","W"&TEXT(WEEKNUM(BK18,21),"00")&" "&YEAR(BK18)))) -> W40 2025 | BM18: Ing Aprobada | BN18: Se valida considerando la condición de corte de los árboles indicado en TSS según lo cordado, esto debe quedar especificados en contrato | BO18: 45882 | BP18: =IF(BO18="","",IF(BO18="TBD","TBD",IF(BO18="N/A","N/A","W"&TEXT(WEEKNUM(BO18,21),"00")&" "&YEAR(BO18)))) -> W33 2025 | BQ18: Ing Aprobada | BR18: "CHECKLIST SITIO" 1. Coordenadas Google Earth: OK 2. Nemonico: 06_379 3. Tipo de estructura: Monoposte/ Colocalizada 4. Altura Torre: OK 30 MTS 5. Altura RF: OK 25MTS 6. Tipo de Soporte: H 3000 7. PGB Altura: OK 8. PGB Piso: OK 9 Disponibilida de recorrido Power: OK 10. EPC Aerea; OK 11 EPC Piso: N/A 12 Rodomo: camuflaje 13. Energia Provisoria: NO 14. Disponibilidad LTE / 5G en Torre OK 15. Disponibilidad de LTE / 5G Piso: OK 16. Requiere Andamios: Andamios 17. Antenas con Plan de RF: OK 18: Tronera: N/A 19. Porta Feeders: OK 20_ GPS: OK 21. Az con Plan de RF: OK Observaciones | BS18: 45890 | BT18: =IF(BS18="","",IF(BS18="TBD","TBD",IF(BS18="N/A","N/A","W"&TEXT(WEEKNUM(BS18,21),"00")&" "&YEAR(BS18)))) -> W34 2025 | BU18: Ing Aprobada Con Observaciones | BV18: En cuadro de cargas (Sección TDF) Se hace referencia a planta rectificadora VERTIV, sin embargo, para sitios nuevos se instalan solo plantas Huawei, esto debe ser corregido. | BW18: 45926 | BX18: =IF(BW18="","",IF(BW18="TBD","TBD",IF(BW18="N/A","N/A","W"&TEXT(WEEKNUM(BW18,21),"00")&" "&YEAR(BW18)))) -> W39 2025 | BY18: 45931 | BZ18: =IF(BY18="","",IF(BY18="TBD","TBD",IF(BY18="N/A","N/A","W"&TEXT(WEEKNUM(BY18,21),"00")&" "&YEAR(BY18)))) -> W40 2025 | CA18: Ing Aprobada con Observaciones 4G | CB18: Finalizadas | CC18: Finalizadas | CF18: 46022 | CH18: 46024 | CI18: =IF(CH18="","",IF(CH18="TBD","TBD",IF(CH18="N/A","N/A","W"&TEXT(WEEKNUM(CH18,21),"00")&" "&YEAR(CH18)))) -> W01 2026 | CJ18: 46027 | CK18: =IF(CJ18="","",IF(CJ18="TBD","TBD",IF(CJ18="N/A","N/A","W"&TEXT(WEEKNUM(CJ18,21),"00")&" "&YEAR(CJ18)))) -> W02 2026 | CL18: =+IF(CJ18="",0,(CJ18-CH18)) -> 3 | CM18: As Built Aprobado | CN18: No hay fotos de mediciones con cinta métrica. Se valida según lo indicado en planos, pero el OOII deberá subsanar en caso de presentarse problemas de implementación. | CO18: 45659 | CP18: =IF(CO18="","",IF(CO18="TBD","TBD",IF(CO18="N/A","N/A","W"&TEXT(WEEKNUM(CO18,21),"00")&" "&YEAR(CO18)))) -> W01 2025 | CQ18: As Built Observado | CR18: Se debe evidenciar la poda de los árboles según comprometido en TSS | CS18: 46027 | CT18: =IF(CS18="","",IF(CS18="TBD","TBD",IF(CS18="N/A","N/A","W"&TEXT(WEEKNUM(CS18,21),"00")&" "&YEAR(CS18)))) -> W02 2026 | CU18: As Built Aprobado | CV18: Aprobado | CW18: 46024 | CX18: =IF(CW18="","",IF(CW18="TBD","TBD",IF(CW18="N/A","N/A","W"&TEXT(WEEKNUM(CW18,21),"00")&" "&YEAR(CW18)))) -> W01 2026 | CY18: As Built Rechazado | CZ18: Sitio sin energía Falta N° Cliente Falta N° Medidor Falta TE1 Falta contrato de suministro | DA18: 46027 | DB18: =IF(DA18="","",IF(DA18="TBD","TBD",IF(DA18="N/A","N/A","W"&TEXT(WEEKNUM(DA18,21),"00")&" "&YEAR(DA18)))) -> W02 2026 | DC18: 46027 | DD18: =IF(DC18="","",IF(DC18="TBD","TBD",IF(DC18="N/A","N/A","W"&TEXT(WEEKNUM(DC18,21),"00")&" "&YEAR(DC18)))) -> W02 2026 | DE18: As Built Rechazado 4G | DG18: Gabinete Huawei | DH18: 0 | DK18: FO | DL18: Poste | DQ18: Huawei | EB18: Construido 4G | EC18: Plan 2024 | EF18: 45870 | EI18: 0 | EJ18: =K18&AY18&CA18&DE18&DT18&DW18 -> VigenteTSS Aprobado 4GIng Aprobada con Observaciones 4GAs Built Rechazado 4G
A19: =IFERROR(IF(VLOOKUP(B19,SEARCH!A:A,1,0)=B19,"OK",""),"") | B19: 33_997 | C19: Colina Santa Filomena | D19: 13 | E19: -33.21475 | F19: -70.6695 | G19: Metropolitana de Santiago | H19: Colina | I19: Camino San Luis Lote E4 sin Número | J19: Fase 1 | K19: Vigente | L19: No aplica | M19: Sitio Recibido | O19: ANTYL | P19: Colo | R19: TORRE | S19: 14 | T19: ANT 197_13 | U19: 45119 | V19: =IF(U19="","",IF(U19="TBD","TBD",IF(U19="N/A","N/A","W"&TEXT(WEEKNUM(U19,21),"00")&" "&YEAR(U19)))) -> W28 2023 | W19: 45236 | X19: 45243 | Y19: =IF(X19="","",IF(X19="TBD","TBD",IF(X19="N/A","N/A","W"&TEXT(WEEKNUM(X19,21),"00")&" "&YEAR(X19)))) -> W46 2023 | Z19: 45244 | AB19: =+IF(Z19="",0,AA19-Z19) -> -45244 | AC19: TSS Aprobado | AD19: 0 | AE19: 45237 | AF19: =IF(AE19="","",IF(AE19="TBD","TBD",IF(AE19="N/A","N/A","W"&TEXT(WEEKNUM(AE19,21),"00")&" "&YEAR(AE19)))) -> W45 2023 | AG19: TSS Aprobado | AH19: Sitio queda condicionado a 4 pipes de L: 4m por temas de espacio. RF aprueba esta condición especial. | AI19: 45237 | AJ19: =IF(AI19="","",IF(AI19="TBD","TBD",IF(AI19="N/A","N/A","W"&TEXT(WEEKNUM(AI19,21),"00")&" "&YEAR(AI19)))) -> W45 2023 | AK19: TSS Aprobado | AL19: : Aprobado V2. Altura definida 14m, Adosamiento (Silo). | AN19: =IF(AM19="","",IF(AM19="TBD","TBD",IF(AM19="N/A","N/A","W"&TEXT(WEEKNUM(AM19,21),"00")&" "&YEAR(AM19)))) | AO19: TSS Aprobado | AQ19: 45247 | AR19: =IF(AQ19="","",IF(AQ19="TBD","TBD",IF(AQ19="N/A","N/A","W"&TEXT(WEEKNUM(AQ19,21),"00")&" "&YEAR(AQ19)))) -> W46 2023 | AW19: 45247 | AX19: =IF(AW19="","",IF(AW19="TBD","TBD",IF(AW19="N/A","N/A","W"&TEXT(WEEKNUM(AW19,21),"00")&" "&YEAR(AW19)))) -> W46 2023 | AY19: TSS Aprobado 4G | AZ19: FC Enviado a OOII | BA19: Contrato Firmado | BB19: 45167 | BC19: 45275 | BD19: 45275 | BE19: =IF(BD19="","",IF(BD19="TBD","TBD",IF(BD19="N/A","N/A","W"&TEXT(WEEKNUM(BD19,21),"00")&" "&YEAR(BD19)))) -> W50 2023 | BF19: 45280 | BG19: =IF(BF19="","",IF(BF19="TBD","TBD",IF(BF19="N/A","N/A","W"&TEXT(WEEKNUM(BF19,21),"00")&" "&YEAR(BF19)))) -> W51 2023 | BH19: =+IF(BF19="",0,(BF19-BD19)) -> 5 | BI19: Ing Aprobada | BK19: 45279 | BL19: =IF(BK19="","",IF(BK19="TBD","TBD",IF(BK19="N/A","N/A","W"&TEXT(WEEKNUM(BK19,21),"00")&" "&YEAR(BK19)))) -> W51 2023 | BM19: Ing Aprobada | BN19: la disponibilidad de 4 soportes en particular en este caso. | BO19: 45256 | BP19: =IF(BO19="","",IF(BO19="TBD","TBD",IF(BO19="N/A","N/A","W"&TEXT(WEEKNUM(BO19,21),"00")&" "&YEAR(BO19)))) -> W47 2023 | BQ19: Ing Aprobada | BR19: 24-11-2023: Aprobado V1. Proyección de 4 Gabinete (Equipamiento en 4 Gabinete de piso) Radier: 3x2 (Plataforma Metálica) | BS19: 45280 | BT19: =IF(BS19="","",IF(BS19="TBD","TBD",IF(BS19="N/A","N/A","W"&TEXT(WEEKNUM(BS19,21),"00")&" "&YEAR(BS19)))) -> W51 2023 | BU19: Ing Aprobada | BV19: Empalme independiente Aéreo trifásico proyectado desde poste referencia # 713553. Acometida eléctrica subterránea trifásica proyectada Medidor + TDAyF proyectado. Línea de 25 mts con conductor 6 AWG Superflex. Unilineal Claro. Aterramientos Proyectados. | BW19: 45254 | BX19: =IF(BW19="","",IF(BW19="TBD","TBD",IF(BW19="N/A","N/A","W"&TEXT(WEEKNUM(BW19,21),"00")&" "&YEAR(BW19)))) -> W47 2023 | BY19: 45280 | BZ19: =IF(BY19="","",IF(BY19="TBD","TBD",IF(BY19="N/A","N/A","W"&TEXT(WEEKNUM(BY19,21),"00")&" "&YEAR(BY19)))) -> W51 2023 | CA19: Ing Aprobada 4G | CB19: Finalizadas | CC19: Finalizadas | CD19: Sin Energía Provisoria | CE19: Si | CF19: 45359 | CG19: 45443 | CH19: 45443 | CI19: =IF(CH19="","",IF(CH19="TBD","TBD",IF(CH19="N/A","N/A","W"&TEXT(WEEKNUM(CH19,21),"00")&" "&YEAR(CH19)))) -> W22 2024 | CJ19: 45450 | CK19: =IF(CJ19="","",IF(CJ19="TBD","TBD",IF(CJ19="N/A","N/A","W"&TEXT(WEEKNUM(CJ19,21),"00")&" "&YEAR(CJ19)))) -> W23 2024 | CL19: =+IF(CJ19="",0,(CJ19-CH19)) -> 7 | CM19: As Built Aprobado con Observaciones | CN19: INFORME FOTOGRÁFICO Rev.2 05:06:2024 Línea F.O: PVC de 63m indicar cantidad de PVC para FO / LE. Observado. Línea eléctrica : Pendiente fotografía con la canalización de LE. Cámara común : Pendiente fotografía interior de cámara. PLANOS AS BUILT Rev.2 05:06:2024 Línea F.O: PVC de 63m indicar cantidad de PVC para FO / LE. Observado. Línea eléctrica: PVC de 63m indicar cantidad de PVC para FO / LE. Observado. | CO19: 45448 | CP19: =IF(CO19="","",IF(CO19="TBD","TBD",IF(CO19="N/A","N/A","W"&TEXT(WEEKNUM(CO19,21),"00")&" "&YEAR(CO19)))) -> W23 2024 | CQ19: As Built Aprobado | CR19: 05/06: Se levantan observaciones | CS19: 45448 | CT19: =IF(CS19="","",IF(CS19="TBD","TBD",IF(CS19="N/A","N/A","W"&TEXT(WEEKNUM(CS19,21),"00")&" "&YEAR(CS19)))) -> W23 2024 | CU19: As Built Aprobado | CV19: 22-03-24: Aprobado V1 - Foto Panorámica de todos los Soportes: SI-OK - Foto del EPC con llegada a los soportes: SI-OK. - Foto con cinta métrica: Indicando altura total de los Soportes: NO-OK - Foto Dimensiones de soportes con la cinta métrica: NO-OK. NOTA: Cuando se inicie con la Implementación, si algunos de los soporte no cumple con las dimensiones plasmada en la Ingeniería y As Built, él OOII deberá realizar los cambios en el Sitio. OBSERVACIONES 22-03-24: Aprobado V1 Router: ZTE. TX: FO: SI. MMOO: N/A Soporte Instalado: No | CW19: 45373 | CX19: =IF(CW19="","",IF(CW19="TBD","TBD",IF(CW19="N/A","N/A","W"&TEXT(WEEKNUM(CW19,21),"00")&" "&YEAR(CW19)))) -> W12 2024 | CY19: As Built Aprobado | CZ19: 22-03-24: Aprobado V1 - Foto Panorámica de todos los Soportes: SI-OK - Foto del EPC con llegada a los soportes: SI-OK. - Foto con cinta métrica: Indicando altura total de los Soportes: NO-OK - Foto Dimensiones de soportes con la cinta métrica: NO-OK. NOTA: Cuando se inicie con la Implementación, si algunos de los soporte no cumple con las dimensiones plasmada en la Ingeniería y As Built, él OOII deberá realizar los cambios en el Sitio. OBSERVACIONES 22-03-24: Aprobado V1 Router: ZTE. TX: FO: SI. MMOO: N/A Soporte Instalado: No | DA19: 45373 | DB19: =IF(DA19="","",IF(DA19="TBD","TBD",IF(DA19="N/A","N/A","W"&TEXT(WEEKNUM(DA19,21),"00")&" "&YEAR(DA19)))) -> W12 2024 | DC19: 45449 | DD19: =IF(DC19="","",IF(DC19="TBD","TBD",IF(DC19="N/A","N/A","W"&TEXT(WEEKNUM(DC19,21),"00")&" "&YEAR(DC19)))) -> W23 2024 | DE19: As Built Aprobado con Observaciones 4G | DG19: Gabinete Huawei | DH19: 0 | DK19: FO | DL19: ODF Instalado | DN19: 45537 | DO19: 45537 | DQ19: ZTE | DS19: 45541 | DU19: 45450 | DV19: 45549 | DW19: On Air | EB19: On Air 4G | EC19: Plan 2024 | EI19: 0 | EJ19: =K19&AY19&CA19&DE19&DT19&DW19 -> VigenteTSS Aprobado 4GIng Aprobada 4GAs Built Aprobado con Observaciones 4GOn Air
A20: =IFERROR(IF(VLOOKUP(B20,SEARCH!A:A,1,0)=B20,"OK",""),"") | B20: 43_160 | C20: Inacap Renca | D20: 13 | E20: -33.405925 | F20: -70.681582 | G20: Metropolitana de Santiago | H20: Renca | I20: AV. PRESIDENTE EDUARDO FREI MONTALVA N°2451 | J20: Fase 1 - Eliminado | K20: No Vigente | L20: No aplica | M20: No aplica | O20: ANTYL | P20: 0 | Q20: Sale de Plan CC RF 2-4-2025 | R20: MONOPOSTE | S20: 12 | T20: PENDIENTE | U20: 45610 | V20: =IF(U20="","",IF(U20="TBD","TBD",IF(U20="N/A","N/A","W"&TEXT(WEEKNUM(U20,21),"00")&" "&YEAR(U20)))) -> W46 2024 | W20: 45610 | Y20: =IF(X20="","",IF(X20="TBD","TBD",IF(X20="N/A","N/A","W"&TEXT(WEEKNUM(X20,21),"00")&" "&YEAR(X20)))) | Z20: 45610 | AA20: 45614 | AB20: =+IF(Z20="",0,AA20-Z20) -> 4 | AC20: TSS Aprobado | AD20: Sin Observaciones | AE20: 45611 | AF20: =IF(AE20="","",IF(AE20="TBD","TBD",IF(AE20="N/A","N/A","W"&TEXT(WEEKNUM(AE20,21),"00")&" "&YEAR(AE20)))) -> W46 2024 | AG20: TSS Aprobado | AH20: 26-11: Aprobado 1. Area en piso 3x3m 2. 6 soportes simples L: 4000mm 3. Canalizaciones a sistema radiante y en radier se verificaran en ingenieria. | AI20: 45622 | AJ20: =IF(AI20="","",IF(AI20="TBD","TBD",IF(AI20="N/A","N/A","W"&TEXT(WEEKNUM(AI20,21),"00")&" "&YEAR(AI20)))) -> W48 2024 | AK20: TSS Aprobado | AL20: 19-11-24: RECHAZADO V1. - Falta Indicar tipo, cantidad de soporte y dimensiones de soportes: NO-OK (PLANOS) | AM20: 45638 | AN20: =IF(AM20="","",IF(AM20="TBD","TBD",IF(AM20="N/A","N/A","W"&TEXT(WEEKNUM(AM20,21),"00")&" "&YEAR(AM20)))) -> W50 2024 | AO20: TSS Aprobado | AP20: REV2 20-11-2024 (ANTYL) Sitio Macro Proyectado Área proyectada 3x3 mts Empalme eléctrico aéreo trifásico proyectado desde poste Enel # 0696609 Acometida eléctrica aérea trifásica proyectada (L=20 mts app) Línea eléctrica aérea Trifásica proyectada (L=75mts app) | AQ20: 45616 | AR20: =IF(AQ20="","",IF(AQ20="TBD","TBD",IF(AQ20="N/A","N/A","W"&TEXT(WEEKNUM(AQ20,21),"00")&" "&YEAR(AQ20)))) -> W47 2024 | AW20: 45638 | AX20: =IF(AW20="","",IF(AW20="TBD","TBD",IF(AW20="N/A","N/A","W"&TEXT(WEEKNUM(AW20,21),"00")&" "&YEAR(AW20)))) -> W50 2024 | AY20: TSS Aprobado 4G | AZ20: FC Enviado a OOII | BA20: Contrato No Firmado | BE20: =IF(BD20="","",IF(BD20="TBD","TBD",IF(BD20="N/A","N/A","W"&TEXT(WEEKNUM(BD20,21),"00")&" "&YEAR(BD20)))) | BG20: =IF(BF20="","",IF(BF20="TBD","TBD",IF(BF20="N/A","N/A","W"&TEXT(WEEKNUM(BF20,21),"00")&" "&YEAR(BF20)))) | BH20: =+IF(BF20="",0,(BF20-BD20)) -> 0 | BI20: Ing No Recibida | BL20: =IF(BK20="","",IF(BK20="TBD","TBD",IF(BK20="N/A","N/A","W"&TEXT(WEEKNUM(BK20,21),"00")&" "&YEAR(BK20)))) | BM20: Ing No Recibida | BP20: =IF(BO20="","",IF(BO20="TBD","TBD",IF(BO20="N/A","N/A","W"&TEXT(WEEKNUM(BO20,21),"00")&" "&YEAR(BO20)))) | BQ20: Ing No Recibida | BT20: =IF(BS20="","",IF(BS20="TBD","TBD",IF(BS20="N/A","N/A","W"&TEXT(WEEKNUM(BS20,21),"00")&" "&YEAR(BS20)))) | BU20: Ing No Recibida | BX20: =IF(BW20="","",IF(BW20="TBD","TBD",IF(BW20="N/A","N/A","W"&TEXT(WEEKNUM(BW20,21),"00")&" "&YEAR(BW20)))) | BZ20: =IF(BY20="","",IF(BY20="TBD","TBD",IF(BY20="N/A","N/A","W"&TEXT(WEEKNUM(BY20,21),"00")&" "&YEAR(BY20)))) | CA20: Ing No Recibida 4G | CB20: No Iniciadas | CC20: No iniciadas | CI20: =IF(CH20="","",IF(CH20="TBD","TBD",IF(CH20="N/A","N/A","W"&TEXT(WEEKNUM(CH20,21),"00")&" "&YEAR(CH20)))) | CK20: =IF(CJ20="","",IF(CJ20="TBD","TBD",IF(CJ20="N/A","N/A","W"&TEXT(WEEKNUM(CJ20,21),"00")&" "&YEAR(CJ20)))) | CL20: =+IF(CJ20="",0,(CJ20-CH20)) -> 0 | CM20: As Built No Recibido | CP20: =IF(CO20="","",IF(CO20="TBD","TBD",IF(CO20="N/A","N/A","W"&TEXT(WEEKNUM(CO20,21),"00")&" "&YEAR(CO20)))) | CQ20: As Built No Recibido | CT20: =IF(CS20="","",IF(CS20="TBD","TBD",IF(CS20="N/A","N/A","W"&TEXT(WEEKNUM(CS20,21),"00")&" "&YEAR(CS20)))) | CU20: As Built No Recibido | CX20: =IF(CW20="","",IF(CW20="TBD","TBD",IF(CW20="N/A","N/A","W"&TEXT(WEEKNUM(CW20,21),"00")&" "&YEAR(CW20)))) | CY20: As Built No Recibido | DB20: =IF(DA20="","",IF(DA20="TBD","TBD",IF(DA20="N/A","N/A","W"&TEXT(WEEKNUM(DA20,21),"00")&" "&YEAR(DA20)))) | DD20: =IF(DC20="","",IF(DC20="TBD","TBD",IF(DC20="N/A","N/A","W"&TEXT(WEEKNUM(DC20,21),"00")&" "&YEAR(DC20)))) | DE20: As Built No Recibido | DG20: Gabinete Huawei | DK20: FO | DL20: Poste | DN20: 45282 | DQ20: ZTE | EA20: SOLPED 21-6-2024 | EB20: En Etapa de Ingeniería 4G | EF20: Sin fecha, respuesta de PM sobre importancia de sitio | EI20: 0 | EJ20: =K20&AY20&CA20&DE20&DT20&DW20 -> No VigenteTSS Aprobado 4GIng No Recibida 4GAs Built No Recibido
A21: =IFERROR(IF(VLOOKUP(B21,SEARCH!A:A,1,0)=B21,"OK",""),"") | B21: 53_336 | C21: Costanera Sur La Capilla | D21: 13 | E21: -33.413103 | F21: -70.759603 | G21: Metropolitana de Santiago | H21: Cerro Navia | I21: LUIS ALBERTO CRUZ N°1174 | J21: 5G | K21: Vigente | L21: 5G | M21: 5 | N21: 1 | O21: ANTYL | P21: Colo | Q21: Posibilidad es Antyl | R21: MONOPOSTE | S21: 35 | T21: ANT235_13 | U21: 45537 | V21: =IF(U21="","",IF(U21="TBD","TBD",IF(U21="N/A","N/A","W"&TEXT(WEEKNUM(U21,21),"00")&" "&YEAR(U21)))) -> W36 2024 | W21: 45544 | Y21: =IF(X21="","",IF(X21="TBD","TBD",IF(X21="N/A","N/A","W"&TEXT(WEEKNUM(X21,21),"00")&" "&YEAR(X21)))) | Z21: 45545 | AA21: 45548 | AB21: =+IF(Z21="",0,AA21-Z21) -> 3 | AC21: TSS Aprobado | AD21: Sitio ANTYL sin Id propio, se requiere ese dato para correcta asociación | AE21: 45558 | AF21: =IF(AE21="","",IF(AE21="TBD","TBD",IF(AE21="N/A","N/A","W"&TEXT(WEEKNUM(AE21,21),"00")&" "&YEAR(AE21)))) -> W39 2024 | AG21: TSS Aprobado | AH21: Rev.1 23-09: Aprobado 1. Soporte RF: 3 soportes dobles en monoposte sin radomo 2. Area en piso: 2,5x2,5m. 3. Canalizacion en radier y sistema radiante (EPC + PORTA FEEDERS) se verificará en ingenieria. ANTYL debe garantizar el libre acceso al sitio | AI21: 45558 | AJ21: =IF(AI21="","",IF(AI21="TBD","TBD",IF(AI21="N/A","N/A","W"&TEXT(WEEKNUM(AI21,21),"00")&" "&YEAR(AI21)))) -> W39 2024 | AK21: TSS Aprobado | AM21: 45558 | AN21: =IF(AM21="","",IF(AM21="TBD","TBD",IF(AM21="N/A","N/A","W"&TEXT(WEEKNUM(AM21,21),"00")&" "&YEAR(AM21)))) -> W39 2024 | AO21: TSS Aprobado | AP21: Sitio Macro Proyectado Área proyectada dentro de cerco existente Empalme trifásico independiente proyectado Acometida eléctrica aérea trifásica proyectada desde poste Compañía eléctrica Enel N°0.709.515 (L= 28 mts) Línea eléctrica subterránea proyectada L=30 mts hasta TDAyF Proyectado Nota: No hay Factibilidad de energía provisoria desde operador existente | AQ21: 45558 | AR21: =IF(AQ21="","",IF(AQ21="TBD","TBD",IF(AQ21="N/A","N/A","W"&TEXT(WEEKNUM(AQ21,21),"00")&" "&YEAR(AQ21)))) -> W39 2024 | AS21: TSS Aprobado | AT21: 0 | AU21: 45558 | AW21: 45558 | AX21: =IF(AW21="","",IF(AW21="TBD","TBD",IF(AW21="N/A","N/A","W"&TEXT(WEEKNUM(AW21,21),"00")&" "&YEAR(AW21)))) -> W39 2024 | AY21: TSS Aprobado 4G | AZ21: FC Enviado a OOII | BA21: Contrato Firmado | BB21: 45588 | BC21: 45607 | BD21: 45607 | BE21: =IF(BD21="","",IF(BD21="TBD","TBD",IF(BD21="N/A","N/A","W"&TEXT(WEEKNUM(BD21,21),"00")&" "&YEAR(BD21)))) -> W46 2024 | BF21: 45609 | BG21: =IF(BF21="","",IF(BF21="TBD","TBD",IF(BF21="N/A","N/A","W"&TEXT(WEEKNUM(BF21,21),"00")&" "&YEAR(BF21)))) -> W46 2024 | BH21: =+IF(BF21="",0,(BF21-BD21)) -> 2 | BI21: Ing Aprobada con Observaciones | BJ21: Según lo conversado en la reunión de ayer con el OI, se cuenta con 7 soportes de L: 4m, lo cual pueden implementar la antena AAU5339w en la parte superior y más abajo la antena AQU4518R24V18. De igual manera se adjunta estudio de cabida en base a dimensiones enviadas en los planos entregados por el OI. Lo que se solicita al OI, instalar los pipes por dentro del anillo existente para correcta instalación. | BK21: 45632 | BL21: =IF(BK21="","",IF(BK21="TBD","TBD",IF(BK21="N/A","N/A","W"&TEXT(WEEKNUM(BK21,21),"00")&" "&YEAR(BK21)))) -> W49 2024 | BM21: Ing Aprobada | BN21: En base a la disponibilidad de 7 soportes y los nuevos análisis internos, la Ingeniería queda Aprobada por RF. | BO21: 45632 | BP21: =IF(BO21="","",IF(BO21="TBD","TBD",IF(BO21="N/A","N/A","W"&TEXT(WEEKNUM(BO21,21),"00")&" "&YEAR(BO21)))) -> W49 2024 | BQ21: Ing Aprobada | BS21: 45628 | BT21: =IF(BS21="","",IF(BS21="TBD","TBD",IF(BS21="N/A","N/A","W"&TEXT(WEEKNUM(BS21,21),"00")&" "&YEAR(BS21)))) -> W49 2024 | BU21: Ing Aprobada | BV21: REV1 24-10-2024 Área proyectada 2,5 x 2,5 mts Acometida eléctrica aéreo trifásica proyectada desde poste referencia # 709515 Acometida eléctrica aéreo proyectada (L=28 mts) Línea eléctrica subterránea proyectada (L=30 mts) (6AWG) Tierras proyectadas | BW21: 45589 | BX21: =IF(BW21="","",IF(BW21="TBD","TBD",IF(BW21="N/A","N/A","W"&TEXT(WEEKNUM(BW21,21),"00")&" "&YEAR(BW21)))) -> W43 2024 | BY21: 45632 | BZ21: =IF(BY21="","",IF(BY21="TBD","TBD",IF(BY21="N/A","N/A","W"&TEXT(WEEKNUM(BY21,21),"00")&" "&YEAR(BY21)))) -> W49 2024 | CA21: Ing Aprobada con Observaciones 4G/5G | CB21: Finalizadas | CC21: Finalizadas | CF21: 45714 | CG21: 45806 | CH21: 45806 | CI21: =IF(CH21="","",IF(CH21="TBD","TBD",IF(CH21="N/A","N/A","W"&TEXT(WEEKNUM(CH21,21),"00")&" "&YEAR(CH21)))) -> W22 2025 | CJ21: 45810 | CK21: =IF(CJ21="","",IF(CJ21="TBD","TBD",IF(CJ21="N/A","N/A","W"&TEXT(WEEKNUM(CJ21,21),"00")&" "&YEAR(CJ21)))) -> W23 2025 | CL21: =+IF(CJ21="",0,(CJ21-CH21)) -> 4 | CM21: As Built Aprobado con Observaciones | CN21: OBSERVACIONES ASB - OOCC - Informe Fotográfico Aprobado. No se agregaron las fotografías solicitadas en revisión anterior. Operador indica que "las dimensiones respaldadas por fotografías, lo acordado es que estas serían respaldadas sólo con los planos as built". El operador deberá resolver en caso de presentarse diferencias respecto al plano. OBSERVACIONES ASB - OOCC - Planos Aprobado en rev. anterior. El Operador de Infraestructura deberá resolver si el equipamiento no tiene cabida con radomo. | CO21: 45807 | CP21: =IF(CO21="","",IF(CO21="TBD","TBD",IF(CO21="N/A","N/A","W"&TEXT(WEEKNUM(CO21,21),"00")&" "&YEAR(CO21)))) -> W22 2025 | CQ21: As Built Aprobado | CS21: 45813 | CT21: =IF(CS21="","",IF(CS21="TBD","TBD",IF(CS21="N/A","N/A","W"&TEXT(WEEKNUM(CS21,21),"00")&" "&YEAR(CS21)))) -> W23 2025 | CU21: As Built Aprobado | CW21: 45813 | CX21: =IF(CW21="","",IF(CW21="TBD","TBD",IF(CW21="N/A","N/A","W"&TEXT(WEEKNUM(CW21,21),"00")&" "&YEAR(CW21)))) -> W23 2025 | CY21: As Built Aprobado Con Observaciones | CZ21: Energía definitiva, falta respaldo de factura por consumo para validar información de cliente final. | DA21: 45807 | DB21: =IF(DA21="","",IF(DA21="TBD","TBD",IF(DA21="N/A","N/A","W"&TEXT(WEEKNUM(DA21,21),"00")&" "&YEAR(DA21)))) -> W22 2025 | DC21: 45813 | DD21: =IF(DC21="","",IF(DC21="TBD","TBD",IF(DC21="N/A","N/A","W"&TEXT(WEEKNUM(DC21,21),"00")&" "&YEAR(DC21)))) -> W23 2025 | DE21: As Built Aprobado con Observaciones 4G | DG21: Gabinete Huawei | DK21: FO | DL21: ODF Instalado | DN21: 45901 | DO21: 45901 | DQ21: ZTE | DU21: 45816 | DV21: 45910 | DW21: On Air | EB21: On Air 4G/5G | ED21: Plan 2025 | EI21: 0 | EJ21: =K21&AY21&CA21&DE21&DT21&DW21 -> VigenteTSS Aprobado 4GIng Aprobada con Observaciones 4G/5GAs Built Aprobado con Observaciones 4GOn Air
A22: =IFERROR(IF(VLOOKUP(B22,SEARCH!A:A,1,0)=B22,"OK",""),"") | B22: 02_434 | C22: Sector Peuco Calama | D22: 2 | E22: -22.46344 | F22: -68.899 | G22: Antofagasta | H22: Calama | I22: CERRO BUGGY, Calama, Antofagasta Chile | J22: No Vigente | K22: No Vigente | L22: No aplica | O22: ATC | P22: Colo | R22: MONOPOSTE | S22: 14 | T22: 153873 | U22: 45131 | V22: =IF(U22="","",IF(U22="TBD","TBD",IF(U22="N/A","N/A","W"&TEXT(WEEKNUM(U22,21),"00")&" "&YEAR(U22)))) -> W30 2023 | W22: 45166 | Y22: =IF(X22="","",IF(X22="TBD","TBD",IF(X22="N/A","N/A","W"&TEXT(WEEKNUM(X22,21),"00")&" "&YEAR(X22)))) | AA22: 45168 | AB22: =+IF(Z22="",0,AA22-Z22) -> 0 | AC22: TSS Aprobado | AE22: 45170 | AF22: =IF(AE22="","",IF(AE22="TBD","TBD",IF(AE22="N/A","N/A","W"&TEXT(WEEKNUM(AE22,21),"00")&" "&YEAR(AE22)))) -> W35 2023 | AG22: TSS Aprobado | AH22: La ingeniería deberá considerar los soportes adecuados. | AI22: 45168 | AJ22: =IF(AI22="","",IF(AI22="TBD","TBD",IF(AI22="N/A","N/A","W"&TEXT(WEEKNUM(AI22,21),"00")&" "&YEAR(AI22)))) -> W35 2023 | AK22: TSS Aprobado | AM22: 45169 | AN22: =IF(AM22="","",IF(AM22="TBD","TBD",IF(AM22="N/A","N/A","W"&TEXT(WEEKNUM(AM22,21),"00")&" "&YEAR(AM22)))) -> W35 2023 | AO22: TSS Aprobado | AQ22: 45191 | AR22: =IF(AQ22="","",IF(AQ22="TBD","TBD",IF(AQ22="N/A","N/A","W"&TEXT(WEEKNUM(AQ22,21),"00")&" "&YEAR(AQ22)))) -> W38 2023 | AW22: 45190 | AX22: =IF(AW22="","",IF(AW22="TBD","TBD",IF(AW22="N/A","N/A","W"&TEXT(WEEKNUM(AW22,21),"00")&" "&YEAR(AW22)))) -> W38 2023 | AY22: TSS Aprobado 4G | AZ22: FC Enviado a OOII | BA22: Contrato No Firmado | BE22: =IF(BD22="","",IF(BD22="TBD","TBD",IF(BD22="N/A","N/A","W"&TEXT(WEEKNUM(BD22,21),"00")&" "&YEAR(BD22)))) | BG22: =IF(BF22="","",IF(BF22="TBD","TBD",IF(BF22="N/A","N/A","W"&TEXT(WEEKNUM(BF22,21),"00")&" "&YEAR(BF22)))) | BH22: =+IF(BF22="",0,(BF22-BD22)) -> 0 | BI22: Ing No Recibida | BL22: =IF(BK22="","",IF(BK22="TBD","TBD",IF(BK22="N/A","N/A","W"&TEXT(WEEKNUM(BK22,21),"00")&" "&YEAR(BK22)))) | BM22: Ing No Recibida | BP22: =IF(BO22="","",IF(BO22="TBD","TBD",IF(BO22="N/A","N/A","W"&TEXT(WEEKNUM(BO22,21),"00")&" "&YEAR(BO22)))) | BQ22: Ing No Recibida | BT22: =IF(BS22="","",IF(BS22="TBD","TBD",IF(BS22="N/A","N/A","W"&TEXT(WEEKNUM(BS22,21),"00")&" "&YEAR(BS22)))) | BU22: Ing No Recibida | BX22: =IF(BW22="","",IF(BW22="TBD","TBD",IF(BW22="N/A","N/A","W"&TEXT(WEEKNUM(BW22,21),"00")&" "&YEAR(BW22)))) | BZ22: =IF(BY22="","",IF(BY22="TBD","TBD",IF(BY22="N/A","N/A","W"&TEXT(WEEKNUM(BY22,21),"00")&" "&YEAR(BY22)))) | CA22: Ing No Recibida 4G | CB22: No Iniciadas | CC22: No iniciadas | CI22: =IF(CH22="","",IF(CH22="TBD","TBD",IF(CH22="N/A","N/A","W"&TEXT(WEEKNUM(CH22,21),"00")&" "&YEAR(CH22)))) | CK22: =IF(CJ22="","",IF(CJ22="TBD","TBD",IF(CJ22="N/A","N/A","W"&TEXT(WEEKNUM(CJ22,21),"00")&" "&YEAR(CJ22)))) | CL22: =+IF(CJ22="",0,(CJ22-CH22)) -> 0 | CM22: As Built No Recibido | CP22: =IF(CO22="","",IF(CO22="TBD","TBD",IF(CO22="N/A","N/A","W"&TEXT(WEEKNUM(CO22,21),"00")&" "&YEAR(CO22)))) | CQ22: As Built No Recibido | CT22: =IF(CS22="","",IF(CS22="TBD","TBD",IF(CS22="N/A","N/A","W"&TEXT(WEEKNUM(CS22,21),"00")&" "&YEAR(CS22)))) | CU22: As Built No Recibido | CX22: =IF(CW22="","",IF(CW22="TBD","TBD",IF(CW22="N/A","N/A","W"&TEXT(WEEKNUM(CW22,21),"00")&" "&YEAR(CW22)))) | CY22: As Built No Recibido | DB22: =IF(DA22="","",IF(DA22="TBD","TBD",IF(DA22="N/A","N/A","W"&TEXT(WEEKNUM(DA22,21),"00")&" "&YEAR(DA22)))) | DD22: =IF(DC22="","",IF(DC22="TBD","TBD",IF(DC22="N/A","N/A","W"&TEXT(WEEKNUM(DC22,21),"00")&" "&YEAR(DC22)))) | DE22: As Built No Recibido | DG22: Gabinete Huawei | DK22: FO | DL22: Pendiente | DQ22: Huawei | EB22: En Etapa de Ingeniería 4G | EI22: 0 | EJ22: =K22&AY22&CA22&DE22&DT22&DW22 -> No VigenteTSS Aprobado 4GIng No Recibida 4GAs Built No Recibido
A23: =IFERROR(IF(VLOOKUP(B23,SEARCH!A:A,1,0)=B23,"OK",""),"") | B23: 02_655 | C23: Toconce | D23: 2 | E23: -22,2648 | F23: -68,1627 | G23: Antofagasta | H23: CALAMA | I23: Lote D, Ampliación Toconce | J23: 5G | K23: Vigente | L23: Localidades | M23: 46203 | N23: 2 | O23: ATC | P23: Colo | R23: 0 | S23: 30 | T23: 151758 | U23: 0 | V23: =IF(U23="","",IF(U23="TBD","TBD",IF(U23="N/A","N/A","W"&TEXT(WEEKNUM(U23,21),"00")&" "&YEAR(U23)))) -> W52 1900 | W23: 45848 | Y23: =IF(X23="","",IF(X23="TBD","TBD",IF(X23="N/A","N/A","W"&TEXT(WEEKNUM(X23,21),"00")&" "&YEAR(X23)))) | Z23: 45849 | AA23: 45853 | AB23: =+IF(Z23="",0,AA23-Z23) -> 4 | AC23: TSS Aprobado | AD23: El candidato ATC 151758 tiene su TSS Aprobado por RF para Sitio Claro 02_655, con la altura ofrecida de 29 a 33 mts. En caso de disminuir la altura ofrecida debe generarse una nueva revisión y validación | AE23: 45853 | AF23: =IF(AE23="","",IF(AE23="TBD","TBD",IF(AE23="N/A","N/A","W"&TEXT(WEEKNUM(AE23,21),"00")&" "&YEAR(AE23)))) -> W29 2025 | AG23: TSS Aprobado | AH23: 15-07-25: APROBADO LLOO 4G (5G). 1. Area en piso 2x1,5m 2. 3 soportes dobles tipo H. 3. Considerar para etapa de ing. la proyección de 1 soporte para TX. 4. Comunicación a sistema radiante se verificará en etapa de ingenieria. | AI23: 45853 | AJ23: =IF(AI23="","",IF(AI23="TBD","TBD",IF(AI23="N/A","N/A","W"&TEXT(WEEKNUM(AI23,21),"00")&" "&YEAR(AI23)))) -> W29 2025 | AK23: TSS Aprobado | AL23: CHECKLIST SITIO 1. Coordenadas Google Earth: OK 2. Nemonico 02_655 3. Tipo de estructura: Ventada 4. Altura: 43 5. Altura RF: 29-33MTS segun plan 6. Tipo de Soporte: SIN ONFORMACION 6. PGB Altura: NOK 7. PGB Piso: NOK 8 Disponibilida de recorrido Power F.O: Sin Informacion 9. EPC Aerea; N/A 10 EPC Piso: OK 11 Rodomo: SI 12. Energia Provisoria: N/A 13. Disponibilidad 5G en Torre OK 14. Disponibilidad de 5G Piso: OK 15. Requiere Andamios: NOK 16. Antenas con Plan de RF: Sin evidencia 17: Tronera: N/A 18. Porta Feeders: N/A 19_ GPS: Sin evidencia en fotomontaje 20. Az con Plan de RF: Sin evidenci | AM23: 45855 | AN23: =IF(AM23="","",IF(AM23="TBD","TBD",IF(AM23="N/A","N/A","W"&TEXT(WEEKNUM(AM23,21),"00")&" "&YEAR(AM23)))) -> W29 2025 | AO23: TSS Aprobado Con Observaciones | AP23: El Diseño enviado por RF y de energía corresponde a la utilización de DPU120D y DBU100B, sin embargo, en TSS se proyecta un gabinete con planta Huawei y un gabinete de baterías Huawei. Esto debe ser subsanado en la Ingeniería si corresponde. PMO debe Revisar con inmobiliaria si se negoció la realización de un Radier y gabinete Huawei en este sito en específico. | AQ23: 45853 | AR23: =IF(AQ23="","",IF(AQ23="TBD","TBD",IF(AQ23="N/A","N/A","W"&TEXT(WEEKNUM(AQ23,21),"00")&" "&YEAR(AQ23)))) -> W29 2025 | AW23: 45855 | AX23: =IF(AW23="","",IF(AW23="TBD","TBD",IF(AW23="N/A","N/A","W"&TEXT(WEEKNUM(AW23,21),"00")&" "&YEAR(AW23)))) -> W29 2025 | AY23: TSS Aprobado 4G | AZ23: FC Enviado a OOII | BA23: Contrato Firmado | BB23: 46162 | BD23: 46132 | BE23: =IF(BD23="","",IF(BD23="TBD","TBD",IF(BD23="N/A","N/A","W"&TEXT(WEEKNUM(BD23,21),"00")&" "&YEAR(BD23)))) -> W17 2026 | BF23: 46134 | BG23: =IF(BF23="","",IF(BF23="TBD","TBD",IF(BF23="N/A","N/A","W"&TEXT(WEEKNUM(BF23,21),"00")&" "&YEAR(BF23)))) -> W17 2026 | BH23: =+IF(BF23="",0,(BF23-BD23)) -> 2 | BI23: Ing Aprobada con Observaciones | BJ23: Sitio Off grid con generador. ATC debe entregar fotografias de camino y proceos de traslado de material al momento de realizar adecuaciones. Equipo de Implementación debrá resolver instalación de Generador de acuerdo a lo revisado por Francisco Robles. Los soportes satelitales deben instalarse en el tope de la torre con total despeje hacia arriba. | BK23: 46154 | BL23: =IF(BK23="","",IF(BK23="TBD","TBD",IF(BK23="N/A","N/A","W"&TEXT(WEEKNUM(BK23,21),"00")&" "&YEAR(BK23)))) -> W20 2026 | BM23: Ing Aprobada Con Observaciones | BN23: para As-built se debe corregir cantidad de antenas a 2; y RRU5512 a 1. | BO23: 46138 | BP23: =IF(BO23="","",IF(BO23="TBD","TBD",IF(BO23="N/A","N/A","W"&TEXT(WEEKNUM(BO23,21),"00")&" "&YEAR(BO23)))) -> W17 2026 | BQ23: Ing Aprobada | BR23: Aprobado | BS23: 46139 | BT23: =IF(BS23="","",IF(BS23="TBD","TBD",IF(BS23="N/A","N/A","W"&TEXT(WEEKNUM(BS23,21),"00")&" "&YEAR(BS23)))) -> W18 2026 | BU23: Ing Aprobada | BV23: Sitio OFFGRID, Sin observaciones | BW23: 46135 | BX23: =IF(BW23="","",IF(BW23="TBD","TBD",IF(BW23="N/A","N/A","W"&TEXT(WEEKNUM(BW23,21),"00")&" "&YEAR(BW23)))) -> W17 2026 | BY23: 46154 | BZ23: =IF(BY23="","",IF(BY23="TBD","TBD",IF(BY23="N/A","N/A","W"&TEXT(WEEKNUM(BY23,21),"00")&" "&YEAR(BY23)))) -> W20 2026 | CA23: Ing Aprobada 4G | CB23: Finalizadas | CC23: Iniciadas | CD23: En proceso | CF23: 46206 | CH23: 46209 | CI23: =IF(CH23="","",IF(CH23="TBD","TBD",IF(CH23="N/A","N/A","W"&TEXT(WEEKNUM(CH23,21),"00")&" "&YEAR(CH23)))) -> W28 2026 | CJ23: 46211 | CK23: =IF(CJ23="","",IF(CJ23="TBD","TBD",IF(CJ23="N/A","N/A","W"&TEXT(WEEKNUM(CJ23,21),"00")&" "&YEAR(CJ23)))) -> W28 2026 | CL23: =+IF(CJ23="",0,(CJ23-CH23)) -> 2 | CM23: As Built Aprobado con Observaciones | CN23: No hay acceso vehicular al sitio para instalar el generador. Los soportes Starlink no quedaron con total despeje hacia arriba. Adosar los soportes Starlink al tope de los pipes RF de ser necesario. El herraje instalado en el poste TDAyF está colocado incorrectamente, implementación deberá instalarlo adecuadamente. | CO23: 46209 | CP23: =IF(CO23="","",IF(CO23="TBD","TBD",IF(CO23="N/A","N/A","W"&TEXT(WEEKNUM(CO23,21),"00")&" "&YEAR(CO23)))) -> W28 2026 | CQ23: As Built Aprobado | CR23: Aprobado | CS23: 46209 | CT23: =IF(CS23="","",IF(CS23="TBD","TBD",IF(CS23="N/A","N/A","W"&TEXT(WEEKNUM(CS23,21),"00")&" "&YEAR(CS23)))) -> W28 2026 | CU23: As Built Aprobado | CV23: Sin Observaciones | CW23: 46209 | CX23: =IF(CW23="","",IF(CW23="TBD","TBD",IF(CW23="N/A","N/A","W"&TEXT(WEEKNUM(CW23,21),"00")&" "&YEAR(CW23)))) -> W28 2026 | CY23: As Built Aprobado | CZ23: Sitio Offgrid, Sin observaciones | DA23: 46209 | DB23: =IF(DA23="","",IF(DA23="TBD","TBD",IF(DA23="N/A","N/A","W"&TEXT(WEEKNUM(DA23,21),"00")&" "&YEAR(DA23)))) -> W28 2026 | DC23: 46209 | DD23: =IF(DC23="","",IF(DC23="TBD","TBD",IF(DC23="N/A","N/A","W"&TEXT(WEEKNUM(DC23,21),"00")&" "&YEAR(DC23)))) -> W28 2026 | DE23: As Built Aprobado con Observaciones 4G | DG23: Gabinete Huawei | DK23: FO | DL23: Pendiente | DQ23: Huawei | EB23: En Etapa de Ingeniería 4G | EF23: 46203 | EH23: OI | EI23: Pendiente Forecast de entrega de ING | EJ23: =K23&AY23&CA23&DE23&DT23&DW23 -> VigenteTSS Aprobado 4GIng Aprobada 4GAs Built Aprobado con Observaciones 4G
A24: =IFERROR(IF(VLOOKUP(B24,SEARCH!A:A,1,0)=B24,"OK",""),"") | B24: 01_677 | C24: Mauque | D24: 1 | E24: -19,3215 | F24: -68,8796 | G24: Tarapacá | H24: COLCHANE | I24: Ruta A-487. Localidad de Mauque | J24: 5G | K24: Vigente | L24: Localidades | M24: 46203 | N24: 2 | O24: ATC | P24: Colo | R24: 0 | S24: 30 | T24: 154095 | U24: 45901 | V24: =IF(U24="","",IF(U24="TBD","TBD",IF(U24="N/A","N/A","W"&TEXT(WEEKNUM(U24,21),"00")&" "&YEAR(U24)))) -> W36 2025 | W24: 45924 | Y24: =IF(X24="","",IF(X24="TBD","TBD",IF(X24="N/A","N/A","W"&TEXT(WEEKNUM(X24,21),"00")&" "&YEAR(X24)))) | Z24: 45925 | AA24: 45929 | AB24: =+IF(Z24="",0,AA24-Z24) -> 4 | AC24: TSS Aprobado | AD24: El TSS del Sitio ATC Id 154095 para Sitio Claro 02_659 está “APROBADO” por RF. Adjunto tabla con datos del Sitio (TSS) y diseño RF definido  se requiere revisar con ATC la dirección del sitio, se requiere una glosa con mejor detalle: | AE24: 45929 | AF24: =IF(AE24="","",IF(AE24="TBD","TBD",IF(AE24="N/A","N/A","W"&TEXT(WEEKNUM(AE24,21),"00")&" "&YEAR(AE24)))) -> W40 2025 | AG24: TSS Aprobado con Observaciones | AH24: Aprobado con comentarios Falta indicar qué tipo de soportes se considera para TX (Confirmar con PMO si será MMOO o satelital) . Se revisará el detalle en la ingeniería. Espacio en piso 2,0 x 1,5 m Se consideran soportes RF dobles. | AI24: 45939 | AJ24: =IF(AI24="","",IF(AI24="TBD","TBD",IF(AI24="N/A","N/A","W"&TEXT(WEEKNUM(AI24,21),"00")&" "&YEAR(AI24)))) -> W41 2025 | AK24: TSS Aprobado con Observaciones | AL24: """CHECKLIST SITIO"" 02_659 29-09-25 Observaciones: 1,- TSS revisado, formato ATC, formato no cuenta con fotos más claras, no se muestra medidas, PGB, escalerilla, en foto montaje. 2.- Cantidad de HW a instalar no aparece en ningún lado. | AM24: 45929 | AN24: =IF(AM24="","",IF(AM24="TBD","TBD",IF(AM24="N/A","N/A","W"&TEXT(WEEKNUM(AM24,21),"00")&" "&YEAR(AM24)))) -> W40 2025 | AO24: TSS Aprobado Con Observaciones | AP24: Respecto al grupo propuesto y el equipamiento Blade (DPU120D + DBU100B), se confirma que estos sean compatibles para poder realizar un sistema de ciclado eficiente? Cuantos serán las horas diarias de funcionamiento del grupo generador? A que porcentajes de descargar de las baterías se utilizará como trigger para que encienda el grupo? con el compromiso que esta información solicitada venga en la Ingeniería. | AQ24: 45944 | AR24: =IF(AQ24="","",IF(AQ24="TBD","TBD",IF(AQ24="N/A","N/A","W"&TEXT(WEEKNUM(AQ24,21),"00")&" "&YEAR(AQ24)))) -> W42 2025 | AW24: 45944 | AX24: =IF(AW24="","",IF(AW24="TBD","TBD",IF(AW24="N/A","N/A","W"&TEXT(WEEKNUM(AW24,21),"00")&" "&YEAR(AW24)))) -> W42 2025 | AY24: TSS Aprobado con Observaciones 4G | AZ24: FC Enviado a OOII | BA24: Contrato Firmado | BB24: 46162 | BD24: 46132 | BE24: =IF(BD24="","",IF(BD24="TBD","TBD",IF(BD24="N/A","N/A","W"&TEXT(WEEKNUM(BD24,21),"00")&" "&YEAR(BD24)))) -> W17 2026 | BF24: 46134 | BG24: =IF(BF24="","",IF(BF24="TBD","TBD",IF(BF24="N/A","N/A","W"&TEXT(WEEKNUM(BF24,21),"00")&" "&YEAR(BF24)))) -> W17 2026 | BH24: =+IF(BF24="",0,(BF24-BD24)) -> 2 | BI24: Ing Aprobada con Observaciones | BJ24: Los soportes satelitales deben instalarse en el tope de la torre con total despeje hacia arriba. La PMO indica que está en negociación, y solicita aprobar con observación. Sitio off grid con acceso vehicular. | BK24: 46133 | BL24: =IF(BK24="","",IF(BK24="TBD","TBD",IF(BK24="N/A","N/A","W"&TEXT(WEEKNUM(BK24,21),"00")&" "&YEAR(BK24)))) -> W17 2026 | BM24: Ing Aprobada Con Observaciones | BN24: para As-built se debe corregir azimuth sector 3 a 270°. | BO24: 46138 | BP24: =IF(BO24="","",IF(BO24="TBD","TBD",IF(BO24="N/A","N/A","W"&TEXT(WEEKNUM(BO24,21),"00")&" "&YEAR(BO24)))) -> W17 2026 | BQ24: Ing Aprobada | BR24: Aprobado | BS24: 46139 | BT24: =IF(BS24="","",IF(BS24="TBD","TBD",IF(BS24="N/A","N/A","W"&TEXT(WEEKNUM(BS24,21),"00")&" "&YEAR(BS24)))) -> W18 2026 | BU24: Ing Aprobada | BV24: Sitio OFFGRID, Sin observaciones | BW24: 46135 | BX24: =IF(BW24="","",IF(BW24="TBD","TBD",IF(BW24="N/A","N/A","W"&TEXT(WEEKNUM(BW24,21),"00")&" "&YEAR(BW24)))) -> W17 2026 | BY24: 46139 | BZ24: =IF(BY24="","",IF(BY24="TBD","TBD",IF(BY24="N/A","N/A","W"&TEXT(WEEKNUM(BY24,21),"00")&" "&YEAR(BY24)))) -> W18 2026 | CA24: Ing Aprobada con Observaciones 4G | CB24: Finalizadas | CC24: En Ejecución | CF24: 46178 | CG24: 46210 | CH24: 46210 | CI24: =IF(CH24="","",IF(CH24="TBD","TBD",IF(CH24="N/A","N/A","W"&TEXT(WEEKNUM(CH24,21),"00")&" "&YEAR(CH24)))) -> W28 2026 | CJ24: 46213 | CK24: =IF(CJ24="","",IF(CJ24="TBD","TBD",IF(CJ24="N/A","N/A","W"&TEXT(WEEKNUM(CJ24,21),"00")&" "&YEAR(CJ24)))) -> W28 2026 | CL24: =+IF(CJ24="",0,(CJ24-CH24)) -> 3 | CM24: As Built Aprobado con Observaciones | CN24: OBSERVACIONES - INFORME FOTOGRAFICO El herraje instalado en el poste TDAyF está colocado incorrectamente, implementación deberá instalarlo adecuadamente. OBSERVACIONES - PLANOS Los soportes satelitales no quedaron con total despeje hacia arriba. Implementación deberá adosar los soportes satelitales a los soportes RF de ser necesario. Sitio off grid con generador. | CO24: 46181 | CP24: =IF(CO24="","",IF(CO24="TBD","TBD",IF(CO24="N/A","N/A","W"&TEXT(WEEKNUM(CO24,21),"00")&" "&YEAR(CO24)))) -> W24 2026 | CQ24: As Built Aprobado | CS24: 46213 | CT24: =IF(CS24="","",IF(CS24="TBD","TBD",IF(CS24="N/A","N/A","W"&TEXT(WEEKNUM(CS24,21),"00")&" "&YEAR(CS24)))) -> W28 2026 | CU24: As Built Aprobado | CV24: 1.- No se observa TDA | CW24: 46182 | CX24: =IF(CW24="","",IF(CW24="TBD","TBD",IF(CW24="N/A","N/A","W"&TEXT(WEEKNUM(CW24,21),"00")&" "&YEAR(CW24)))) -> W24 2026 | CY24: As Built Aprobado | CZ24: Sin observaciones. - Gabinete tipo TDAYF será proporcionado por Claro a la implementación del sitio. | DA24: 46181 | DB24: =IF(DA24="","",IF(DA24="TBD","TBD",IF(DA24="N/A","N/A","W"&TEXT(WEEKNUM(DA24,21),"00")&" "&YEAR(DA24)))) -> W24 2026 | DC24: 46213 | DD24: =IF(DC24="","",IF(DC24="TBD","TBD",IF(DC24="N/A","N/A","W"&TEXT(WEEKNUM(DC24,21),"00")&" "&YEAR(DC24)))) -> W28 2026 | DE24: As Built Aprobado 4G | DG24: Gabinete SITES | DK24: Satelital | DL24: Starlink Instalado | DQ24: Huawei | DW24: Off Air | EB24: Construido 4G | EF24: 46172 | EH24: OI-Inmobiliaria | EI24: Pendiente de negociar el área necesaria para la instalación de los paneles solares. @Tovar Teran Fiorella favor tu ayuda. | EJ24: =K24&AY24&CA24&DE24&DT24&DW24 -> VigenteTSS Aprobado con Observaciones 4GIng Aprobada con Observaciones 4GAs Built Aprobado 4GOff Air
A25: =IFERROR(IF(VLOOKUP(B25,SEARCH!A:A,1,0)=B25,"OK",""),"") | B25: 01_678 | C25: Macaya | D25: 1 | E25: -20,1336 | F25: -69,1822 | G25: Tarapacá | H25: POZO ALMONTE | I25: Ruta A-629. Localidad de Macaya | J25: 5G | K25: Vigente | L25: Localidades | M25: 46203 | N25: 2 | O25: ATC | P25: Colo | R25: 0 | S25: 18 | T25: 154309 | V25: =IF(U25="","",IF(U25="TBD","TBD",IF(U25="N/A","N/A","W"&TEXT(WEEKNUM(U25,21),"00")&" "&YEAR(U25)))) | W25: 46006 | Y25: =IF(X25="","",IF(X25="TBD","TBD",IF(X25="N/A","N/A","W"&TEXT(WEEKNUM(X25,21),"00")&" "&YEAR(X25)))) | Z25: 46006 | AA25: 46008 | AB25: =+IF(Z25="",0,AA25-Z25) -> 2 | AC25: TSS Aprobado | AD25: El TSS del Sitio ATC 154309 está “APROBADO” por RF para Sitio 02_660. | AE25: 46007 | AF25: =IF(AE25="","",IF(AE25="TBD","TBD",IF(AE25="N/A","N/A","W"&TEXT(WEEKNUM(AE25,21),"00")&" "&YEAR(AE25)))) -> W51 2025 | AG25: TSS Aprobado | AH25: Aprobado con comentarios. Se revisará en la ingeniería lo siguiente: - Radier proyectado de 2,0 x 1,5 m - 3 soportes dobles para RF - 1 soporte MMOO - EPC , canalizaciones y portafeeders según estándar Claro | AI25: 46008 | AJ25: =IF(AI25="","",IF(AI25="TBD","TBD",IF(AI25="N/A","N/A","W"&TEXT(WEEKNUM(AI25,21),"00")&" "&YEAR(AI25)))) -> W51 2025 | AK25: TSS Aprobado | AM25: 46009 | AN25: =IF(AM25="","",IF(AM25="TBD","TBD",IF(AM25="N/A","N/A","W"&TEXT(WEEKNUM(AM25,21),"00")&" "&YEAR(AM25)))) -> W51 2025 | AO25: TSS Aprobado Con Observaciones | AP25: Grupo generador. Falta detalle de sistema de ciclado junto con cantidad de baterías. | AQ25: 46007 | AR25: =IF(AQ25="","",IF(AQ25="TBD","TBD",IF(AQ25="N/A","N/A","W"&TEXT(WEEKNUM(AQ25,21),"00")&" "&YEAR(AQ25)))) -> W51 2025 | AW25: 46009 | AX25: =IF(AW25="","",IF(AW25="TBD","TBD",IF(AW25="N/A","N/A","W"&TEXT(WEEKNUM(AW25,21),"00")&" "&YEAR(AW25)))) -> W51 2025 | AY25: TSS Aprobado con Observaciones 4G | AZ25: FC Enviado a OOII | BA25: Contrato Firmado | BB25: 46162 | BD25: 46132 | BE25: =IF(BD25="","",IF(BD25="TBD","TBD",IF(BD25="N/A","N/A","W"&TEXT(WEEKNUM(BD25,21),"00")&" "&YEAR(BD25)))) -> W17 2026 | BF25: 46134 | BG25: =IF(BF25="","",IF(BF25="TBD","TBD",IF(BF25="N/A","N/A","W"&TEXT(WEEKNUM(BF25,21),"00")&" "&YEAR(BF25)))) -> W17 2026 | BH25: =+IF(BF25="",0,(BF25-BD25)) -> 2 | BI25: Ing Aprobada Con Observaciones | BJ25: Sitio Off grid con generador. Los soportes satelitales deben instalarse con total despeje hacia arriba (de ser necesario, adosar los soportes satelitales en la punta de los soportes RF de Claro). | BK25: 46149 | BL25: =IF(BK25="","",IF(BK25="TBD","TBD",IF(BK25="N/A","N/A","W"&TEXT(WEEKNUM(BK25,21),"00")&" "&YEAR(BK25)))) -> W19 2026 | BM25: Ing Aprobada | BO25: 46138 | BP25: =IF(BO25="","",IF(BO25="TBD","TBD",IF(BO25="N/A","N/A","W"&TEXT(WEEKNUM(BO25,21),"00")&" "&YEAR(BO25)))) -> W17 2026 | BQ25: Ing Aprobada | BR25: Aprobado | BS25: 46139 | BT25: =IF(BS25="","",IF(BS25="TBD","TBD",IF(BS25="N/A","N/A","W"&TEXT(WEEKNUM(BS25,21),"00")&" "&YEAR(BS25)))) -> W18 2026 | BU25: Ing Aprobada | BV25: Sitio OFFGRID, Sin observaciones | BW25: 46135 | BX25: =IF(BW25="","",IF(BW25="TBD","TBD",IF(BW25="N/A","N/A","W"&TEXT(WEEKNUM(BW25,21),"00")&" "&YEAR(BW25)))) -> W17 2026 | BY25: 46149 | BZ25: =IF(BY25="","",IF(BY25="TBD","TBD",IF(BY25="N/A","N/A","W"&TEXT(WEEKNUM(BY25,21),"00")&" "&YEAR(BY25)))) -> W19 2026 | CA25: Ing Aprobada Con Observaciones 4G | CB25: Finalizadas | CC25: Iniciadas | CF25: 46178 | CH25: 46180 | CI25: =IF(CH25="","",IF(CH25="TBD","TBD",IF(CH25="N/A","N/A","W"&TEXT(WEEKNUM(CH25,21),"00")&" "&YEAR(CH25)))) -> W23 2026 | CJ25: 46183 | CK25: =IF(CJ25="","",IF(CJ25="TBD","TBD",IF(CJ25="N/A","N/A","W"&TEXT(WEEKNUM(CJ25,21),"00")&" "&YEAR(CJ25)))) -> W24 2026 | CL25: =+IF(CJ25="",0,(CJ25-CH25)) -> 3 | CM25: As Built Aprobado con Observaciones | CN25: OBSERVACIONES - INFORME FOTOGRAFICO El herraje instalado en el poste TDAyF está colocado incorrectamente, implementación deberá instalarlo adecuadamente. OBSERVACIONES - PLANOS Sitio Off grid con generador. Se observa complicación para ingresar el generador al sitio. | CO25: 46181 | CP25: =IF(CO25="","",IF(CO25="TBD","TBD",IF(CO25="N/A","N/A","W"&TEXT(WEEKNUM(CO25,21),"00")&" "&YEAR(CO25)))) -> W24 2026 | CQ25: As Built Aprobado | CR25: Sin observaciones. | CS25: 46181 | CT25: =IF(CS25="","",IF(CS25="TBD","TBD",IF(CS25="N/A","N/A","W"&TEXT(WEEKNUM(CS25,21),"00")&" "&YEAR(CS25)))) -> W24 2026 | CU25: As Built Aprobado | CV25: 1.- No se observa TDA. | CW25: 46182 | CX25: =IF(CW25="","",IF(CW25="TBD","TBD",IF(CW25="N/A","N/A","W"&TEXT(WEEKNUM(CW25,21),"00")&" "&YEAR(CW25)))) -> W24 2026 | CY25: As Built Aprobado | CZ25: Sin observaciones, sitio OffGrid. - Gabinete tipo TDAYF será proporcionado por Claro a la implementación del sitio. | DA25: 46181 | DB25: =IF(DA25="","",IF(DA25="TBD","TBD",IF(DA25="N/A","N/A","W"&TEXT(WEEKNUM(DA25,21),"00")&" "&YEAR(DA25)))) -> W24 2026 | DC25: 46182 | DD25: =IF(DC25="","",IF(DC25="TBD","TBD",IF(DC25="N/A","N/A","W"&TEXT(WEEKNUM(DC25,21),"00")&" "&YEAR(DC25)))) -> W24 2026 | DE25: As Built Aprobado con Observaciones 4G | DG25: Gabinete Huawei | DK25: Starlink | DL25: Pendiente | DQ25: Huawei | EB25: Construido 4G | EF25: 46203 | EH25: OI-Inmobiliaria | EI25: Pendiente de negociar el área necesaria para la instalación de los paneles solares. @Tovar Teran Fiorella favor tu ayuda. | EJ25: =K25&AY25&CA25&DE25&DT25&DW25 -> VigenteTSS Aprobado con Observaciones 4GIng Aprobada Con Observaciones 4GAs Built Aprobado con Observaciones 4G
A26: =IFERROR(IF(VLOOKUP(B26,SEARCH!A:A,1,0)=B26,"OK",""),"") | B26: 03_463 | C26: Copiapo Juan Antonio Rios | D26: 3 | E26: -27.3711 | F26: -70.3309 | G26: Atacama | H26: Copiapó | I26: CHANARCILLO 969 COPIAPO | J26: Fase 1 | K26: Vigente | L26: No aplica | M26: Sitio Recibido | O26: ATC | P26: Colo | R26: MONOPOSTE | S26: 14 | T26: 151648 | U26: 45131 | V26: =IF(U26="","",IF(U26="TBD","TBD",IF(U26="N/A","N/A","W"&TEXT(WEEKNUM(U26,21),"00")&" "&YEAR(U26)))) -> W30 2023 | W26: 45166 | Y26: =IF(X26="","",IF(X26="TBD","TBD",IF(X26="N/A","N/A","W"&TEXT(WEEKNUM(X26,21),"00")&" "&YEAR(X26)))) | AA26: 45168 | AB26: =+IF(Z26="",0,AA26-Z26) -> 0 | AC26: TSS Aprobado | AE26: 45170 | AF26: =IF(AE26="","",IF(AE26="TBD","TBD",IF(AE26="N/A","N/A","W"&TEXT(WEEKNUM(AE26,21),"00")&" "&YEAR(AE26)))) -> W35 2023 | AG26: TSS Aprobado | AI26: 45168 | AJ26: =IF(AI26="","",IF(AI26="TBD","TBD",IF(AI26="N/A","N/A","W"&TEXT(WEEKNUM(AI26,21),"00")&" "&YEAR(AI26)))) -> W35 2023 | AK26: TSS Aprobado | AM26: 45169 | AN26: =IF(AM26="","",IF(AM26="TBD","TBD",IF(AM26="N/A","N/A","W"&TEXT(WEEKNUM(AM26,21),"00")&" "&YEAR(AM26)))) -> W35 2023 | AO26: TSS Aprobado | AQ26: 45163 | AR26: =IF(AQ26="","",IF(AQ26="TBD","TBD",IF(AQ26="N/A","N/A","W"&TEXT(WEEKNUM(AQ26,21),"00")&" "&YEAR(AQ26)))) -> W34 2023 | AW26: 45170 | AX26: =IF(AW26="","",IF(AW26="TBD","TBD",IF(AW26="N/A","N/A","W"&TEXT(WEEKNUM(AW26,21),"00")&" "&YEAR(AW26)))) -> W35 2023 | AY26: TSS Aprobado 4G | AZ26: FC Enviado a OOII | BA26: Contrato Firmado | BB26: 45525 | BD26: 45526 | BE26: =IF(BD26="","",IF(BD26="TBD","TBD",IF(BD26="N/A","N/A","W"&TEXT(WEEKNUM(BD26,21),"00")&" "&YEAR(BD26)))) -> W34 2024 | BG26: =IF(BF26="","",IF(BF26="TBD","TBD",IF(BF26="N/A","N/A","W"&TEXT(WEEKNUM(BF26,21),"00")&" "&YEAR(BF26)))) | BH26: =+IF(BF26="",0,(BF26-BD26)) -> 0 | BI26: Ing Aprobada | BJ26: Rev.2 12-09: Aprobado Se levantan las observaciones indicadasFaltó detalle del soporte MMOO pero se valida segun lo declarado en plano de elevación de la torre, por favor agregar detalle en el plano Asbuilt. | BK26: 45547 | BL26: =IF(BK26="","",IF(BK26="TBD","TBD",IF(BK26="N/A","N/A","W"&TEXT(WEEKNUM(BK26,21),"00")&" "&YEAR(BK26)))) -> W37 2024 | BM26: Ing Aprobada | BN26: la RRU esta en la posición de la antena y viceversa | BO26: 45548 | BP26: =IF(BO26="","",IF(BO26="TBD","TBD",IF(BO26="N/A","N/A","W"&TEXT(WEEKNUM(BO26,21),"00")&" "&YEAR(BO26)))) -> W37 2024 | BQ26: Ing Aprobada | BS26: 45547 | BT26: =IF(BS26="","",IF(BS26="TBD","TBD",IF(BS26="N/A","N/A","W"&TEXT(WEEKNUM(BS26,21),"00")&" "&YEAR(BS26)))) -> W37 2024 | BU26: Ing Aprobada | BV26: Area Proyectada 2x1,5 mts Acometida electrica BT Trifasica aerea proyectada (L=15 mts) desde poste referencia N° 006859 Linea electrica proyectada trifasica canalizada por fachada de muro (5X Superflex) + Tramo subterraneo (4x8AWG) (L= 40mts) TDAyF + Gabinete PCC + Gabiente banco baterias proyectado Malla Tierra proyectada para Sitio | BW26: 45531 | BX26: =IF(BW26="","",IF(BW26="TBD","TBD",IF(BW26="N/A","N/A","W"&TEXT(WEEKNUM(BW26,21),"00")&" "&YEAR(BW26)))) -> W35 2024 | BY26: 45548 | BZ26: =IF(BY26="","",IF(BY26="TBD","TBD",IF(BY26="N/A","N/A","W"&TEXT(WEEKNUM(BY26,21),"00")&" "&YEAR(BY26)))) -> W37 2024 | CA26: Ing Aprobada 4G | CB26: Finalizadas | CC26: Finalizadas | CF26: 45588 | CH26: 45588 | CI26: =IF(CH26="","",IF(CH26="TBD","TBD",IF(CH26="N/A","N/A","W"&TEXT(WEEKNUM(CH26,21),"00")&" "&YEAR(CH26)))) -> W43 2024 | CK26: =IF(CJ26="","",IF(CJ26="TBD","TBD",IF(CJ26="N/A","N/A","W"&TEXT(WEEKNUM(CJ26,21),"00")&" "&YEAR(CJ26)))) | CL26: =+IF(CJ26="",0,(CJ26-CH26)) -> 0 | CM26: As Built Aprobado | CN26: INFORME FOTOGRÁFICO 23-10: Aprobado Se validan fotografias con lo proyectado en planimetria. PLANOS AS BUILT 23-10: Aprobado Se validan planos. | CO26: 45588 | CP26: =IF(CO26="","",IF(CO26="TBD","TBD",IF(CO26="N/A","N/A","W"&TEXT(WEEKNUM(CO26,21),"00")&" "&YEAR(CO26)))) -> W43 2024 | CQ26: As Built Aprobado | CR26: Sin Observaciones | CS26: 45590 | CT26: =IF(CS26="","",IF(CS26="TBD","TBD",IF(CS26="N/A","N/A","W"&TEXT(WEEKNUM(CS26,21),"00")&" "&YEAR(CS26)))) -> W43 2024 | CU26: As Built Aprobado | CW26: 45588 | CX26: =IF(CW26="","",IF(CW26="TBD","TBD",IF(CW26="N/A","N/A","W"&TEXT(WEEKNUM(CW26,21),"00")&" "&YEAR(CW26)))) -> W43 2024 | CY26: As Built Aprobado con Observaciones | CZ26: REV1 23-10-2024 Sitio con Energía provisoria 3x6A Pendiente TE1 N° de medidor N° Cliente Informe conexión energía definitiva Contrato de suministro eléctrico | DA26: 45588 | DB26: =IF(DA26="","",IF(DA26="TBD","TBD",IF(DA26="N/A","N/A","W"&TEXT(WEEKNUM(DA26,21),"00")&" "&YEAR(DA26)))) -> W43 2024 | DC26: 45590 | DD26: =IF(DC26="","",IF(DC26="TBD","TBD",IF(DC26="N/A","N/A","W"&TEXT(WEEKNUM(DC26,21),"00")&" "&YEAR(DC26)))) -> W43 2024 | DE26: As Built Aprobado con Observaciones 4G | DG26: Gabinete Huawei | DH26: 0 | DK26: FO | DL26: ODF Instalado | DN26: 45735 | DO26: 45735 | DQ26: Huawei | DS26: 45748 | DT26: Integrado | DV26: 45748 | DW26: On Air | DZ26: Contrato Holistico | EA26: Pagado con OC 4500187147 | EB26: On Air 4G | EC26: Plan 2024 | EI26: 0 | EJ26: =K26&AY26&CA26&DE26&DT26&DW26 -> VigenteTSS Aprobado 4GIng Aprobada 4GAs Built Aprobado con Observaciones 4GIntegradoOn Air
A27: =IFERROR(IF(VLOOKUP(B27,SEARCH!A:A,1,0)=B27,"OK",""),"") | B27: 04_038 | C27: Prieto - Vasquez | D27: 4 | E27: -29.8811 | F27: -71.2526 | G27: Coquimbo | H27: La Serena | I27: Juan José Latorre Sitio Nº 6 Compañía Baja, Coquimbo, Coquimbo Chile | J27: Fase 2 | K27: Vigente | L27: No aplica | M27: 7 | O27: ATC | P27: Colo | R27: MONOPOSTE | S27: 15 | T27: 154327 | U27: 45131 | V27: =IF(U27="","",IF(U27="TBD","TBD",IF(U27="N/A","N/A","W"&TEXT(WEEKNUM(U27,21),"00")&" "&YEAR(U27)))) -> W30 2023 | W27: 45166 | Y27: =IF(X27="","",IF(X27="TBD","TBD",IF(X27="N/A","N/A","W"&TEXT(WEEKNUM(X27,21),"00")&" "&YEAR(X27)))) | AA27: 45168 | AB27: =+IF(Z27="",0,AA27-Z27) -> 0 | AC27: TSS Aprobado | AE27: 45170 | AF27: =IF(AE27="","",IF(AE27="TBD","TBD",IF(AE27="N/A","N/A","W"&TEXT(WEEKNUM(AE27,21),"00")&" "&YEAR(AE27)))) -> W35 2023 | AG27: TSS Aprobado | AI27: 45168 | AJ27: =IF(AI27="","",IF(AI27="TBD","TBD",IF(AI27="N/A","N/A","W"&TEXT(WEEKNUM(AI27,21),"00")&" "&YEAR(AI27)))) -> W35 2023 | AK27: TSS Aprobado | AL27: 1. Coordenadas Google Earth: OK | AM27: 45169 | AN27: =IF(AM27="","",IF(AM27="TBD","TBD",IF(AM27="N/A","N/A","W"&TEXT(WEEKNUM(AM27,21),"00")&" "&YEAR(AM27)))) -> W35 2023 | AO27: TSS Aprobado | AQ27: 45170 | AR27: =IF(AQ27="","",IF(AQ27="TBD","TBD",IF(AQ27="N/A","N/A","W"&TEXT(WEEKNUM(AQ27,21),"00")&" "&YEAR(AQ27)))) -> W35 2023 | AW27: 45170 | AX27: =IF(AW27="","",IF(AW27="TBD","TBD",IF(AW27="N/A","N/A","W"&TEXT(WEEKNUM(AW27,21),"00")&" "&YEAR(AW27)))) -> W35 2023 | AY27: TSS Aprobado 4G | AZ27: FC Enviado a OOII | BA27: Contrato Firmado | BB27: 45729 | BC27: 45810 | BD27: 45811 | BE27: =IF(BD27="","",IF(BD27="TBD","TBD",IF(BD27="N/A","N/A","W"&TEXT(WEEKNUM(BD27,21),"00")&" "&YEAR(BD27)))) -> W23 2025 | BF27: 45814 | BG27: =IF(BF27="","",IF(BF27="TBD","TBD",IF(BF27="N/A","N/A","W"&TEXT(WEEKNUM(BF27,21),"00")&" "&YEAR(BF27)))) -> W23 2025 | BH27: =+IF(BF27="",0,(BF27-BD27)) -> 3 | BI27: Ing Aprobada | BJ27: Aprobado. Radier 2,0 x 1,5 m Conduit de energía de 1 1 /4", ATC garantiza cumplimiento de norma RIC N°4 de energía. Soportes y EPC de acuerdo a estándar, canalización FO 2", ductera 4 x 110 mm ATC indica que en caso que las antenas no entren dentro del Radomo, ATC es responsable de realizar la modificación correspondiente. | BK27: 45811 | BL27: 45733 | BM27: Ing Aprobada | BN27: Aclarado el sitio, diseño según HLD 21 3 RRU 5513w + 3 antena ADU4518R6v06 | BO27: 45799 | BP27: =IF(BO27="","",IF(BO27="TBD","TBD",IF(BO27="N/A","N/A","W"&TEXT(WEEKNUM(BO27,21),"00")&" "&YEAR(BO27)))) -> W21 2025 | BQ27: Ing Aprobada | BR27: "CHECKLIST SITIO" 1. Coordenadas Google Earth: OK 2. Nemonico: 04_038 3. Tipo de estructura: Monopolo / Colocalizada 4. Altura Torre: OK 5. Altura RF: OK 6. Tipo de Soporte: H 3000 7. PGB Altura: OK 8. PGB Piso: OK 9 Disponibilida de recorrido Power: OK 10. EPC Aerea; OK 11 EPC Piso: N/A 12 Rodomo: N/A 13. Energia Provisoria: NO 14. Disponibilidad LTE / 5G en Torre OK 15. Disponibilidad de LTE / 5G Piso: OK 16. Requiere Andamios: SI 17. Antenas con Plan de RF: OK 18: Tronera: N/A 19. Porta Feeders: OK 20_ GPS: OK 21. Az con Plan de RF: OK Observaciones : | BS27: 45799 | BT27: =IF(BS27="","",IF(BS27="TBD","TBD",IF(BS27="N/A","N/A","W"&TEXT(WEEKNUM(BS27,21),"00")&" "&YEAR(BS27)))) -> W21 2025 | BU27: Ing Aprobada | BV27: 17-03-2025: Observado V1 - Validar configuración FC con RF. CORREGIR: - Proyección antena GPS (Porta Feeders)= H=4m Distancia GPS= ?m (Recorrido desde el Gabinete superior hasta la antena GPS) 3 Antenas:ADU4518R6v06 (1365 mm) 3 RRU 5513w (1900+AWS) 3 AAU5339W (5G 3.5) - Ruteo por Porta Feeders: SI-OK | BW27: 45733 | BX27: =IF(BW27="","",IF(BW27="TBD","TBD",IF(BW27="N/A","N/A","W"&TEXT(WEEKNUM(BW27,21),"00")&" "&YEAR(BW27)))) -> W12 2025 | BY27: 45811 | BZ27: =IF(BY27="","",IF(BY27="TBD","TBD",IF(BY27="N/A","N/A","W"&TEXT(WEEKNUM(BY27,21),"00")&" "&YEAR(BY27)))) -> W23 2025 | CA27: Ing Aprobada 4G | CB27: Finalizadas | CC27: Finalizadas | CD27: SI | CF27: 45818 | CG27: 45890 | CH27: 45890 | CI27: =IF(CH27="","",IF(CH27="TBD","TBD",IF(CH27="N/A","N/A","W"&TEXT(WEEKNUM(CH27,21),"00")&" "&YEAR(CH27)))) -> W34 2025 | CJ27: 45894 | CK27: =IF(CJ27="","",IF(CJ27="TBD","TBD",IF(CJ27="N/A","N/A","W"&TEXT(WEEKNUM(CJ27,21),"00")&" "&YEAR(CJ27)))) -> W35 2025 | CL27: =+IF(CJ27="",0,(CJ27-CH27)) -> 4 | CM27: As built Aprobado Con Observacioes | CN27: Aprobado con comentarios La escalerilla del radier es más larga que lo indicado en el plano, por lo que podría interferir con la instalación del gabinete. ATC no envió la foto de medición con cinta métrica solicitada en la revisión anterior para verificar lo antes señalado. ATC deberá resolver en caso de presentarse inconvenientes con la instalación del gabinete. Aprobado con comentarios. Radier 2,0 x 1,5 m Conduit de energía de 1 1 /4", ATC garantiza cumplimiento de norma RIC N°4 de energía. Soportes y EPC de acuerdo a estándar, canalización FO 2", ductera 4 x 110 mm ATC indica que en caso que las antenas no entren dentro del Radomo, ATC es responsable de realizar la modificación correspondiente. | CO27: 45849 | CP27: =IF(CO27="","",IF(CO27="TBD","TBD",IF(CO27="N/A","N/A","W"&TEXT(WEEKNUM(CO27,21),"00")&" "&YEAR(CO27)))) -> W28 2025 | CQ27: As Built Aprobado | CR27: 13/08: se corrigen observaciones | CS27: 45882 | CT27: =IF(CS27="","",IF(CS27="TBD","TBD",IF(CS27="N/A","N/A","W"&TEXT(WEEKNUM(CS27,21),"00")&" "&YEAR(CS27)))) -> W33 2025 | CU27: As Built Aprobado | CW27: 45819 | CX27: =IF(CW27="","",IF(CW27="TBD","TBD",IF(CW27="N/A","N/A","W"&TEXT(WEEKNUM(CW27,21),"00")&" "&YEAR(CW27)))) -> W24 2025 | CY27: As Built Aprobado Con Observaciones | CZ27: se valida energía provisora 3x10A trifásico para la capacidad de tecnologías + recargas de BB. | DA27: 45891 | DB27: =IF(DA27="","",IF(DA27="TBD","TBD",IF(DA27="N/A","N/A","W"&TEXT(WEEKNUM(DA27,21),"00")&" "&YEAR(DA27)))) -> W34 2025 | DC27: 45891 | DD27: =IF(DC27="","",IF(DC27="TBD","TBD",IF(DC27="N/A","N/A","W"&TEXT(WEEKNUM(DC27,21),"00")&" "&YEAR(DC27)))) -> W34 2025 | DE27: As Built Aprobado con Observaciones 4G | DG27: Gabinete Huawei | DH27: 0 | DK27: FO | DL27: ODF Instalado | DN27: 45967 | DO27: 45967 | DQ27: Huawei | DU27: 45894 | DV27: 45982 | DW27: On Air | EA27: 4500228792 | EB27: On Air 4G | ED27: Plan 2025 | EF27: W33 | EI27: 0 | EJ27: =K27&AY27&CA27&DE27&DT27&DW27 -> VigenteTSS Aprobado 4GIng Aprobada 4GAs Built Aprobado con Observaciones 4GOn Air
A28: =IFERROR(IF(VLOOKUP(B28,SEARCH!A:A,1,0)=B28,"OK",""),"") | B28: 04_041 | C28: Coquimbo Parques | D28: 4 | E28: -29.9683 | F28: -71.2544 | G28: Coquimbo | H28: Coquimbo | I28: Cerro Parque Nacional Pan de Azucar 1058 | J28: No Vigente | K28: No Vigente | L28: No aplica | M28: 7 | O28: ATC | P28: Colo | Q28: On Hold RF 21-8-2026 | R28: TORRE | S28: 9 | T28: 151332 | U28: 45131 | V28: =IF(U28="","",IF(U28="TBD","TBD",IF(U28="N/A","N/A","W"&TEXT(WEEKNUM(U28,21),"00")&" "&YEAR(U28)))) -> W30 2023 | W28: 45261 | Y28: =IF(X28="","",IF(X28="TBD","TBD",IF(X28="N/A","N/A","W"&TEXT(WEEKNUM(X28,21),"00")&" "&YEAR(X28)))) | Z28: 45264 | AA28: 45267 | AB28: =+IF(Z28="",0,AA28-Z28) -> 3 | AC28: TSS aprobado | AE28: 45264 | AF28: =IF(AE28="","",IF(AE28="TBD","TBD",IF(AE28="N/A","N/A","W"&TEXT(WEEKNUM(AE28,21),"00")&" "&YEAR(AE28)))) -> W49 2023 | AG28: TSS Aprobado | AI28: 45264 | AJ28: =IF(AI28="","",IF(AI28="TBD","TBD",IF(AI28="N/A","N/A","W"&TEXT(WEEKNUM(AI28,21),"00")&" "&YEAR(AI28)))) -> W49 2023 | AK28: TSS Aprobado | AL28: 2. Nemonico 03_546 | AM28: 45264 | AN28: =IF(AM28="","",IF(AM28="TBD","TBD",IF(AM28="N/A","N/A","W"&TEXT(WEEKNUM(AM28,21),"00")&" "&YEAR(AM28)))) -> W49 2023 | AO28: TSS Aprobado | AQ28: 45264 | AR28: =IF(AQ28="","",IF(AQ28="TBD","TBD",IF(AQ28="N/A","N/A","W"&TEXT(WEEKNUM(AQ28,21),"00")&" "&YEAR(AQ28)))) -> W49 2023 | AW28: 45264 | AX28: =IF(AW28="","",IF(AW28="TBD","TBD",IF(AW28="N/A","N/A","W"&TEXT(WEEKNUM(AW28,21),"00")&" "&YEAR(AW28)))) -> W49 2023 | AY28: TSS Aprobado 4G | AZ28: Pendiente FC | BA28: Contrato No Firmado | BB28: 45880 | BD28: 45880 | BE28: =IF(BD28="","",IF(BD28="TBD","TBD",IF(BD28="N/A","N/A","W"&TEXT(WEEKNUM(BD28,21),"00")&" "&YEAR(BD28)))) -> W33 2025 | BF28: 45883 | BG28: =IF(BF28="","",IF(BF28="TBD","TBD",IF(BF28="N/A","N/A","W"&TEXT(WEEKNUM(BF28,21),"00")&" "&YEAR(BF28)))) -> W33 2025 | BH28: =+IF(BF28="",0,(BF28-BD28)) -> 3 | BI28: Ing Aprobada | BJ28: Aprobado con comentarios. Espacio reducido para gabinete en plataforma metálica existente. ATC debe garantizar que el gabinete podrá abrir sin problemas. Porta feeders deben ser L mínimo = 350 mm No hay soporte de MMOO. Confirmar con PMO que la transmisión es por FO. Se verifica la cabida en radomo con las dimensiones entregadas en el plano. Canalización energía 1 1/4" ATC garantiza cumplimiento norma RIC. Canalización FO 2" OK EPC OK Soportes RF OK | BL28: =IF(BK28="","",IF(BK28="TBD","TBD",IF(BK28="N/A","N/A","W"&TEXT(WEEKNUM(BK28,21),"00")&" "&YEAR(BK28)))) | BM28: Ing Aprobada | BN28: Sin observaciones | BO28: 45880 | BP28: =IF(BO28="","",IF(BO28="TBD","TBD",IF(BO28="N/A","N/A","W"&TEXT(WEEKNUM(BO28,21),"00")&" "&YEAR(BO28)))) -> W33 2025 | BQ28: Ing Aprobada | BR28: "CHECKLIST SITIO" 1. Coordenadas Google Earth: OK 2. Nemonico: 04_041 3. Tipo de estructura: Monoposte/ Colocalizada 4. Altura Torre: OK 22 MTS 5. Altura RF: OK 9MTS 6. Tipo de Soporte: H 3000 7. PGB Altura: OK 8. PGB Piso: OK 9 Disponibilida de recorrido Power: OK 10. EPC Aerea; OK 11 EPC Piso: N/A 12 Rodomo: NO 13. Energia Provisoria: NO 14. Disponibilidad LTE / 5G en Torre OK 15. Disponibilidad de LTE / 5G Piso: OK 16. Requiere Andamios: por definir por el tipo de estructura e ubicacion 17. Antenas con Plan de RF: OK 18: Tronera: N/A 19. Porta Feeders: OK 20_ GPS: OK 21. Az con Plan de RF: OK Observaciones : | BS28: 45890 | BT28: =IF(BS28="","",IF(BS28="TBD","TBD",IF(BS28="N/A","N/A","W"&TEXT(WEEKNUM(BS28,21),"00")&" "&YEAR(BS28)))) -> W34 2025 | BU28: Ing Aprobada | BW28: 45889 | BX28: =IF(BW28="","",IF(BW28="TBD","TBD",IF(BW28="N/A","N/A","W"&TEXT(WEEKNUM(BW28,21),"00")&" "&YEAR(BW28)))) -> W34 2025 | BZ28: =IF(BY28="","",IF(BY28="TBD","TBD",IF(BY28="N/A","N/A","W"&TEXT(WEEKNUM(BY28,21),"00")&" "&YEAR(BY28)))) | CA28: Ing Aprobada 4G | CB28: No Iniciadas | CC28: No iniciadas | CI28: =IF(CH28="","",IF(CH28="TBD","TBD",IF(CH28="N/A","N/A","W"&TEXT(WEEKNUM(CH28,21),"00")&" "&YEAR(CH28)))) | CK28: =IF(CJ28="","",IF(CJ28="TBD","TBD",IF(CJ28="N/A","N/A","W"&TEXT(WEEKNUM(CJ28,21),"00")&" "&YEAR(CJ28)))) | CL28: =+IF(CJ28="",0,(CJ28-CH28)) -> 0 | CM28: As Built No Recibido | CP28: =IF(CO28="","",IF(CO28="TBD","TBD",IF(CO28="N/A","N/A","W"&TEXT(WEEKNUM(CO28,21),"00")&" "&YEAR(CO28)))) | CQ28: As Built No Recibido | CT28: =IF(CS28="","",IF(CS28="TBD","TBD",IF(CS28="N/A","N/A","W"&TEXT(WEEKNUM(CS28,21),"00")&" "&YEAR(CS28)))) | CU28: As Built No Recibido | CX28: =IF(CW28="","",IF(CW28="TBD","TBD",IF(CW28="N/A","N/A","W"&TEXT(WEEKNUM(CW28,21),"00")&" "&YEAR(CW28)))) | CY28: As Built No Recibido | DB28: =IF(DA28="","",IF(DA28="TBD","TBD",IF(DA28="N/A","N/A","W"&TEXT(WEEKNUM(DA28,21),"00")&" "&YEAR(DA28)))) | DD28: =IF(DC28="","",IF(DC28="TBD","TBD",IF(DC28="N/A","N/A","W"&TEXT(WEEKNUM(DC28,21),"00")&" "&YEAR(DC28)))) | DE28: As Built No Recibido | DG28: Gabinete Huawei | DK28: FO | DL28: Poste | DQ28: Huawei | EA28: 4500228792 | EB28: No Vigente - Detenidos | ED28: Plan 2025 | EI28: 0 | EJ28: =K28&AY28&CA28&DE28&DT28&DW28 -> No VigenteTSS Aprobado 4GIng Aprobada 4GAs Built No Recibido
A29: =IFERROR(IF(VLOOKUP(B29,SEARCH!A:A,1,0)=B29,"OK",""),"") | B29: 04_774 | C29: Monte Patria Subercaseaux | D29: 4 | E29: -30.6866 | F29: -70.9647 | G29: Coquimbo | H29: Monte Patria | I29: Lago Laf Quen S/N Loteo Prealito, Ovalle, Coquimbo Chile | J29: On Hold | K29: No Vigente | L29: No aplica | O29: ATC | P29: Colo | R29: TORRE | S29: 14 | T29: 153913 | U29: 45131 | V29: =IF(U29="","",IF(U29="TBD","TBD",IF(U29="N/A","N/A","W"&TEXT(WEEKNUM(U29,21),"00")&" "&YEAR(U29)))) -> W30 2023 | W29: 45166 | Y29: =IF(X29="","",IF(X29="TBD","TBD",IF(X29="N/A","N/A","W"&TEXT(WEEKNUM(X29,21),"00")&" "&YEAR(X29)))) | AA29: 45168 | AB29: =+IF(Z29="",0,AA29-Z29) -> 0 | AC29: TSS Aprobado | AE29: 45173 | AF29: =IF(AE29="","",IF(AE29="TBD","TBD",IF(AE29="N/A","N/A","W"&TEXT(WEEKNUM(AE29,21),"00")&" "&YEAR(AE29)))) -> W36 2023 | AG29: TSS Aprobado | AI29: 45168 | AJ29: =IF(AI29="","",IF(AI29="TBD","TBD",IF(AI29="N/A","N/A","W"&TEXT(WEEKNUM(AI29,21),"00")&" "&YEAR(AI29)))) -> W35 2023 | AK29: TSS Aprobado | AM29: 45169 | AN29: =IF(AM29="","",IF(AM29="TBD","TBD",IF(AM29="N/A","N/A","W"&TEXT(WEEKNUM(AM29,21),"00")&" "&YEAR(AM29)))) -> W35 2023 | AO29: TSS Aprobado | AQ29: 45170 | AR29: =IF(AQ29="","",IF(AQ29="TBD","TBD",IF(AQ29="N/A","N/A","W"&TEXT(WEEKNUM(AQ29,21),"00")&" "&YEAR(AQ29)))) -> W35 2023 | AW29: 45177 | AX29: =IF(AW29="","",IF(AW29="TBD","TBD",IF(AW29="N/A","N/A","W"&TEXT(WEEKNUM(AW29,21),"00")&" "&YEAR(AW29)))) -> W36 2023 | AY29: TSS Aprobado 4G | AZ29: FC Enviado a OOII | BA29: Contrato No Firmado | BE29: =IF(BD29="","",IF(BD29="TBD","TBD",IF(BD29="N/A","N/A","W"&TEXT(WEEKNUM(BD29,21),"00")&" "&YEAR(BD29)))) | BG29: =IF(BF29="","",IF(BF29="TBD","TBD",IF(BF29="N/A","N/A","W"&TEXT(WEEKNUM(BF29,21),"00")&" "&YEAR(BF29)))) | BH29: =+IF(BF29="",0,(BF29-BD29)) -> 0 | BI29: Ing No Recibida | BL29: =IF(BK29="","",IF(BK29="TBD","TBD",IF(BK29="N/A","N/A","W"&TEXT(WEEKNUM(BK29,21),"00")&" "&YEAR(BK29)))) | BM29: Ing No Recibida | BP29: =IF(BO29="","",IF(BO29="TBD","TBD",IF(BO29="N/A","N/A","W"&TEXT(WEEKNUM(BO29,21),"00")&" "&YEAR(BO29)))) | BQ29: Ing No Recibida | BT29: =IF(BS29="","",IF(BS29="TBD","TBD",IF(BS29="N/A","N/A","W"&TEXT(WEEKNUM(BS29,21),"00")&" "&YEAR(BS29)))) | BU29: Ing No Recibida | BX29: =IF(BW29="","",IF(BW29="TBD","TBD",IF(BW29="N/A","N/A","W"&TEXT(WEEKNUM(BW29,21),"00")&" "&YEAR(BW29)))) | BZ29: =IF(BY29="","",IF(BY29="TBD","TBD",IF(BY29="N/A","N/A","W"&TEXT(WEEKNUM(BY29,21),"00")&" "&YEAR(BY29)))) | CA29: Ing No Recibida 4G | CB29: No Iniciadas | CC29: No iniciadas | CI29: =IF(CH29="","",IF(CH29="TBD","TBD",IF(CH29="N/A","N/A","W"&TEXT(WEEKNUM(CH29,21),"00")&" "&YEAR(CH29)))) | CK29: =IF(CJ29="","",IF(CJ29="TBD","TBD",IF(CJ29="N/A","N/A","W"&TEXT(WEEKNUM(CJ29,21),"00")&" "&YEAR(CJ29)))) | CL29: =+IF(CJ29="",0,(CJ29-CH29)) -> 0 | CM29: As Built No Recibido | CP29: =IF(CO29="","",IF(CO29="TBD","TBD",IF(CO29="N/A","N/A","W"&TEXT(WEEKNUM(CO29,21),"00")&" "&YEAR(CO29)))) | CQ29: As Built No Recibido | CT29: =IF(CS29="","",IF(CS29="TBD","TBD",IF(CS29="N/A","N/A","W"&TEXT(WEEKNUM(CS29,21),"00")&" "&YEAR(CS29)))) | CU29: As Built No Recibido | CX29: =IF(CW29="","",IF(CW29="TBD","TBD",IF(CW29="N/A","N/A","W"&TEXT(WEEKNUM(CW29,21),"00")&" "&YEAR(CW29)))) | CY29: As Built No Recibido | DB29: =IF(DA29="","",IF(DA29="TBD","TBD",IF(DA29="N/A","N/A","W"&TEXT(WEEKNUM(DA29,21),"00")&" "&YEAR(DA29)))) | DD29: =IF(DC29="","",IF(DC29="TBD","TBD",IF(DC29="N/A","N/A","W"&TEXT(WEEKNUM(DC29,21),"00")&" "&YEAR(DC29)))) | DE29: As Built No Recibido | DG29: Gabinete Huawei | DK29: FO | DL29: Pendiente | DQ29: Huawei | EB29: En Etapa de Ingeniería 4G | EI29: 0 | EJ29: =K29&AY29&CA29&DE29&DT29&DW29 -> No VigenteTSS Aprobado 4GIng No Recibida 4GAs Built No Recibido
A30: =IFERROR(IF(VLOOKUP(B30,SEARCH!A:A,1,0)=B30,"OK",""),"") | B30: 04_776 | C30: Chañaral Alto Ruta D-55 | D30: 4 | E30: -30.8812 | F30: -71.0093 | G30: Coquimbo | H30: Monte Patria | I30: HIJUELA S/N CHANARAL ALTO, MONTE PATRIA | J30: No Vigente | K30: No Vigente | L30: No aplica | O30: ATC | P30: Colo | R30: TORRE | S30: 33 m | T30: 151772 | U30: 45131 | V30: =IF(U30="","",IF(U30="TBD","TBD",IF(U30="N/A","N/A","W"&TEXT(WEEKNUM(U30,21),"00")&" "&YEAR(U30)))) -> W30 2023 | W30: 45166 | Y30: =IF(X30="","",IF(X30="TBD","TBD",IF(X30="N/A","N/A","W"&TEXT(WEEKNUM(X30,21),"00")&" "&YEAR(X30)))) | AA30: 45168 | AB30: =+IF(Z30="",0,AA30-Z30) -> 0 | AC30: TSS Aprobado | AE30: 45170 | AF30: =IF(AE30="","",IF(AE30="TBD","TBD",IF(AE30="N/A","N/A","W"&TEXT(WEEKNUM(AE30,21),"00")&" "&YEAR(AE30)))) -> W35 2023 | AG30: TSS Aprobado | AI30: 45168 | AJ30: =IF(AI30="","",IF(AI30="TBD","TBD",IF(AI30="N/A","N/A","W"&TEXT(WEEKNUM(AI30,21),"00")&" "&YEAR(AI30)))) -> W35 2023 | AK30: TSS Aprobado | AM30: 45169 | AN30: =IF(AM30="","",IF(AM30="TBD","TBD",IF(AM30="N/A","N/A","W"&TEXT(WEEKNUM(AM30,21),"00")&" "&YEAR(AM30)))) -> W35 2023 | AO30: TSS Aprobado | AQ30: 45170 | AR30: =IF(AQ30="","",IF(AQ30="TBD","TBD",IF(AQ30="N/A","N/A","W"&TEXT(WEEKNUM(AQ30,21),"00")&" "&YEAR(AQ30)))) -> W35 2023 | AW30: 45170 | AX30: =IF(AW30="","",IF(AW30="TBD","TBD",IF(AW30="N/A","N/A","W"&TEXT(WEEKNUM(AW30,21),"00")&" "&YEAR(AW30)))) -> W35 2023 | AY30: TSS Aprobado 4G | AZ30: FC Enviado a OOII | BA30: Contrato No Firmado | BE30: =IF(BD30="","",IF(BD30="TBD","TBD",IF(BD30="N/A","N/A","W"&TEXT(WEEKNUM(BD30,21),"00")&" "&YEAR(BD30)))) | BG30: =IF(BF30="","",IF(BF30="TBD","TBD",IF(BF30="N/A","N/A","W"&TEXT(WEEKNUM(BF30,21),"00")&" "&YEAR(BF30)))) | BH30: =+IF(BF30="",0,(BF30-BD30)) -> 0 | BI30: Ing No Recibida | BL30: =IF(BK30="","",IF(BK30="TBD","TBD",IF(BK30="N/A","N/A","W"&TEXT(WEEKNUM(BK30,21),"00")&" "&YEAR(BK30)))) | BM30: Ing No Recibida | BP30: =IF(BO30="","",IF(BO30="TBD","TBD",IF(BO30="N/A","N/A","W"&TEXT(WEEKNUM(BO30,21),"00")&" "&YEAR(BO30)))) | BQ30: Ing No Recibida | BT30: =IF(BS30="","",IF(BS30="TBD","TBD",IF(BS30="N/A","N/A","W"&TEXT(WEEKNUM(BS30,21),"00")&" "&YEAR(BS30)))) | BU30: Ing No Recibida | BX30: =IF(BW30="","",IF(BW30="TBD","TBD",IF(BW30="N/A","N/A","W"&TEXT(WEEKNUM(BW30,21),"00")&" "&YEAR(BW30)))) | BZ30: =IF(BY30="","",IF(BY30="TBD","TBD",IF(BY30="N/A","N/A","W"&TEXT(WEEKNUM(BY30,21),"00")&" "&YEAR(BY30)))) | CA30: Ing No Recibida 4G | CB30: No Iniciadas | CC30: No iniciadas | CI30: =IF(CH30="","",IF(CH30="TBD","TBD",IF(CH30="N/A","N/A","W"&TEXT(WEEKNUM(CH30,21),"00")&" "&YEAR(CH30)))) | CK30: =IF(CJ30="","",IF(CJ30="TBD","TBD",IF(CJ30="N/A","N/A","W"&TEXT(WEEKNUM(CJ30,21),"00")&" "&YEAR(CJ30)))) | CL30: =+IF(CJ30="",0,(CJ30-CH30)) -> 0 | CM30: As Built No Recibido | CP30: =IF(CO30="","",IF(CO30="TBD","TBD",IF(CO30="N/A","N/A","W"&TEXT(WEEKNUM(CO30,21),"00")&" "&YEAR(CO30)))) | CQ30: As Built No Recibido | CT30: =IF(CS30="","",IF(CS30="TBD","TBD",IF(CS30="N/A","N/A","W"&TEXT(WEEKNUM(CS30,21),"00")&" "&YEAR(CS30)))) | CU30: As Built No Recibido | CX30: =IF(CW30="","",IF(CW30="TBD","TBD",IF(CW30="N/A","N/A","W"&TEXT(WEEKNUM(CW30,21),"00")&" "&YEAR(CW30)))) | CY30: As Built No Recibido | DB30: =IF(DA30="","",IF(DA30="TBD","TBD",IF(DA30="N/A","N/A","W"&TEXT(WEEKNUM(DA30,21),"00")&" "&YEAR(DA30)))) | DD30: =IF(DC30="","",IF(DC30="TBD","TBD",IF(DC30="N/A","N/A","W"&TEXT(WEEKNUM(DC30,21),"00")&" "&YEAR(DC30)))) | DE30: As Built No Recibido | DG30: Gabinete Huawei | DK30: FO | DL30: Pendiente | DQ30: Huawei | EB30: En Etapa de Ingeniería 4G | EI30: 0 | EJ30: =K30&AY30&CA30&DE30&DT30&DW30 -> No VigenteTSS Aprobado 4GIng No Recibida 4GAs Built No Recibido
A31: =IFERROR(IF(VLOOKUP(B31,SEARCH!A:A,1,0)=B31,"OK",""),"") | B31: 06_081 | C31: Viña Santa Blanca | D31: 6 | E31: -34.1938 | F31: -70.7458 | G31: Libertador General Bernardo O'Higgins | H31: Rancagua | I31: Lote D Parcela 79 Fundo El Puente | J31: Fase 1 | K31: Vigente | L31: No aplica | M31: Sitio Recibido | O31: ATC | P31: Colo | R31: TORRE | S31: 27 | T31: 151552 | U31: 45131 | V31: =IF(U31="","",IF(U31="TBD","TBD",IF(U31="N/A","N/A","W"&TEXT(WEEKNUM(U31,21),"00")&" "&YEAR(U31)))) -> W30 2023 | W31: 45139 | Y31: =IF(X31="","",IF(X31="TBD","TBD",IF(X31="N/A","N/A","W"&TEXT(WEEKNUM(X31,21),"00")&" "&YEAR(X31)))) | AB31: =+IF(Z31="",0,AA31-Z31) -> 0 | AC31: TSS Aprobado | AD31: 0 | AE31: 45139 | AF31: =IF(AE31="","",IF(AE31="TBD","TBD",IF(AE31="N/A","N/A","W"&TEXT(WEEKNUM(AE31,21),"00")&" "&YEAR(AE31)))) -> W31 2023 | AG31: TSS Aprobado | AI31: 45139 | AJ31: =IF(AI31="","",IF(AI31="TBD","TBD",IF(AI31="N/A","N/A","W"&TEXT(WEEKNUM(AI31,21),"00")&" "&YEAR(AI31)))) -> W31 2023 | AK31: TSS Aprobado | AM31: 45139 | AN31: =IF(AM31="","",IF(AM31="TBD","TBD",IF(AM31="N/A","N/A","W"&TEXT(WEEKNUM(AM31,21),"00")&" "&YEAR(AM31)))) -> W31 2023 | AO31: TSS Aprobado | AQ31: 45139 | AR31: =IF(AQ31="","",IF(AQ31="TBD","TBD",IF(AQ31="N/A","N/A","W"&TEXT(WEEKNUM(AQ31,21),"00")&" "&YEAR(AQ31)))) -> W31 2023 | AW31: 45139 | AX31: =IF(AW31="","",IF(AW31="TBD","TBD",IF(AW31="N/A","N/A","W"&TEXT(WEEKNUM(AW31,21),"00")&" "&YEAR(AW31)))) -> W31 2023 | AY31: TSS Aprobado 4G | AZ31: FC Enviado a OOII | BA31: Contrato Firmado | BB31: 45194 | BC31: 45245 | BD31: 45250 | BE31: =IF(BD31="","",IF(BD31="TBD","TBD",IF(BD31="N/A","N/A","W"&TEXT(WEEKNUM(BD31,21),"00")&" "&YEAR(BD31)))) -> W47 2023 | BF31: 45253 | BG31: =IF(BF31="","",IF(BF31="TBD","TBD",IF(BF31="N/A","N/A","W"&TEXT(WEEKNUM(BF31,21),"00")&" "&YEAR(BF31)))) -> W47 2023 | BH31: =+IF(BF31="",0,(BF31-BD31)) -> 3 | BI31: Ing Aprobada | BK31: 45250 | BL31: =IF(BK31="","",IF(BK31="TBD","TBD",IF(BK31="N/A","N/A","W"&TEXT(WEEKNUM(BK31,21),"00")&" "&YEAR(BK31)))) -> W47 2023 | BM31: Ing Aprobada | BO31: 45251 | BP31: =IF(BO31="","",IF(BO31="TBD","TBD",IF(BO31="N/A","N/A","W"&TEXT(WEEKNUM(BO31,21),"00")&" "&YEAR(BO31)))) -> W47 2023 | BQ31: Ing Aprobada | BR31: 09-11-2023: Aprobado V2. Se levantan observaciones. Ausente: Antena GPS (Se debe proyectar en el PIPE TDAyF e indicar la altura) | BS31: 45251 | BT31: =IF(BS31="","",IF(BS31="TBD","TBD",IF(BS31="N/A","N/A","W"&TEXT(WEEKNUM(BS31,21),"00")&" "&YEAR(BS31)))) -> W47 2023 | BU31: Ing Aprobada | BV31: Área proyectada 3x2 mts/ Empalme trifásico proyectado con línea eléctrica aérea de 60 mts (Conductor 3x25+1x50 mm2 Calpe) con poste de conexión N° 1124681 / Unilineal Claro / aterramientos proyectados. | BW31: 45250 | BX31: =IF(BW31="","",IF(BW31="TBD","TBD",IF(BW31="N/A","N/A","W"&TEXT(WEEKNUM(BW31,21),"00")&" "&YEAR(BW31)))) -> W47 2023 | BY31: 45251 | BZ31: =IF(BY31="","",IF(BY31="TBD","TBD",IF(BY31="N/A","N/A","W"&TEXT(WEEKNUM(BY31,21),"00")&" "&YEAR(BY31)))) -> W47 2023 | CA31: Ing Aprobada 4G | CB31: Finalizadas | CC31: Finalizadas | CD31: Si | CF31: 45496 | CH31: 45496 | CI31: =IF(CH31="","",IF(CH31="TBD","TBD",IF(CH31="N/A","N/A","W"&TEXT(WEEKNUM(CH31,21),"00")&" "&YEAR(CH31)))) -> W30 2024 | CK31: =IF(CJ31="","",IF(CJ31="TBD","TBD",IF(CJ31="N/A","N/A","W"&TEXT(WEEKNUM(CJ31,21),"00")&" "&YEAR(CJ31)))) | CL31: =+IF(CJ31="",0,(CJ31-CH31)) -> 0 | CM31: As Built Aprobado con Observaciones | CN31: INFORME FOTOGRÁFICO 29-07: Aprobado con observaciones Se valida segun plano Asbuilt. Correo ATC Alejandra Bernal indica que "ATC cuenta con un equipo de Calidad donde se certifica el detalle constructivo del AS-BUILT, es el mismo que se ejecuto en terreno. " PLANOS AS BUILT 29-07: Aprobado con observaciones 1. ATC indica que dimensiones de lo solicitado en revisión 1 esta segun planimetria Asbuilt. 2. Portafeeders: Segun fotografias esta se encuenta adosada con cadenas y no con pernos U. | CO31: 45502 | CP31: =IF(CO31="","",IF(CO31="TBD","TBD",IF(CO31="N/A","N/A","W"&TEXT(WEEKNUM(CO31,21),"00")&" "&YEAR(CO31)))) -> W31 2024 | CQ31: As Built Aprobado | CR31: Sin observaciones | CS31: 45498 | CT31: =IF(CS31="","",IF(CS31="TBD","TBD",IF(CS31="N/A","N/A","W"&TEXT(WEEKNUM(CS31,21),"00")&" "&YEAR(CS31)))) -> W30 2024 | CU31: As Built Aprobado con Observaciones | CV31: INFORME FOTOGRÁFICO (PROYECCIÓN - PISO) 24-07-24: Aprobado con observaciones V2 - Alejandra Bernal envía correo donde indica y certifica el detalle constructivo del AS-BUILT, es el mismo que se ejecutó en terreno. 24-07-24: Observado V1. - Fotos con Georreferencias: NO-OK - Foto del EPC con llegada a los Feeders de la Estructura: SI-OK - Radier a nivel de piso: SI-OK - Foto con cinta métrica de las Dimensiones del radier 3x2m: NO-OK - Antena GPS debe implementarse en el EPC Aéreo: SI-OK INFORME FOTOGRÁFICO (PROYECCIÓN - ELEVACIÓN) 24-07-24: Aprobado con observaciones V2 - Alejandra Bernal envía correo donde indica y certifica el detalle constructivo del AS-BUILT, es el mismo que se ejecutó en terreno. 24-07-24: Observado V1. - Fotos con Georreferencias: NO-OK - Foto de los Feeders con llegada a los Soportes: SI-OK - Foto Panorámicas S1-S2-S3: SI-OK - Foto con cinta métrica de la altura de los soportes definida para ClaroVTR: NO-OK - Foto Dimensiones de soportes: NO-OK | CW31: 45503 | CX31: =IF(CW31="","",IF(CW31="TBD","TBD",IF(CW31="N/A","N/A","W"&TEXT(WEEKNUM(CW31,21),"00")&" "&YEAR(CW31)))) -> W31 2024 | CY31: As Built Aprobado | CZ31: REV2 07-10-2024 Sitio con Energia Trifasica definitiva Pendiente N° de Cliente | DA31: 45503 | DB31: =IF(DA31="","",IF(DA31="TBD","TBD",IF(DA31="N/A","N/A","W"&TEXT(WEEKNUM(DA31,21),"00")&" "&YEAR(DA31)))) -> W31 2024 | DC31: 45504 | DD31: =IF(DC31="","",IF(DC31="TBD","TBD",IF(DC31="N/A","N/A","W"&TEXT(WEEKNUM(DC31,21),"00")&" "&YEAR(DC31)))) -> W31 2024 | DE31: As Built Aprobado con Observaciones 4G | DG31: Gabinete Huawei | DH31: 0 | DK31: FO | DL31: ODF Instalado | DN31: 45638 | DO31: 45638 | DQ31: Huawei | DU31: 45505 | DV31: 45654 | DW31: On Air | EB31: On Air 4G | EC31: Plan 2024 | EI31: 0 | EJ31: =K31&AY31&CA31&DE31&DT31&DW31 -> VigenteTSS Aprobado 4GIng Aprobada 4GAs Built Aprobado con Observaciones 4GOn Air
A32: =IFERROR(IF(VLOOKUP(B32,SEARCH!A:A,1,0)=B32,"OK",""),"") | B32: 06_114 | C32: Coltauco Ciudad | D32: 6 | E32: -34.2622 | F32: -71.0204 | G32: Libertador General Bernardo O'Higgins | H32: Coltauco | I32: Ruta H 30 parcela 14 Sector el Molino, Rancagua, Libertador General Bernardo O'Higgins Chile | J32: On Hold | K32: No Vigente | L32: No aplica | O32: ATC | P32: Colo | R32: TORRE | S32: 42 a 46 m | T32: 153831 | U32: 45131 | V32: =IF(U32="","",IF(U32="TBD","TBD",IF(U32="N/A","N/A","W"&TEXT(WEEKNUM(U32,21),"00")&" "&YEAR(U32)))) -> W30 2023 | W32: 45166 | Y32: =IF(X32="","",IF(X32="TBD","TBD",IF(X32="N/A","N/A","W"&TEXT(WEEKNUM(X32,21),"00")&" "&YEAR(X32)))) | AA32: 45168 | AB32: =+IF(Z32="",0,AA32-Z32) -> 0 | AC32: TSS Aprobado | AE32: 45170 | AF32: =IF(AE32="","",IF(AE32="TBD","TBD",IF(AE32="N/A","N/A","W"&TEXT(WEEKNUM(AE32,21),"00")&" "&YEAR(AE32)))) -> W35 2023 | AG32: TSS Aprobado | AI32: 45168 | AJ32: =IF(AI32="","",IF(AI32="TBD","TBD",IF(AI32="N/A","N/A","W"&TEXT(WEEKNUM(AI32,21),"00")&" "&YEAR(AI32)))) -> W35 2023 | AK32: TSS Aprobado | AM32: 45169 | AN32: =IF(AM32="","",IF(AM32="TBD","TBD",IF(AM32="N/A","N/A","W"&TEXT(WEEKNUM(AM32,21),"00")&" "&YEAR(AM32)))) -> W35 2023 | AO32: TSS Aprobado | AQ32: 45170 | AR32: =IF(AQ32="","",IF(AQ32="TBD","TBD",IF(AQ32="N/A","N/A","W"&TEXT(WEEKNUM(AQ32,21),"00")&" "&YEAR(AQ32)))) -> W35 2023 | AW32: 45170 | AX32: =IF(AW32="","",IF(AW32="TBD","TBD",IF(AW32="N/A","N/A","W"&TEXT(WEEKNUM(AW32,21),"00")&" "&YEAR(AW32)))) -> W35 2023 | AY32: TSS Aprobado 4G | AZ32: FC Enviado a OOII | BA32: Contrato No Firmado | BE32: =IF(BD32="","",IF(BD32="TBD","TBD",IF(BD32="N/A","N/A","W"&TEXT(WEEKNUM(BD32,21),"00")&" "&YEAR(BD32)))) | BG32: =IF(BF32="","",IF(BF32="TBD","TBD",IF(BF32="N/A","N/A","W"&TEXT(WEEKNUM(BF32,21),"00")&" "&YEAR(BF32)))) | BH32: =+IF(BF32="",0,(BF32-BD32)) -> 0 | BI32: Ing No Recibida | BL32: =IF(BK32="","",IF(BK32="TBD","TBD",IF(BK32="N/A","N/A","W"&TEXT(WEEKNUM(BK32,21),"00")&" "&YEAR(BK32)))) | BM32: Ing No Recibida | BP32: =IF(BO32="","",IF(BO32="TBD","TBD",IF(BO32="N/A","N/A","W"&TEXT(WEEKNUM(BO32,21),"00")&" "&YEAR(BO32)))) | BQ32: Ing No Recibida | BT32: =IF(BS32="","",IF(BS32="TBD","TBD",IF(BS32="N/A","N/A","W"&TEXT(WEEKNUM(BS32,21),"00")&" "&YEAR(BS32)))) | BU32: Ing No Recibida | BX32: =IF(BW32="","",IF(BW32="TBD","TBD",IF(BW32="N/A","N/A","W"&TEXT(WEEKNUM(BW32,21),"00")&" "&YEAR(BW32)))) | BZ32: =IF(BY32="","",IF(BY32="TBD","TBD",IF(BY32="N/A","N/A","W"&TEXT(WEEKNUM(BY32,21),"00")&" "&YEAR(BY32)))) | CA32: Ing No Recibida 4G | CB32: No Iniciadas | CC32: No iniciadas | CI32: =IF(CH32="","",IF(CH32="TBD","TBD",IF(CH32="N/A","N/A","W"&TEXT(WEEKNUM(CH32,21),"00")&" "&YEAR(CH32)))) | CK32: =IF(CJ32="","",IF(CJ32="TBD","TBD",IF(CJ32="N/A","N/A","W"&TEXT(WEEKNUM(CJ32,21),"00")&" "&YEAR(CJ32)))) | CL32: =+IF(CJ32="",0,(CJ32-CH32)) -> 0 | CM32: As Built No Recibido | CP32: =IF(CO32="","",IF(CO32="TBD","TBD",IF(CO32="N/A","N/A","W"&TEXT(WEEKNUM(CO32,21),"00")&" "&YEAR(CO32)))) | CQ32: As Built No Recibido | CT32: =IF(CS32="","",IF(CS32="TBD","TBD",IF(CS32="N/A","N/A","W"&TEXT(WEEKNUM(CS32,21),"00")&" "&YEAR(CS32)))) | CU32: As Built No Recibido | CX32: =IF(CW32="","",IF(CW32="TBD","TBD",IF(CW32="N/A","N/A","W"&TEXT(WEEKNUM(CW32,21),"00")&" "&YEAR(CW32)))) | CY32: As Built No Recibido | DB32: =IF(DA32="","",IF(DA32="TBD","TBD",IF(DA32="N/A","N/A","W"&TEXT(WEEKNUM(DA32,21),"00")&" "&YEAR(DA32)))) | DD32: =IF(DC32="","",IF(DC32="TBD","TBD",IF(DC32="N/A","N/A","W"&TEXT(WEEKNUM(DC32,21),"00")&" "&YEAR(DC32)))) | DE32: As Built No Recibido | DG32: Gabinete Huawei | DK32: FO | DL32: Pendiente | DQ32: Huawei | EB32: En Etapa de Ingeniería 4G | EI32: 0 | EJ32: =K32&AY32&CA32&DE32&DT32&DW32 -> No VigenteTSS Aprobado 4GIng No Recibida 4GAs Built No Recibido
A33: =IFERROR(IF(VLOOKUP(B33,SEARCH!A:A,1,0)=B33,"OK",""),"") | B33: 06_125 | C33: Coinco Ciudad Centro | D33: 6 | E33: -34.26744 | F33: -70.94907 | G33: Libertador General Bernardo O'Higgins | H33: Coinco | I33: Libertador Bernardo O´Higgins 212 | J33: No Vigente | K33: No Vigente | L33: No aplica | O33: ATC | P33: Colo | R33: TORRE | S33: 26 | T33: 150627 | U33: 45131 | V33: =IF(U33="","",IF(U33="TBD","TBD",IF(U33="N/A","N/A","W"&TEXT(WEEKNUM(U33,21),"00")&" "&YEAR(U33)))) -> W30 2023 | W33: 45156 | Y33: =IF(X33="","",IF(X33="TBD","TBD",IF(X33="N/A","N/A","W"&TEXT(WEEKNUM(X33,21),"00")&" "&YEAR(X33)))) | Z33: 45160 | AA33: 45163 | AB33: =+IF(Z33="",0,AA33-Z33) -> 3 | AC33: TSS Aprobado | AE33: 45173 | AF33: =IF(AE33="","",IF(AE33="TBD","TBD",IF(AE33="N/A","N/A","W"&TEXT(WEEKNUM(AE33,21),"00")&" "&YEAR(AE33)))) -> W36 2023 | AG33: TSS Aprobado | AI33: 45160 | AJ33: =IF(AI33="","",IF(AI33="TBD","TBD",IF(AI33="N/A","N/A","W"&TEXT(WEEKNUM(AI33,21),"00")&" "&YEAR(AI33)))) -> W34 2023 | AK33: TSS Aprobado | AM33: 45159 | AN33: =IF(AM33="","",IF(AM33="TBD","TBD",IF(AM33="N/A","N/A","W"&TEXT(WEEKNUM(AM33,21),"00")&" "&YEAR(AM33)))) -> W34 2023 | AO33: TSS Aprobado | AQ33: 45159 | AR33: =IF(AQ33="","",IF(AQ33="TBD","TBD",IF(AQ33="N/A","N/A","W"&TEXT(WEEKNUM(AQ33,21),"00")&" "&YEAR(AQ33)))) -> W34 2023 | AW33: 45177 | AX33: =IF(AW33="","",IF(AW33="TBD","TBD",IF(AW33="N/A","N/A","W"&TEXT(WEEKNUM(AW33,21),"00")&" "&YEAR(AW33)))) -> W36 2023 | AY33: TSS Aprobado 4G | AZ33: FC Enviado a OOII | BA33: Contrato No Firmado | BE33: =IF(BD33="","",IF(BD33="TBD","TBD",IF(BD33="N/A","N/A","W"&TEXT(WEEKNUM(BD33,21),"00")&" "&YEAR(BD33)))) | BG33: =IF(BF33="","",IF(BF33="TBD","TBD",IF(BF33="N/A","N/A","W"&TEXT(WEEKNUM(BF33,21),"00")&" "&YEAR(BF33)))) | BH33: =+IF(BF33="",0,(BF33-BD33)) -> 0 | BI33: Ing No Recibida | BL33: =IF(BK33="","",IF(BK33="TBD","TBD",IF(BK33="N/A","N/A","W"&TEXT(WEEKNUM(BK33,21),"00")&" "&YEAR(BK33)))) | BM33: Ing No Recibida | BP33: =IF(BO33="","",IF(BO33="TBD","TBD",IF(BO33="N/A","N/A","W"&TEXT(WEEKNUM(BO33,21),"00")&" "&YEAR(BO33)))) | BQ33: Ing No Recibida | BT33: =IF(BS33="","",IF(BS33="TBD","TBD",IF(BS33="N/A","N/A","W"&TEXT(WEEKNUM(BS33,21),"00")&" "&YEAR(BS33)))) | BU33: Ing No Recibida | BX33: =IF(BW33="","",IF(BW33="TBD","TBD",IF(BW33="N/A","N/A","W"&TEXT(WEEKNUM(BW33,21),"00")&" "&YEAR(BW33)))) | BZ33: =IF(BY33="","",IF(BY33="TBD","TBD",IF(BY33="N/A","N/A","W"&TEXT(WEEKNUM(BY33,21),"00")&" "&YEAR(BY33)))) | CA33: Ing No Recibida 4G | CB33: No Iniciadas | CC33: No iniciadas | CI33: =IF(CH33="","",IF(CH33="TBD","TBD",IF(CH33="N/A","N/A","W"&TEXT(WEEKNUM(CH33,21),"00")&" "&YEAR(CH33)))) | CK33: =IF(CJ33="","",IF(CJ33="TBD","TBD",IF(CJ33="N/A","N/A","W"&TEXT(WEEKNUM(CJ33,21),"00")&" "&YEAR(CJ33)))) | CL33: =+IF(CJ33="",0,(CJ33-CH33)) -> 0 | CM33: As Built No Recibido | CP33: =IF(CO33="","",IF(CO33="TBD","TBD",IF(CO33="N/A","N/A","W"&TEXT(WEEKNUM(CO33,21),"00")&" "&YEAR(CO33)))) | CQ33: As Built No Recibido | CT33: =IF(CS33="","",IF(CS33="TBD","TBD",IF(CS33="N/A","N/A","W"&TEXT(WEEKNUM(CS33,21),"00")&" "&YEAR(CS33)))) | CU33: As Built No Recibido | CX33: =IF(CW33="","",IF(CW33="TBD","TBD",IF(CW33="N/A","N/A","W"&TEXT(WEEKNUM(CW33,21),"00")&" "&YEAR(CW33)))) | CY33: As Built No Recibido | DB33: =IF(DA33="","",IF(DA33="TBD","TBD",IF(DA33="N/A","N/A","W"&TEXT(WEEKNUM(DA33,21),"00")&" "&YEAR(DA33)))) | DD33: =IF(DC33="","",IF(DC33="TBD","TBD",IF(DC33="N/A","N/A","W"&TEXT(WEEKNUM(DC33,21),"00")&" "&YEAR(DC33)))) | DE33: As Built No Recibido | DG33: Gabinete Huawei | DK33: FO | DL33: Pendiente | DQ33: Huawei | EB33: En Etapa de Ingeniería 4G | EI33: 0 | EJ33: =K33&AY33&CA33&DE33&DT33&DW33 -> No VigenteTSS Aprobado 4GIng No Recibida 4GAs Built No Recibido
A34: =IFERROR(IF(VLOOKUP(B34,SEARCH!A:A,1,0)=B34,"OK",""),"") | B34: 06_140 | C34: Rancagua Los Pinares | D34: 6 | E34: -34.14606 | F34: -70.69733 | G34: Libertador General Bernardo O'Higgins | H34: Rancagua | I34: Reserva Fundo los Quilos, Hijuela II, (Rol 1411-123) | J34: On Hold | K34: No Vigente | L34: No aplica | O34: ATC | P34: Colo | R34: MONOPOSTE | S34: 16 | T34: 151426 | U34: 45131 | V34: =IF(U34="","",IF(U34="TBD","TBD",IF(U34="N/A","N/A","W"&TEXT(WEEKNUM(U34,21),"00")&" "&YEAR(U34)))) -> W30 2023 | W34: 45156 | Y34: =IF(X34="","",IF(X34="TBD","TBD",IF(X34="N/A","N/A","W"&TEXT(WEEKNUM(X34,21),"00")&" "&YEAR(X34)))) | Z34: 45160 | AA34: 45163 | AB34: =+IF(Z34="",0,AA34-Z34) -> 3 | AC34: TSS Aprobado | AE34: 45181 | AF34: =IF(AE34="","",IF(AE34="TBD","TBD",IF(AE34="N/A","N/A","W"&TEXT(WEEKNUM(AE34,21),"00")&" "&YEAR(AE34)))) -> W37 2023 | AG34: TSS Aprobado | AI34: 45160 | AJ34: =IF(AI34="","",IF(AI34="TBD","TBD",IF(AI34="N/A","N/A","W"&TEXT(WEEKNUM(AI34,21),"00")&" "&YEAR(AI34)))) -> W34 2023 | AK34: TSS Aprobado | AM34: 45159 | AN34: =IF(AM34="","",IF(AM34="TBD","TBD",IF(AM34="N/A","N/A","W"&TEXT(WEEKNUM(AM34,21),"00")&" "&YEAR(AM34)))) -> W34 2023 | AO34: TSS Aprobado | AQ34: 45159 | AR34: =IF(AQ34="","",IF(AQ34="TBD","TBD",IF(AQ34="N/A","N/A","W"&TEXT(WEEKNUM(AQ34,21),"00")&" "&YEAR(AQ34)))) -> W34 2023 | AW34: 45181 | AX34: =IF(AW34="","",IF(AW34="TBD","TBD",IF(AW34="N/A","N/A","W"&TEXT(WEEKNUM(AW34,21),"00")&" "&YEAR(AW34)))) -> W37 2023 | AY34: TSS Aprobado 4G | AZ34: FC Enviado a OOII | BA34: Contrato No Firmado | BE34: =IF(BD34="","",IF(BD34="TBD","TBD",IF(BD34="N/A","N/A","W"&TEXT(WEEKNUM(BD34,21),"00")&" "&YEAR(BD34)))) | BG34: =IF(BF34="","",IF(BF34="TBD","TBD",IF(BF34="N/A","N/A","W"&TEXT(WEEKNUM(BF34,21),"00")&" "&YEAR(BF34)))) | BH34: =+IF(BF34="",0,(BF34-BD34)) -> 0 | BI34: Ing No Recibida | BL34: =IF(BK34="","",IF(BK34="TBD","TBD",IF(BK34="N/A","N/A","W"&TEXT(WEEKNUM(BK34,21),"00")&" "&YEAR(BK34)))) | BM34: Ing No Recibida | BP34: =IF(BO34="","",IF(BO34="TBD","TBD",IF(BO34="N/A","N/A","W"&TEXT(WEEKNUM(BO34,21),"00")&" "&YEAR(BO34)))) | BQ34: Ing No Recibida | BT34: =IF(BS34="","",IF(BS34="TBD","TBD",IF(BS34="N/A","N/A","W"&TEXT(WEEKNUM(BS34,21),"00")&" "&YEAR(BS34)))) | BU34: Ing No Recibida | BX34: =IF(BW34="","",IF(BW34="TBD","TBD",IF(BW34="N/A","N/A","W"&TEXT(WEEKNUM(BW34,21),"00")&" "&YEAR(BW34)))) | BZ34: =IF(BY34="","",IF(BY34="TBD","TBD",IF(BY34="N/A","N/A","W"&TEXT(WEEKNUM(BY34,21),"00")&" "&YEAR(BY34)))) | CA34: Ing No Recibida 4G | CB34: No Iniciadas | CC34: No iniciadas | CI34: =IF(CH34="","",IF(CH34="TBD","TBD",IF(CH34="N/A","N/A","W"&TEXT(WEEKNUM(CH34,21),"00")&" "&YEAR(CH34)))) | CK34: =IF(CJ34="","",IF(CJ34="TBD","TBD",IF(CJ34="N/A","N/A","W"&TEXT(WEEKNUM(CJ34,21),"00")&" "&YEAR(CJ34)))) | CL34: =+IF(CJ34="",0,(CJ34-CH34)) -> 0 | CM34: As Built No Recibido | CP34: =IF(CO34="","",IF(CO34="TBD","TBD",IF(CO34="N/A","N/A","W"&TEXT(WEEKNUM(CO34,21),"00")&" "&YEAR(CO34)))) | CQ34: As Built No Recibido | CT34: =IF(CS34="","",IF(CS34="TBD","TBD",IF(CS34="N/A","N/A","W"&TEXT(WEEKNUM(CS34,21),"00")&" "&YEAR(CS34)))) | CU34: As Built No Recibido | CX34: =IF(CW34="","",IF(CW34="TBD","TBD",IF(CW34="N/A","N/A","W"&TEXT(WEEKNUM(CW34,21),"00")&" "&YEAR(CW34)))) | CY34: As Built No Recibido | DB34: =IF(DA34="","",IF(DA34="TBD","TBD",IF(DA34="N/A","N/A","W"&TEXT(WEEKNUM(DA34,21),"00")&" "&YEAR(DA34)))) | DD34: =IF(DC34="","",IF(DC34="TBD","TBD",IF(DC34="N/A","N/A","W"&TEXT(WEEKNUM(DC34,21),"00")&" "&YEAR(DC34)))) | DE34: As Built No Recibido | DG34: Gabinete Huawei | DK34: FO | DL34: Pendiente | DQ34: Huawei | EB34: En Etapa de Ingeniería 4G | EI34: 0 | EJ34: =K34&AY34&CA34&DE34&DT34&DW34 -> No VigenteTSS Aprobado 4GIng No Recibida 4GAs Built No Recibido
A35: =IFERROR(IF(VLOOKUP(B35,SEARCH!A:A,1,0)=B35,"OK",""),"") | B35: 06_444 | C35: Essbio Pichilemu Oriente | D35: 6 | E35: -34.400472 | F35: -71.996194 | G35: Libertador General Bernardo O'Higgins | H35: Pichilemu | I35: "Los Queltehues, Parcela #10 s/n Pichilemu, Libertador General Bernardo O'Higgins Chile " | J35: Fase 1 | K35: Vigente | L35: No aplica | M35: Sitio Recibido | O35: ATC | P35: Colo | R35: MONOPOSTE | S35: 21 | T35: 154169 | U35: 45131 | V35: =IF(U35="","",IF(U35="TBD","TBD",IF(U35="N/A","N/A","W"&TEXT(WEEKNUM(U35,21),"00")&" "&YEAR(U35)))) -> W30 2023 | W35: 45156 | Y35: =IF(X35="","",IF(X35="TBD","TBD",IF(X35="N/A","N/A","W"&TEXT(WEEKNUM(X35,21),"00")&" "&YEAR(X35)))) | Z35: 45160 | AA35: 45163 | AB35: =+IF(Z35="",0,AA35-Z35) -> 3 | AC35: TSS Aprobado | AE35: 45173 | AF35: =IF(AE35="","",IF(AE35="TBD","TBD",IF(AE35="N/A","N/A","W"&TEXT(WEEKNUM(AE35,21),"00")&" "&YEAR(AE35)))) -> W36 2023 | AG35: TSS Aprobado | AI35: 45160 | AJ35: =IF(AI35="","",IF(AI35="TBD","TBD",IF(AI35="N/A","N/A","W"&TEXT(WEEKNUM(AI35,21),"00")&" "&YEAR(AI35)))) -> W34 2023 | AK35: TSS Aprobado | AM35: 45159 | AN35: =IF(AM35="","",IF(AM35="TBD","TBD",IF(AM35="N/A","N/A","W"&TEXT(WEEKNUM(AM35,21),"00")&" "&YEAR(AM35)))) -> W34 2023 | AO35: TSS Aprobado | AQ35: 45159 | AR35: =IF(AQ35="","",IF(AQ35="TBD","TBD",IF(AQ35="N/A","N/A","W"&TEXT(WEEKNUM(AQ35,21),"00")&" "&YEAR(AQ35)))) -> W34 2023 | AW35: 45177 | AX35: =IF(AW35="","",IF(AW35="TBD","TBD",IF(AW35="N/A","N/A","W"&TEXT(WEEKNUM(AW35,21),"00")&" "&YEAR(AW35)))) -> W36 2023 | AY35: TSS Aprobado 4G | AZ35: FC Enviado a OOII | BA35: Contrato Firmado | BB35: 45475 | BD35: 45475 | BE35: =IF(BD35="","",IF(BD35="TBD","TBD",IF(BD35="N/A","N/A","W"&TEXT(WEEKNUM(BD35,21),"00")&" "&YEAR(BD35)))) -> W27 2024 | BG35: =IF(BF35="","",IF(BF35="TBD","TBD",IF(BF35="N/A","N/A","W"&TEXT(WEEKNUM(BF35,21),"00")&" "&YEAR(BF35)))) | BH35: =+IF(BF35="",0,(BF35-BD35)) -> 0 | BI35: Ing Aprobada con Observaciones | BJ35: 01-08: Aprobado con observaciones (V3) 1. Estudio de cabida: ATC no envía dimensiones del pin central ni del radomo existente por lo que no se puede verificar cabida de equipamiento, solo colocaron una nota en el plano: "EN CASO DE SER NECESARIO UNA MODIFICACION DEL RADOMO, AMERICAN TOWER ASUME LA MODIFICACION Y EL COSTO DEL MISMO." Cualquier costo asociado a no poder implementar el sitio, ATC seria el responsable. | BK35: 45505 | BL35: =IF(BK35="","",IF(BK35="TBD","TBD",IF(BK35="N/A","N/A","W"&TEXT(WEEKNUM(BK35,21),"00")&" "&YEAR(BK35)))) -> W31 2024 | BM35: Ing Aprobada | BN35: Sin comentarios | BO35: 45484 | BP35: =IF(BO35="","",IF(BO35="TBD","TBD",IF(BO35="N/A","N/A","W"&TEXT(WEEKNUM(BO35,21),"00")&" "&YEAR(BO35)))) -> W28 2024 | BQ35: Ing Aprobada | BR35: 20-08: Aprobado OBSERVACIONES ING - IMPL (Lámina 2) 22-07-2024: Observado V2 Mantiene la misma Observación. 08-07-2024: Observado V1 - Altura Antenas: 21m Corregir: Antena GPS y descripción: Proyectar GPS: En el EPC aéreo. Dist. antena GPS= ? m (Gabinete principal Superior hasta la antena) Corregir Modelo de antena en S1 y S3: 3 antenas HUAWEI: AQU4518R24v18 3 RF (RRU5513W - 1900/AWS) 3 RF (RRU5512 - 700/850) En el plano de piso proyectar Modulo de RRU tipo Blade en un solo Pipe del soporte H. Soporte H= L= 3m Router: HUAWEI. Factibilidad TX: MMOO: SI Corregir Proyección de la MMOO: Soporte MMOO Proyectado: NO-OK Altura MMOO: ? m Longitud Soporte MMOO= 1m | BS35: 45524 | BT35: =IF(BS35="","",IF(BS35="TBD","TBD",IF(BS35="N/A","N/A","W"&TEXT(WEEKNUM(BS35,21),"00")&" "&YEAR(BS35)))) -> W34 2024 | BU35: Ing Aprobada | BV35: Acometida: L= 26 mts Linea electrica= 7 mts L total= 17 mts | BW35: 45513 | BX35: =IF(BW35="","",IF(BW35="TBD","TBD",IF(BW35="N/A","N/A","W"&TEXT(WEEKNUM(BW35,21),"00")&" "&YEAR(BW35)))) -> W32 2024 | BY35: 45524 | BZ35: =IF(BY35="","",IF(BY35="TBD","TBD",IF(BY35="N/A","N/A","W"&TEXT(WEEKNUM(BY35,21),"00")&" "&YEAR(BY35)))) -> W34 2024 | CA35: Ing Aprobada con Observaciones 4G | CB35: Finalizadas | CC35: Finalizadas | CF35: 45643 | CH35: 45643 | CI35: =IF(CH35="","",IF(CH35="TBD","TBD",IF(CH35="N/A","N/A","W"&TEXT(WEEKNUM(CH35,21),"00")&" "&YEAR(CH35)))) -> W51 2024 | CJ35: 45646 | CK35: =IF(CJ35="","",IF(CJ35="TBD","TBD",IF(CJ35="N/A","N/A","W"&TEXT(WEEKNUM(CJ35,21),"00")&" "&YEAR(CJ35)))) -> W51 2024 | CL35: =+IF(CJ35="",0,(CJ35-CH35)) -> 3 | CM35: As Built Aprobado con Observaciones | CN35: 0 | CO35: 45644 | CP35: =IF(CO35="","",IF(CO35="TBD","TBD",IF(CO35="N/A","N/A","W"&TEXT(WEEKNUM(CO35,21),"00")&" "&YEAR(CO35)))) -> W51 2024 | CQ35: As Built Aprobado | CS35: 45649 | CT35: =IF(CS35="","",IF(CS35="TBD","TBD",IF(CS35="N/A","N/A","W"&TEXT(WEEKNUM(CS35,21),"00")&" "&YEAR(CS35)))) -> W52 2024 | CU35: As Built Aprobado | CV35: 24-12-2024: Aprobado V1 - Fotos con Georreferencias: SI-OK - Radier en piso 2x1,5m: SI-OK - EPC 400x100m a nivel de piso con llegada a los porta Feeders de la estructura=L= 5m: SI-OK - Fotos de los porta Feeder hasta los soportes: SI-OK - Antena GPS: Factible Implementarse en los Porta feeders=H=4 o 5 m: SI-OK - Canalización FO: SI-OK | CW35: 45650 | CX35: =IF(CW35="","",IF(CW35="TBD","TBD",IF(CW35="N/A","N/A","W"&TEXT(WEEKNUM(CW35,21),"00")&" "&YEAR(CW35)))) -> W52 2024 | CY35: As Built Aprobado | CZ35: Se registra informe de conexión de energía definitiva, falta respaldo de facturación de suministro para validación de gestión | DA35: 45915 | DB35: =IF(DA35="","",IF(DA35="TBD","TBD",IF(DA35="N/A","N/A","W"&TEXT(WEEKNUM(DA35,21),"00")&" "&YEAR(DA35)))) -> W38 2025 | DC35: 45652 | DD35: =IF(DC35="","",IF(DC35="TBD","TBD",IF(DC35="N/A","N/A","W"&TEXT(WEEKNUM(DC35,21),"00")&" "&YEAR(DC35)))) -> W52 2024 | DE35: As Built Aprobado con Observaciones 4G | DG35: Gabinete Huawei | DH35: 0 | DK35: FO | DL35: ODF Instalado | DN35: 45694 | DO35: 45694 | DQ35: Huawei | DV35: 45734 | DW35: On Air | DZ35: Contrato Holistico | EA35: Pagado con OC 4500187147 | EB35: On Air 4G | EC35: Plan 2024 | EI35: 0 | EJ35: =K35&AY35&CA35&DE35&DT35&DW35 -> VigenteTSS Aprobado 4GIng Aprobada con Observaciones 4GAs Built Aprobado con Observaciones 4GOn Air
A36: =IFERROR(IF(VLOOKUP(B36,SEARCH!A:A,1,0)=B36,"OK",""),"") | B36: 06_468 | C36: El Rabanal | D36: 6 | E36: -34.1867 | F36: -70.7327 | G36: Libertador General Bernardo O'Higgins | H36: Rancagua | I36: BLANCO ENCALADA 1315 POBLACION GRANJA ESTADIO RANCAGUA | J36: Fase 1 | K36: Vigente | L36: No aplica | M36: 1 | O36: ATC | P36: Colo | R36: MONOPOSTE | S36: 20 | T36: 153167 | U36: 45131 | V36: =IF(U36="","",IF(U36="TBD","TBD",IF(U36="N/A","N/A","W"&TEXT(WEEKNUM(U36,21),"00")&" "&YEAR(U36)))) -> W30 2023 | W36: 45156 | Y36: =IF(X36="","",IF(X36="TBD","TBD",IF(X36="N/A","N/A","W"&TEXT(WEEKNUM(X36,21),"00")&" "&YEAR(X36)))) | Z36: 45160 | AA36: 45163 | AB36: =+IF(Z36="",0,AA36-Z36) -> 3 | AC36: TSS Aprobado | AE36: 45181 | AF36: =IF(AE36="","",IF(AE36="TBD","TBD",IF(AE36="N/A","N/A","W"&TEXT(WEEKNUM(AE36,21),"00")&" "&YEAR(AE36)))) -> W37 2023 | AG36: TSS Aprobado | AI36: 45160 | AJ36: =IF(AI36="","",IF(AI36="TBD","TBD",IF(AI36="N/A","N/A","W"&TEXT(WEEKNUM(AI36,21),"00")&" "&YEAR(AI36)))) -> W34 2023 | AK36: TSS Aprobado | AM36: 45159 | AN36: =IF(AM36="","",IF(AM36="TBD","TBD",IF(AM36="N/A","N/A","W"&TEXT(WEEKNUM(AM36,21),"00")&" "&YEAR(AM36)))) -> W34 2023 | AO36: TSS Aprobado | AQ36: 45160 | AR36: =IF(AQ36="","",IF(AQ36="TBD","TBD",IF(AQ36="N/A","N/A","W"&TEXT(WEEKNUM(AQ36,21),"00")&" "&YEAR(AQ36)))) -> W34 2023 | AW36: 45181 | AX36: =IF(AW36="","",IF(AW36="TBD","TBD",IF(AW36="N/A","N/A","W"&TEXT(WEEKNUM(AW36,21),"00")&" "&YEAR(AW36)))) -> W37 2023 | AY36: TSS Aprobado 4G | AZ36: FC Enviado a OOII | BA36: Contrato Firmado | BB36: 45475 | BD36: 45475 | BE36: =IF(BD36="","",IF(BD36="TBD","TBD",IF(BD36="N/A","N/A","W"&TEXT(WEEKNUM(BD36,21),"00")&" "&YEAR(BD36)))) -> W27 2024 | BG36: =IF(BF36="","",IF(BF36="TBD","TBD",IF(BF36="N/A","N/A","W"&TEXT(WEEKNUM(BF36,21),"00")&" "&YEAR(BF36)))) | BH36: =+IF(BF36="",0,(BF36-BD36)) -> 0 | BI36: Ing Aprobada | BJ36: 08-07: Aprobado 2. El area en piso es de 2x1,5m: 3m2. | BK36: 45481 | BL36: =IF(BK36="","",IF(BK36="TBD","TBD",IF(BK36="N/A","N/A","W"&TEXT(WEEKNUM(BK36,21),"00")&" "&YEAR(BK36)))) -> W28 2024 | BM36: Ing Aprobada | BN36: Sin Comentarios | BO36: 45518 | BP36: =IF(BO36="","",IF(BO36="TBD","TBD",IF(BO36="N/A","N/A","W"&TEXT(WEEKNUM(BO36,21),"00")&" "&YEAR(BO36)))) -> W33 2024 | BQ36: Ing Aprobada | BS36: 45495 | BT36: =IF(BS36="","",IF(BS36="TBD","TBD",IF(BS36="N/A","N/A","W"&TEXT(WEEKNUM(BS36,21),"00")&" "&YEAR(BS36)))) -> W30 2024 | BU36: Ing Aprobada | BV36: REV3 06-08-2024 Acometida: 10 mts Línea Eléctrica: 20 mts L total: 20 mts | BW36: 45484 | BX36: =IF(BW36="","",IF(BW36="TBD","TBD",IF(BW36="N/A","N/A","W"&TEXT(WEEKNUM(BW36,21),"00")&" "&YEAR(BW36)))) -> W28 2024 | BY36: 45518 | BZ36: =IF(BY36="","",IF(BY36="TBD","TBD",IF(BY36="N/A","N/A","W"&TEXT(WEEKNUM(BY36,21),"00")&" "&YEAR(BY36)))) -> W33 2024 | CA36: Ing Aprobada 4G | CB36: Finalizadas | CC36: Finalizadas | CF36: 45567 | CH36: 45567 | CI36: =IF(CH36="","",IF(CH36="TBD","TBD",IF(CH36="N/A","N/A","W"&TEXT(WEEKNUM(CH36,21),"00")&" "&YEAR(CH36)))) -> W40 2024 | CK36: =IF(CJ36="","",IF(CJ36="TBD","TBD",IF(CJ36="N/A","N/A","W"&TEXT(WEEKNUM(CJ36,21),"00")&" "&YEAR(CJ36)))) | CL36: =+IF(CJ36="",0,(CJ36-CH36)) -> 0 | CM36: As Built Aprobado con Observaciones | CN36: INFORME FOTOGRÁFICO Rev.1 03-10: Aprobado con observaciones 1. Se valida segun plano Asbuilt y fotografias adicionales fuera del informe fotografico. PLANOS AS BUILT Rev.1 Aprobado 1. Se valida planimetria. | CO36: 45568 | CP36: =IF(CO36="","",IF(CO36="TBD","TBD",IF(CO36="N/A","N/A","W"&TEXT(WEEKNUM(CO36,21),"00")&" "&YEAR(CO36)))) -> W40 2024 | CQ36: As Built Aprobado | CR36: Sin observacion | CS36: 45568 | CT36: =IF(CS36="","",IF(CS36="TBD","TBD",IF(CS36="N/A","N/A","W"&TEXT(WEEKNUM(CS36,21),"00")&" "&YEAR(CS36)))) -> W40 2024 | CU36: As Built Aprobado | CW36: 45569 | CX36: =IF(CW36="","",IF(CW36="TBD","TBD",IF(CW36="N/A","N/A","W"&TEXT(WEEKNUM(CW36,21),"00")&" "&YEAR(CW36)))) -> W40 2024 | CY36: As Built Aprobado | DA36: 45569 | DB36: =IF(DA36="","",IF(DA36="TBD","TBD",IF(DA36="N/A","N/A","W"&TEXT(WEEKNUM(DA36,21),"00")&" "&YEAR(DA36)))) -> W40 2024 | DC36: 45666 | DD36: =IF(DC36="","",IF(DC36="TBD","TBD",IF(DC36="N/A","N/A","W"&TEXT(WEEKNUM(DC36,21),"00")&" "&YEAR(DC36)))) -> W02 2025 | DE36: As Built Aprobado 4G | DG36: Gabinete Huawei | DH36: 0 | DK36: FO | DL36: ODF Instalado | DN36: 45701 | DO36: 45701 | DQ36: Huawei | DS36: 45715 | DT36: Integrado | DV36: 45716 | DW36: On Air | DZ36: Contrato Holistico | EA36: Pagado con OC 4500187147 | EB36: On Air 4G | EC36: Plan 2024 | EI36: 0 | EJ36: =K36&AY36&CA36&DE36&DT36&DW36 -> VigenteTSS Aprobado 4GIng Aprobada 4GAs Built Aprobado 4GIntegradoOn Air
A37: =IFERROR(IF(VLOOKUP(B37,SEARCH!A:A,1,0)=B37,"OK",""),"") | B37: 06_601 | C37: By Pass Ruta 5 Rancagua | D37: 6 | E37: -34.1331 | F37: -70.764 | G37: Libertador General Bernardo O'Higgins | H37: Graneros | I37: Parcela 9, La Moranina, Rancagua | J37: Rutas Fase 1 | K37: Vigente | L37: No aplica | M37: 3 | O37: ATC | P37: Colo | R37: TORRE | S37: 33 | T37: 151833 | U37: 45131 | V37: =IF(U37="","",IF(U37="TBD","TBD",IF(U37="N/A","N/A","W"&TEXT(WEEKNUM(U37,21),"00")&" "&YEAR(U37)))) -> W30 2023 | W37: 45258 | Y37: =IF(X37="","",IF(X37="TBD","TBD",IF(X37="N/A","N/A","W"&TEXT(WEEKNUM(X37,21),"00")&" "&YEAR(X37)))) | Z37: 45258 | AA37: 45261 | AB37: =+IF(Z37="",0,AA37-Z37) -> 3 | AC37: TSS Aprobado | AE37: 45260 | AF37: =IF(AE37="","",IF(AE37="TBD","TBD",IF(AE37="N/A","N/A","W"&TEXT(WEEKNUM(AE37,21),"00")&" "&YEAR(AE37)))) -> W48 2023 | AG37: TSS Aprobado | AI37: 45259 | AJ37: =IF(AI37="","",IF(AI37="TBD","TBD",IF(AI37="N/A","N/A","W"&TEXT(WEEKNUM(AI37,21),"00")&" "&YEAR(AI37)))) -> W48 2023 | AK37: TSS Aprobado | AL37: 29-11-23: Aprobado V1. Altura definida 33m útil. Proyección Radier 2x1,5 | AM37: 45259 | AN37: =IF(AM37="","",IF(AM37="TBD","TBD",IF(AM37="N/A","N/A","W"&TEXT(WEEKNUM(AM37,21),"00")&" "&YEAR(AM37)))) -> W48 2023 | AO37: TSS Aprobado | AP37: Área Proyectada 2x1,5 mts Empalme trifásico proyectado con línea aérea de 480 metros hasta TDAYF. Poste de conexión N° 820680. | AQ37: 45259 | AR37: =IF(AQ37="","",IF(AQ37="TBD","TBD",IF(AQ37="N/A","N/A","W"&TEXT(WEEKNUM(AQ37,21),"00")&" "&YEAR(AQ37)))) -> W48 2023 | AW37: 45260 | AX37: =IF(AW37="","",IF(AW37="TBD","TBD",IF(AW37="N/A","N/A","W"&TEXT(WEEKNUM(AW37,21),"00")&" "&YEAR(AW37)))) -> W48 2023 | AY37: TSS Aprobado 4G | AZ37: FC Enviado a OOII | BA37: Contrato Firmado | BB37: 45573 | BD37: 45573 | BE37: =IF(BD37="","",IF(BD37="TBD","TBD",IF(BD37="N/A","N/A","W"&TEXT(WEEKNUM(BD37,21),"00")&" "&YEAR(BD37)))) -> W41 2024 | BG37: =IF(BF37="","",IF(BF37="TBD","TBD",IF(BF37="N/A","N/A","W"&TEXT(WEEKNUM(BF37,21),"00")&" "&YEAR(BF37)))) | BH37: =+IF(BF37="",0,(BF37-BD37)) -> 0 | BI37: Ing Aprobada | BJ37: Rev.3 Aprobado Se levantan las observaciones indicadas. | BK37: 45586 | BL37: =IF(BK37="","",IF(BK37="TBD","TBD",IF(BK37="N/A","N/A","W"&TEXT(WEEKNUM(BK37,21),"00")&" "&YEAR(BK37)))) -> W43 2024 | BM37: Ing Aprobada | BN37: Sin comentarios | BO37: 45607 | BP37: =IF(BO37="","",IF(BO37="TBD","TBD",IF(BO37="N/A","N/A","W"&TEXT(WEEKNUM(BO37,21),"00")&" "&YEAR(BO37)))) -> W46 2024 | BQ37: Ing Aprobada | BS37: 45622 | BT37: =IF(BS37="","",IF(BS37="TBD","TBD",IF(BS37="N/A","N/A","W"&TEXT(WEEKNUM(BS37,21),"00")&" "&YEAR(BS37)))) -> W48 2024 | BU37: Ing Aprobada | BV37: REV1 14-10-2024 Sitio Macro Proyectado Area arriendo 2x1,5 mts Empalme electrico aereo trifasico proyectado desde poste N° 820680 Acometida electrica trifasica aerea proyectada L= 30 mts Linea electrica trifasica aerea proyectada (Lt= 490 mts) (Calpe 3x25 + 1x50 mm2) Malla tierra proyectada Meidor + TDAyF Trifasico Proyectado | BW37: 45579 | BX37: =IF(BW37="","",IF(BW37="TBD","TBD",IF(BW37="N/A","N/A","W"&TEXT(WEEKNUM(BW37,21),"00")&" "&YEAR(BW37)))) -> W42 2024 | BY37: 45616 | BZ37: =IF(BY37="","",IF(BY37="TBD","TBD",IF(BY37="N/A","N/A","W"&TEXT(WEEKNUM(BY37,21),"00")&" "&YEAR(BY37)))) -> W47 2024 | CA37: Ing Aprobada 4G | CB37: Finalizadas | CC37: Finalizadas | CD37: SI | CF37: 45687 | CH37: 45687 | CI37: =IF(CH37="","",IF(CH37="TBD","TBD",IF(CH37="N/A","N/A","W"&TEXT(WEEKNUM(CH37,21),"00")&" "&YEAR(CH37)))) -> W05 2025 | CJ37: 45663 | CK37: =IF(CJ37="","",IF(CJ37="TBD","TBD",IF(CJ37="N/A","N/A","W"&TEXT(WEEKNUM(CJ37,21),"00")&" "&YEAR(CJ37)))) -> W02 2025 | CL37: =+IF(CJ37="",0,(CJ37-CH37)) -> -24 | CM37: As Built Aprobado | CN37: 31-01 Aprobado | CO37: 45688 | CP37: =IF(CO37="","",IF(CO37="TBD","TBD",IF(CO37="N/A","N/A","W"&TEXT(WEEKNUM(CO37,21),"00")&" "&YEAR(CO37)))) -> W05 2025 | CQ37: As Built Aprobado | CR37: Sin Observaciones | CS37: 45687 | CT37: =IF(CS37="","",IF(CS37="TBD","TBD",IF(CS37="N/A","N/A","W"&TEXT(WEEKNUM(CS37,21),"00")&" "&YEAR(CS37)))) -> W05 2025 | CU37: As Built Aprobado | CV37: 31-01 Aprobado | CW37: 45688 | CX37: =IF(CW37="","",IF(CW37="TBD","TBD",IF(CW37="N/A","N/A","W"&TEXT(WEEKNUM(CW37,21),"00")&" "&YEAR(CW37)))) -> W05 2025 | CY37: As Built Aprobado | CZ37: Se registra informe de conexión de energía definitiva, falta respaldo de facturación de suministro para validación de gestión | DA37: 45915 | DB37: =IF(DA37="","",IF(DA37="TBD","TBD",IF(DA37="N/A","N/A","W"&TEXT(WEEKNUM(DA37,21),"00")&" "&YEAR(DA37)))) -> W38 2025 | DC37: 45747 | DD37: =IF(DC37="","",IF(DC37="TBD","TBD",IF(DC37="N/A","N/A","W"&TEXT(WEEKNUM(DC37,21),"00")&" "&YEAR(DC37)))) -> W14 2025 | DE37: As Built Aprobado 4G | DG37: Gabinete Huawei | DK37: FO | DL37: ODF Instalado | DN37: 45799 | DO37: 45799 | DQ37: Huawei | DS37: 45806 | DT37: Integrado | DV37: 45806 | DW37: On Air | EB37: On Air 4G | EC37: Plan 2024 | EJ37: =K37&AY37&CA37&DE37&DT37&DW37 -> VigenteTSS Aprobado 4GIng Aprobada 4GAs Built Aprobado 4GIntegradoOn Air
A38: =IFERROR(IF(VLOOKUP(B38,SEARCH!A:A,1,0)=B38,"OK",""),"") | B38: 06_718 | C38: AgroSuper Lo Miranda | D38: 6 | E38: -34.197644 | F38: -70.871405 | G38: Libertador General Bernardo O'Higgins | H38: Doñihue | I38: CARRETERA H-30 NUMERO 3793 LOC LO MIRANDA | J38: No Vigente | K38: No Vigente | L38: No aplica | O38: ATC | P38: Colo | R38: TORRE | S38: 49 a 53 m | T38: 153195 | U38: 45131 | V38: =IF(U38="","",IF(U38="TBD","TBD",IF(U38="N/A","N/A","W"&TEXT(WEEKNUM(U38,21),"00")&" "&YEAR(U38)))) -> W30 2023 | W38: 45166 | Y38: =IF(X38="","",IF(X38="TBD","TBD",IF(X38="N/A","N/A","W"&TEXT(WEEKNUM(X38,21),"00")&" "&YEAR(X38)))) | AA38: 45168 | AB38: =+IF(Z38="",0,AA38-Z38) -> 0 | AC38: TSS Aprobado | AE38: 45173 | AF38: =IF(AE38="","",IF(AE38="TBD","TBD",IF(AE38="N/A","N/A","W"&TEXT(WEEKNUM(AE38,21),"00")&" "&YEAR(AE38)))) -> W36 2023 | AG38: TSS Aprobado | AI38: 45168 | AJ38: =IF(AI38="","",IF(AI38="TBD","TBD",IF(AI38="N/A","N/A","W"&TEXT(WEEKNUM(AI38,21),"00")&" "&YEAR(AI38)))) -> W35 2023 | AK38: TSS Aprobado | AM38: 45169 | AN38: =IF(AM38="","",IF(AM38="TBD","TBD",IF(AM38="N/A","N/A","W"&TEXT(WEEKNUM(AM38,21),"00")&" "&YEAR(AM38)))) -> W35 2023 | AO38: TSS Aprobado | AQ38: 45173 | AR38: =IF(AQ38="","",IF(AQ38="TBD","TBD",IF(AQ38="N/A","N/A","W"&TEXT(WEEKNUM(AQ38,21),"00")&" "&YEAR(AQ38)))) -> W36 2023 | AW38: 45177 | AX38: =IF(AW38="","",IF(AW38="TBD","TBD",IF(AW38="N/A","N/A","W"&TEXT(WEEKNUM(AW38,21),"00")&" "&YEAR(AW38)))) -> W36 2023 | AY38: TSS Aprobado 4G | AZ38: FC Enviado a OOII | BA38: Contrato No Firmado | BE38: =IF(BD38="","",IF(BD38="TBD","TBD",IF(BD38="N/A","N/A","W"&TEXT(WEEKNUM(BD38,21),"00")&" "&YEAR(BD38)))) | BG38: =IF(BF38="","",IF(BF38="TBD","TBD",IF(BF38="N/A","N/A","W"&TEXT(WEEKNUM(BF38,21),"00")&" "&YEAR(BF38)))) | BH38: =+IF(BF38="",0,(BF38-BD38)) -> 0 | BI38: Ing No Recibida | BL38: =IF(BK38="","",IF(BK38="TBD","TBD",IF(BK38="N/A","N/A","W"&TEXT(WEEKNUM(BK38,21),"00")&" "&YEAR(BK38)))) | BM38: Ing No Recibida | BP38: =IF(BO38="","",IF(BO38="TBD","TBD",IF(BO38="N/A","N/A","W"&TEXT(WEEKNUM(BO38,21),"00")&" "&YEAR(BO38)))) | BQ38: Ing No Recibida | BT38: =IF(BS38="","",IF(BS38="TBD","TBD",IF(BS38="N/A","N/A","W"&TEXT(WEEKNUM(BS38,21),"00")&" "&YEAR(BS38)))) | BU38: Ing No Recibida | BX38: =IF(BW38="","",IF(BW38="TBD","TBD",IF(BW38="N/A","N/A","W"&TEXT(WEEKNUM(BW38,21),"00")&" "&YEAR(BW38)))) | BZ38: =IF(BY38="","",IF(BY38="TBD","TBD",IF(BY38="N/A","N/A","W"&TEXT(WEEKNUM(BY38,21),"00")&" "&YEAR(BY38)))) | CA38: Ing No Recibida 4G | CB38: No Iniciadas | CC38: No iniciadas | CI38: =IF(CH38="","",IF(CH38="TBD","TBD",IF(CH38="N/A","N/A","W"&TEXT(WEEKNUM(CH38,21),"00")&" "&YEAR(CH38)))) | CK38: =IF(CJ38="","",IF(CJ38="TBD","TBD",IF(CJ38="N/A","N/A","W"&TEXT(WEEKNUM(CJ38,21),"00")&" "&YEAR(CJ38)))) | CL38: =+IF(CJ38="",0,(CJ38-CH38)) -> 0 | CM38: As Built No Recibido | CP38: =IF(CO38="","",IF(CO38="TBD","TBD",IF(CO38="N/A","N/A","W"&TEXT(WEEKNUM(CO38,21),"00")&" "&YEAR(CO38)))) | CQ38: As Built No Recibido | CT38: =IF(CS38="","",IF(CS38="TBD","TBD",IF(CS38="N/A","N/A","W"&TEXT(WEEKNUM(CS38,21),"00")&" "&YEAR(CS38)))) | CU38: As Built No Recibido | CX38: =IF(CW38="","",IF(CW38="TBD","TBD",IF(CW38="N/A","N/A","W"&TEXT(WEEKNUM(CW38,21),"00")&" "&YEAR(CW38)))) | CY38: As Built No Recibido | DB38: =IF(DA38="","",IF(DA38="TBD","TBD",IF(DA38="N/A","N/A","W"&TEXT(WEEKNUM(DA38,21),"00")&" "&YEAR(DA38)))) | DD38: =IF(DC38="","",IF(DC38="TBD","TBD",IF(DC38="N/A","N/A","W"&TEXT(WEEKNUM(DC38,21),"00")&" "&YEAR(DC38)))) | DE38: As Built No Recibido | DG38: Gabinete Huawei | DK38: FO | DL38: Pendiente | DQ38: Huawei | EB38: En Etapa de Ingeniería 4G | EI38: 0 | EJ38: =K38&AY38&CA38&DE38&DT38&DW38 -> No VigenteTSS Aprobado 4GIng No Recibida 4GAs Built No Recibido
A39: =IFERROR(IF(VLOOKUP(B39,SEARCH!A:A,1,0)=B39,"OK",""),"") | B39: 06_722 | C39: Coltauco Fundo San José | D39: 6 | E39: -34.2567 | F39: -71.0568 | G39: Libertador General Bernardo O'Higgins | H39: Coltauco | I39: FUNDO SAN JOSE, RINCONADA DE PARRAL, COLTAUCO | J39: No Vigente | K39: No Vigente | L39: No aplica | O39: ATC | P39: Colo | R39: TORRE | S39: 46 a 50m | T39: 151825 | U39: 45131 | V39: =IF(U39="","",IF(U39="TBD","TBD",IF(U39="N/A","N/A","W"&TEXT(WEEKNUM(U39,21),"00")&" "&YEAR(U39)))) -> W30 2023 | W39: 45175 | Y39: =IF(X39="","",IF(X39="TBD","TBD",IF(X39="N/A","N/A","W"&TEXT(WEEKNUM(X39,21),"00")&" "&YEAR(X39)))) | AA39: 45180 | AB39: =+IF(Z39="",0,AA39-Z39) -> 0 | AC39: TSS Aprobado | AE39: 45181 | AF39: =IF(AE39="","",IF(AE39="TBD","TBD",IF(AE39="N/A","N/A","W"&TEXT(WEEKNUM(AE39,21),"00")&" "&YEAR(AE39)))) -> W37 2023 | AG39: TSS Aprobado | AI39: 45177 | AJ39: =IF(AI39="","",IF(AI39="TBD","TBD",IF(AI39="N/A","N/A","W"&TEXT(WEEKNUM(AI39,21),"00")&" "&YEAR(AI39)))) -> W36 2023 | AK39: TSS Aprobado | AM39: 45175 | AN39: =IF(AM39="","",IF(AM39="TBD","TBD",IF(AM39="N/A","N/A","W"&TEXT(WEEKNUM(AM39,21),"00")&" "&YEAR(AM39)))) -> W36 2023 | AO39: TSS Aprobado | AQ39: 45180 | AR39: =IF(AQ39="","",IF(AQ39="TBD","TBD",IF(AQ39="N/A","N/A","W"&TEXT(WEEKNUM(AQ39,21),"00")&" "&YEAR(AQ39)))) -> W37 2023 | AW39: 45181 | AX39: =IF(AW39="","",IF(AW39="TBD","TBD",IF(AW39="N/A","N/A","W"&TEXT(WEEKNUM(AW39,21),"00")&" "&YEAR(AW39)))) -> W37 2023 | AY39: TSS Aprobado 4G | AZ39: FC Enviado a OOII | BA39: Contrato No Firmado | BE39: =IF(BD39="","",IF(BD39="TBD","TBD",IF(BD39="N/A","N/A","W"&TEXT(WEEKNUM(BD39,21),"00")&" "&YEAR(BD39)))) | BG39: =IF(BF39="","",IF(BF39="TBD","TBD",IF(BF39="N/A","N/A","W"&TEXT(WEEKNUM(BF39,21),"00")&" "&YEAR(BF39)))) | BH39: =+IF(BF39="",0,(BF39-BD39)) -> 0 | BI39: Ing No Recibida | BL39: =IF(BK39="","",IF(BK39="TBD","TBD",IF(BK39="N/A","N/A","W"&TEXT(WEEKNUM(BK39,21),"00")&" "&YEAR(BK39)))) | BM39: Ing No Recibida | BP39: =IF(BO39="","",IF(BO39="TBD","TBD",IF(BO39="N/A","N/A","W"&TEXT(WEEKNUM(BO39,21),"00")&" "&YEAR(BO39)))) | BQ39: Ing No Recibida | BT39: =IF(BS39="","",IF(BS39="TBD","TBD",IF(BS39="N/A","N/A","W"&TEXT(WEEKNUM(BS39,21),"00")&" "&YEAR(BS39)))) | BU39: Ing No Recibida | BX39: =IF(BW39="","",IF(BW39="TBD","TBD",IF(BW39="N/A","N/A","W"&TEXT(WEEKNUM(BW39,21),"00")&" "&YEAR(BW39)))) | BZ39: =IF(BY39="","",IF(BY39="TBD","TBD",IF(BY39="N/A","N/A","W"&TEXT(WEEKNUM(BY39,21),"00")&" "&YEAR(BY39)))) | CA39: Ing No Recibida 4G | CB39: No Iniciadas | CC39: No iniciadas | CI39: =IF(CH39="","",IF(CH39="TBD","TBD",IF(CH39="N/A","N/A","W"&TEXT(WEEKNUM(CH39,21),"00")&" "&YEAR(CH39)))) | CK39: =IF(CJ39="","",IF(CJ39="TBD","TBD",IF(CJ39="N/A","N/A","W"&TEXT(WEEKNUM(CJ39,21),"00")&" "&YEAR(CJ39)))) | CL39: =+IF(CJ39="",0,(CJ39-CH39)) -> 0 | CM39: As Built No Recibido | CP39: =IF(CO39="","",IF(CO39="TBD","TBD",IF(CO39="N/A","N/A","W"&TEXT(WEEKNUM(CO39,21),"00")&" "&YEAR(CO39)))) | CQ39: As Built No Recibido | CT39: =IF(CS39="","",IF(CS39="TBD","TBD",IF(CS39="N/A","N/A","W"&TEXT(WEEKNUM(CS39,21),"00")&" "&YEAR(CS39)))) | CU39: As Built No Recibido | CX39: =IF(CW39="","",IF(CW39="TBD","TBD",IF(CW39="N/A","N/A","W"&TEXT(WEEKNUM(CW39,21),"00")&" "&YEAR(CW39)))) | CY39: As Built No Recibido | DB39: =IF(DA39="","",IF(DA39="TBD","TBD",IF(DA39="N/A","N/A","W"&TEXT(WEEKNUM(DA39,21),"00")&" "&YEAR(DA39)))) | DD39: =IF(DC39="","",IF(DC39="TBD","TBD",IF(DC39="N/A","N/A","W"&TEXT(WEEKNUM(DC39,21),"00")&" "&YEAR(DC39)))) | DE39: As Built No Recibido | DG39: Gabinete Huawei | DK39: FO | DL39: Pendiente | DQ39: Huawei | EB39: En Etapa de Ingeniería 4G | EI39: 0 | EJ39: =K39&AY39&CA39&DE39&DT39&DW39 -> No VigenteTSS Aprobado 4GIng No Recibida 4GAs Built No Recibido
A40: =IFERROR(IF(VLOOKUP(B40,SEARCH!A:A,1,0)=B40,"OK",""),"") | B40: 06_726 | C40: Codegua Ruta H-185 | D40: 6 | E40: -34.0537 | F40: -70.6708 | G40: Libertador General Bernardo O'Higgins | H40: Codegua | I40: LOTE B, PARCELA 8-9 , FUNDO LEONERA, CODEGUA | J40: No Vigente | K40: No Vigente | L40: No aplica | O40: ATC | P40: Colo | R40: TORRE | S40: 44 a 48 m | T40: 151854 | U40: 45131 | V40: =IF(U40="","",IF(U40="TBD","TBD",IF(U40="N/A","N/A","W"&TEXT(WEEKNUM(U40,21),"00")&" "&YEAR(U40)))) -> W30 2023 | W40: 45166 | Y40: =IF(X40="","",IF(X40="TBD","TBD",IF(X40="N/A","N/A","W"&TEXT(WEEKNUM(X40,21),"00")&" "&YEAR(X40)))) | AA40: 45168 | AB40: =+IF(Z40="",0,AA40-Z40) -> 0 | AC40: TSS Aprobado | AE40: 45173 | AF40: =IF(AE40="","",IF(AE40="TBD","TBD",IF(AE40="N/A","N/A","W"&TEXT(WEEKNUM(AE40,21),"00")&" "&YEAR(AE40)))) -> W36 2023 | AG40: TSS Aprobado | AI40: 45168 | AJ40: =IF(AI40="","",IF(AI40="TBD","TBD",IF(AI40="N/A","N/A","W"&TEXT(WEEKNUM(AI40,21),"00")&" "&YEAR(AI40)))) -> W35 2023 | AK40: TSS Aprobado | AM40: 45169 | AN40: =IF(AM40="","",IF(AM40="TBD","TBD",IF(AM40="N/A","N/A","W"&TEXT(WEEKNUM(AM40,21),"00")&" "&YEAR(AM40)))) -> W35 2023 | AO40: TSS Aprobado | AQ40: 45170 | AR40: =IF(AQ40="","",IF(AQ40="TBD","TBD",IF(AQ40="N/A","N/A","W"&TEXT(WEEKNUM(AQ40,21),"00")&" "&YEAR(AQ40)))) -> W35 2023 | AW40: 45177 | AX40: =IF(AW40="","",IF(AW40="TBD","TBD",IF(AW40="N/A","N/A","W"&TEXT(WEEKNUM(AW40,21),"00")&" "&YEAR(AW40)))) -> W36 2023 | AY40: TSS Aprobado 4G | AZ40: FC Enviado a OOII | BA40: Contrato No Firmado | BE40: =IF(BD40="","",IF(BD40="TBD","TBD",IF(BD40="N/A","N/A","W"&TEXT(WEEKNUM(BD40,21),"00")&" "&YEAR(BD40)))) | BG40: =IF(BF40="","",IF(BF40="TBD","TBD",IF(BF40="N/A","N/A","W"&TEXT(WEEKNUM(BF40,21),"00")&" "&YEAR(BF40)))) | BH40: =+IF(BF40="",0,(BF40-BD40)) -> 0 | BI40: Ing No Recibida | BL40: =IF(BK40="","",IF(BK40="TBD","TBD",IF(BK40="N/A","N/A","W"&TEXT(WEEKNUM(BK40,21),"00")&" "&YEAR(BK40)))) | BM40: Ing No Recibida | BP40: =IF(BO40="","",IF(BO40="TBD","TBD",IF(BO40="N/A","N/A","W"&TEXT(WEEKNUM(BO40,21),"00")&" "&YEAR(BO40)))) | BQ40: Ing No Recibida | BT40: =IF(BS40="","",IF(BS40="TBD","TBD",IF(BS40="N/A","N/A","W"&TEXT(WEEKNUM(BS40,21),"00")&" "&YEAR(BS40)))) | BU40: Ing No Recibida | BX40: =IF(BW40="","",IF(BW40="TBD","TBD",IF(BW40="N/A","N/A","W"&TEXT(WEEKNUM(BW40,21),"00")&" "&YEAR(BW40)))) | BZ40: =IF(BY40="","",IF(BY40="TBD","TBD",IF(BY40="N/A","N/A","W"&TEXT(WEEKNUM(BY40,21),"00")&" "&YEAR(BY40)))) | CA40: Ing No Recibida 4G | CB40: No Iniciadas | CC40: No iniciadas | CI40: =IF(CH40="","",IF(CH40="TBD","TBD",IF(CH40="N/A","N/A","W"&TEXT(WEEKNUM(CH40,21),"00")&" "&YEAR(CH40)))) | CK40: =IF(CJ40="","",IF(CJ40="TBD","TBD",IF(CJ40="N/A","N/A","W"&TEXT(WEEKNUM(CJ40,21),"00")&" "&YEAR(CJ40)))) | CL40: =+IF(CJ40="",0,(CJ40-CH40)) -> 0 | CM40: As Built No Recibido | CP40: =IF(CO40="","",IF(CO40="TBD","TBD",IF(CO40="N/A","N/A","W"&TEXT(WEEKNUM(CO40,21),"00")&" "&YEAR(CO40)))) | CQ40: As Built No Recibido | CT40: =IF(CS40="","",IF(CS40="TBD","TBD",IF(CS40="N/A","N/A","W"&TEXT(WEEKNUM(CS40,21),"00")&" "&YEAR(CS40)))) | CU40: As Built No Recibido | CX40: =IF(CW40="","",IF(CW40="TBD","TBD",IF(CW40="N/A","N/A","W"&TEXT(WEEKNUM(CW40,21),"00")&" "&YEAR(CW40)))) | CY40: As Built No Recibido | DB40: =IF(DA40="","",IF(DA40="TBD","TBD",IF(DA40="N/A","N/A","W"&TEXT(WEEKNUM(DA40,21),"00")&" "&YEAR(DA40)))) | DD40: =IF(DC40="","",IF(DC40="TBD","TBD",IF(DC40="N/A","N/A","W"&TEXT(WEEKNUM(DC40,21),"00")&" "&YEAR(DC40)))) | DE40: As Built No Recibido | DG40: Gabinete Huawei | DK40: FO | DL40: Pendiente | DQ40: Huawei | EB40: En Etapa de Ingeniería 4G | EI40: 0 | EJ40: =K40&AY40&CA40&DE40&DT40&DW40 -> No VigenteTSS Aprobado 4GIng No Recibida 4GAs Built No Recibido
A41: =IFERROR(IF(VLOOKUP(B41,SEARCH!A:A,1,0)=B41,"OK",""),"") | B41: 06_740 | C41: Machali Avenida Madero | D41: 6 | E41: -34.18267 | F41: -70.66092 | G41: Libertador General Bernardo O'Higgins | H41: Machalí | I41: Camino Las Rosas 115 | J41: Fase 1 | K41: Vigente | L41: No aplica | M41: 1 | O41: ATC | P41: Colo | R41: MONOPOSTE | S41: 20 | T41: 151392 | U41: 45131 | V41: =IF(U41="","",IF(U41="TBD","TBD",IF(U41="N/A","N/A","W"&TEXT(WEEKNUM(U41,21),"00")&" "&YEAR(U41)))) -> W30 2023 | W41: 45156 | Y41: =IF(X41="","",IF(X41="TBD","TBD",IF(X41="N/A","N/A","W"&TEXT(WEEKNUM(X41,21),"00")&" "&YEAR(X41)))) | Z41: 45160 | AA41: 45163 | AB41: =+IF(Z41="",0,AA41-Z41) -> 3 | AC41: TSS Aprobado | AD41: Parte de las panoramicas obstruido por arboles, Panoramicas desordenadas, | AE41: 45190 | AF41: =IF(AE41="","",IF(AE41="TBD","TBD",IF(AE41="N/A","N/A","W"&TEXT(WEEKNUM(AE41,21),"00")&" "&YEAR(AE41)))) -> W38 2023 | AG41: TSS Aprobado | AI41: 45160 | AJ41: =IF(AI41="","",IF(AI41="TBD","TBD",IF(AI41="N/A","N/A","W"&TEXT(WEEKNUM(AI41,21),"00")&" "&YEAR(AI41)))) -> W34 2023 | AK41: TSS Aprobado | AM41: 45168 | AN41: =IF(AM41="","",IF(AM41="TBD","TBD",IF(AM41="N/A","N/A","W"&TEXT(WEEKNUM(AM41,21),"00")&" "&YEAR(AM41)))) -> W35 2023 | AO41: TSS Aprobado | AQ41: 45159 | AR41: =IF(AQ41="","",IF(AQ41="TBD","TBD",IF(AQ41="N/A","N/A","W"&TEXT(WEEKNUM(AQ41,21),"00")&" "&YEAR(AQ41)))) -> W34 2023 | AW41: 45190 | AX41: =IF(AW41="","",IF(AW41="TBD","TBD",IF(AW41="N/A","N/A","W"&TEXT(WEEKNUM(AW41,21),"00")&" "&YEAR(AW41)))) -> W38 2023 | AY41: TSS Aprobado 4G | AZ41: FC Enviado a OOII | BA41: Contrato Firmado | BB41: 45475 | BD41: 45475 | BE41: =IF(BD41="","",IF(BD41="TBD","TBD",IF(BD41="N/A","N/A","W"&TEXT(WEEKNUM(BD41,21),"00")&" "&YEAR(BD41)))) -> W27 2024 | BG41: =IF(BF41="","",IF(BF41="TBD","TBD",IF(BF41="N/A","N/A","W"&TEXT(WEEKNUM(BF41,21),"00")&" "&YEAR(BF41)))) | BH41: =+IF(BF41="",0,(BF41-BD41)) -> 0 | BI41: Ing Aprobada | BJ41: OBSERVACIONES ING - OOCC (lámina 1) 08-07: Observado 1. Tronera: Deben indicar ubicación y dimensiones de tronera en piso y en altura (ruteo cables a sistema radiante) 19-07: Observado 1. Tronera: Falta indicar dimensiones de tronera en la parte superior. 01-08: Observado No se encuentra ingeniería en ubicación indicada. 01-08: Observado No se encuentra ingeniería en ubicación indicada. 19-08: Observado 1. Tronera: Falta indicar dimensiones de tronera en la parte superior. Observación levantada. Ok. | BK41: 45523 | BL41: =IF(BK41="","",IF(BK41="TBD","TBD",IF(BK41="N/A","N/A","W"&TEXT(WEEKNUM(BK41,21),"00")&" "&YEAR(BK41)))) -> W34 2024 | BM41: Ing Aprobada | BN41: Sin comentarios | BO41: 45484 | BP41: =IF(BO41="","",IF(BO41="TBD","TBD",IF(BO41="N/A","N/A","W"&TEXT(WEEKNUM(BO41,21),"00")&" "&YEAR(BO41)))) -> W28 2024 | BQ41: Ing Aprobada | BS41: 45495 | BT41: =IF(BS41="","",IF(BS41="TBD","TBD",IF(BS41="N/A","N/A","W"&TEXT(WEEKNUM(BS41,21),"00")&" "&YEAR(BS41)))) -> W30 2024 | BU41: Ing Aprobada | BV41: REV3 06-08-2024 Acometida: 10 mts Línea Eléctrica: 8 mts L total: 8 mts | BW41: 45483 | BX41: =IF(BW41="","",IF(BW41="TBD","TBD",IF(BW41="N/A","N/A","W"&TEXT(WEEKNUM(BW41,21),"00")&" "&YEAR(BW41)))) -> W28 2024 | BY41: 45523 | BZ41: =IF(BY41="","",IF(BY41="TBD","TBD",IF(BY41="N/A","N/A","W"&TEXT(WEEKNUM(BY41,21),"00")&" "&YEAR(BY41)))) -> W34 2024 | CA41: Ing Aprobada 4G | CB41: Finalizadas | CC41: Finalizadas | CF41: 45636 | CH41: 45636 | CI41: =IF(CH41="","",IF(CH41="TBD","TBD",IF(CH41="N/A","N/A","W"&TEXT(WEEKNUM(CH41,21),"00")&" "&YEAR(CH41)))) -> W50 2024 | CJ41: 45639 | CK41: =IF(CJ41="","",IF(CJ41="TBD","TBD",IF(CJ41="N/A","N/A","W"&TEXT(WEEKNUM(CJ41,21),"00")&" "&YEAR(CJ41)))) -> W50 2024 | CL41: =+IF(CJ41="",0,(CJ41-CH41)) -> 3 | CM41: As Built Aprobado | CN41: INFORME FOTOGRÁFICO 02-01: Aprobado 1. Se validan fotografias con lo proyectado en planos asbuilt. PLANOS AS BUILT 02-01: Aprobado 1. Se valida planimetria. Libro de Obras: Presentado Calidad Acero: Presentado Calidad Hormigon: Presentado (Dosificacion). Ingenieria Aprobada: Presentado | CO41: 45659 | CP41: =IF(CO41="","",IF(CO41="TBD","TBD",IF(CO41="N/A","N/A","W"&TEXT(WEEKNUM(CO41,21),"00")&" "&YEAR(CO41)))) -> W01 2025 | CQ41: As Built Aprobado | CS41: 45659 | CT41: =IF(CS41="","",IF(CS41="TBD","TBD",IF(CS41="N/A","N/A","W"&TEXT(WEEKNUM(CS41,21),"00")&" "&YEAR(CS41)))) -> W01 2025 | CU41: As Built Aprobado | CW41: 45642 | CX41: =IF(CW41="","",IF(CW41="TBD","TBD",IF(CW41="N/A","N/A","W"&TEXT(WEEKNUM(CW41,21),"00")&" "&YEAR(CW41)))) -> W51 2024 | CY41: As Built Aprobado con Observaciones | CZ41: REV2 23-12-2024 Sitio con Energía Provisoria de 3X10A Pendiente N° Medidor Pendiente N° Cliente Pendiente Informe conexión energía definitiva | DA41: 45642 | DB41: =IF(DA41="","",IF(DA41="TBD","TBD",IF(DA41="N/A","N/A","W"&TEXT(WEEKNUM(DA41,21),"00")&" "&YEAR(DA41)))) -> W51 2024 | DC41: 45673 | DD41: =IF(DC41="","",IF(DC41="TBD","TBD",IF(DC41="N/A","N/A","W"&TEXT(WEEKNUM(DC41,21),"00")&" "&YEAR(DC41)))) -> W03 2025 | DE41: As Built Aprobado con Observaciones 4G | DG41: Gabinete Huawei | DH41: 0 | DK41: FO | DL41: ODF Instalado | DN41: 45735 | DO41: 45735 | DQ41: Huawei | DS41: 45751 | DT41: Integrado | DV41: 45751 | DW41: On Air | DZ41: Contrato Holistico | EA41: Pagado con OC 4500187147 | EB41: On Air 4G | EC41: Plan 2024 | EI41: 0 | EJ41: =K41&AY41&CA41&DE41&DT41&DW41 -> VigenteTSS Aprobado 4GIng Aprobada 4GAs Built Aprobado con Observaciones 4GIntegradoOn Air
A42: =IFERROR(IF(VLOOKUP(B42,SEARCH!A:A,1,0)=B42,"OK",""),"") | B42: 06_748 | C42: Cerro Pataguas Ruta H-880 | D42: 6 | E42: -34.2985 | F42: -71.3936 | G42: Libertador General Bernardo O'Higgins | H42: Pichidegua | I42: LOTE A PARCELA 63 | J42: No Vigente | K42: No Vigente | L42: No aplica | O42: ATC | P42: Colo | R42: TORRE | S42: 51 a 55 m | T42: 152329 | U42: 45131 | V42: =IF(U42="","",IF(U42="TBD","TBD",IF(U42="N/A","N/A","W"&TEXT(WEEKNUM(U42,21),"00")&" "&YEAR(U42)))) -> W30 2023 | W42: 45166 | Y42: =IF(X42="","",IF(X42="TBD","TBD",IF(X42="N/A","N/A","W"&TEXT(WEEKNUM(X42,21),"00")&" "&YEAR(X42)))) | AA42: 45168 | AB42: =+IF(Z42="",0,AA42-Z42) -> 0 | AC42: TSS Aprobado | AE42: 45173 | AF42: =IF(AE42="","",IF(AE42="TBD","TBD",IF(AE42="N/A","N/A","W"&TEXT(WEEKNUM(AE42,21),"00")&" "&YEAR(AE42)))) -> W36 2023 | AG42: TSS Aprobado | AI42: 45168 | AJ42: =IF(AI42="","",IF(AI42="TBD","TBD",IF(AI42="N/A","N/A","W"&TEXT(WEEKNUM(AI42,21),"00")&" "&YEAR(AI42)))) -> W35 2023 | AK42: TSS Aprobado | AM42: 45169 | AN42: =IF(AM42="","",IF(AM42="TBD","TBD",IF(AM42="N/A","N/A","W"&TEXT(WEEKNUM(AM42,21),"00")&" "&YEAR(AM42)))) -> W35 2023 | AO42: TSS Aprobado | AQ42: 45173 | AR42: =IF(AQ42="","",IF(AQ42="TBD","TBD",IF(AQ42="N/A","N/A","W"&TEXT(WEEKNUM(AQ42,21),"00")&" "&YEAR(AQ42)))) -> W36 2023 | AW42: 45177 | AX42: =IF(AW42="","",IF(AW42="TBD","TBD",IF(AW42="N/A","N/A","W"&TEXT(WEEKNUM(AW42,21),"00")&" "&YEAR(AW42)))) -> W36 2023 | AY42: TSS Aprobado 4G | AZ42: FC Enviado a OOII | BA42: Contrato No Firmado | BE42: =IF(BD42="","",IF(BD42="TBD","TBD",IF(BD42="N/A","N/A","W"&TEXT(WEEKNUM(BD42,21),"00")&" "&YEAR(BD42)))) | BG42: =IF(BF42="","",IF(BF42="TBD","TBD",IF(BF42="N/A","N/A","W"&TEXT(WEEKNUM(BF42,21),"00")&" "&YEAR(BF42)))) | BH42: =+IF(BF42="",0,(BF42-BD42)) -> 0 | BI42: Ing No Recibida | BL42: =IF(BK42="","",IF(BK42="TBD","TBD",IF(BK42="N/A","N/A","W"&TEXT(WEEKNUM(BK42,21),"00")&" "&YEAR(BK42)))) | BM42: Ing No Recibida | BP42: =IF(BO42="","",IF(BO42="TBD","TBD",IF(BO42="N/A","N/A","W"&TEXT(WEEKNUM(BO42,21),"00")&" "&YEAR(BO42)))) | BQ42: Ing No Recibida | BT42: =IF(BS42="","",IF(BS42="TBD","TBD",IF(BS42="N/A","N/A","W"&TEXT(WEEKNUM(BS42,21),"00")&" "&YEAR(BS42)))) | BU42: Ing No Recibida | BX42: =IF(BW42="","",IF(BW42="TBD","TBD",IF(BW42="N/A","N/A","W"&TEXT(WEEKNUM(BW42,21),"00")&" "&YEAR(BW42)))) | BZ42: =IF(BY42="","",IF(BY42="TBD","TBD",IF(BY42="N/A","N/A","W"&TEXT(WEEKNUM(BY42,21),"00")&" "&YEAR(BY42)))) | CA42: Ing No Recibida 4G | CB42: No Iniciadas | CC42: No iniciadas | CI42: =IF(CH42="","",IF(CH42="TBD","TBD",IF(CH42="N/A","N/A","W"&TEXT(WEEKNUM(CH42,21),"00")&" "&YEAR(CH42)))) | CK42: =IF(CJ42="","",IF(CJ42="TBD","TBD",IF(CJ42="N/A","N/A","W"&TEXT(WEEKNUM(CJ42,21),"00")&" "&YEAR(CJ42)))) | CL42: =+IF(CJ42="",0,(CJ42-CH42)) -> 0 | CM42: As Built No Recibido | CP42: =IF(CO42="","",IF(CO42="TBD","TBD",IF(CO42="N/A","N/A","W"&TEXT(WEEKNUM(CO42,21),"00")&" "&YEAR(CO42)))) | CQ42: As Built No Recibido | CT42: =IF(CS42="","",IF(CS42="TBD","TBD",IF(CS42="N/A","N/A","W"&TEXT(WEEKNUM(CS42,21),"00")&" "&YEAR(CS42)))) | CU42: As Built No Recibido | CX42: =IF(CW42="","",IF(CW42="TBD","TBD",IF(CW42="N/A","N/A","W"&TEXT(WEEKNUM(CW42,21),"00")&" "&YEAR(CW42)))) | CY42: As Built No Recibido | DB42: =IF(DA42="","",IF(DA42="TBD","TBD",IF(DA42="N/A","N/A","W"&TEXT(WEEKNUM(DA42,21),"00")&" "&YEAR(DA42)))) | DD42: =IF(DC42="","",IF(DC42="TBD","TBD",IF(DC42="N/A","N/A","W"&TEXT(WEEKNUM(DC42,21),"00")&" "&YEAR(DC42)))) | DE42: As Built No Recibido | DG42: Gabinete Huawei | DK42: FO | DL42: Pendiente | DQ42: Huawei | EB42: En Etapa de Ingeniería 4G | EI42: 0 | EJ42: =K42&AY42&CA42&DE42&DT42&DW42 -> No VigenteTSS Aprobado 4GIng No Recibida 4GAs Built No Recibido
A43: =IFERROR(IF(VLOOKUP(B43,SEARCH!A:A,1,0)=B43,"OK",""),"") | B43: 06_754 | C43: Rancagua Norte Lago Azul | D43: 6 | E43: -34.1322 | F43: -70.73 | G43: Libertador General Bernardo O'Higgins | H43: Rancagua | I43: AV. KENNEDY 3100 | J43: Fase 1 | K43: Vigente | L43: No aplica | M43: Sitio Recibido | O43: ATC | P43: Colo | R43: TORRE | S43: 32 | T43: 152255 | U43: 45131 | V43: =IF(U43="","",IF(U43="TBD","TBD",IF(U43="N/A","N/A","W"&TEXT(WEEKNUM(U43,21),"00")&" "&YEAR(U43)))) -> W30 2023 | W43: 45156 | Y43: =IF(X43="","",IF(X43="TBD","TBD",IF(X43="N/A","N/A","W"&TEXT(WEEKNUM(X43,21),"00")&" "&YEAR(X43)))) | Z43: 45160 | AA43: 45163 | AB43: =+IF(Z43="",0,AA43-Z43) -> 3 | AC43: TSS Aprobado | AD43: Torre cercana a sitio existente, organizar panoramicas, Actualizar HW con el enviado, | AE43: 45190 | AF43: =IF(AE43="","",IF(AE43="TBD","TBD",IF(AE43="N/A","N/A","W"&TEXT(WEEKNUM(AE43,21),"00")&" "&YEAR(AE43)))) -> W38 2023 | AG43: TSS Aprobado | AI43: 45160 | AJ43: =IF(AI43="","",IF(AI43="TBD","TBD",IF(AI43="N/A","N/A","W"&TEXT(WEEKNUM(AI43,21),"00")&" "&YEAR(AI43)))) -> W34 2023 | AK43: TSS Aprobado | AM43: 45168 | AN43: =IF(AM43="","",IF(AM43="TBD","TBD",IF(AM43="N/A","N/A","W"&TEXT(WEEKNUM(AM43,21),"00")&" "&YEAR(AM43)))) -> W35 2023 | AO43: TSS Aprobado | AQ43: 45160 | AR43: =IF(AQ43="","",IF(AQ43="TBD","TBD",IF(AQ43="N/A","N/A","W"&TEXT(WEEKNUM(AQ43,21),"00")&" "&YEAR(AQ43)))) -> W34 2023 | AW43: 45190 | AX43: =IF(AW43="","",IF(AW43="TBD","TBD",IF(AW43="N/A","N/A","W"&TEXT(WEEKNUM(AW43,21),"00")&" "&YEAR(AW43)))) -> W38 2023 | AY43: TSS Aprobado 4G | AZ43: FC Enviado a OOII | BA43: Contrato Firmado | BB43: 45475 | BD43: 45475 | BE43: =IF(BD43="","",IF(BD43="TBD","TBD",IF(BD43="N/A","N/A","W"&TEXT(WEEKNUM(BD43,21),"00")&" "&YEAR(BD43)))) -> W27 2024 | BG43: =IF(BF43="","",IF(BF43="TBD","TBD",IF(BF43="N/A","N/A","W"&TEXT(WEEKNUM(BF43,21),"00")&" "&YEAR(BF43)))) | BH43: =+IF(BF43="",0,(BF43-BD43)) -> 0 | BI43: Ing Aprobada | BJ43: 08-07: Aprobado 2. El area en piso es de 2x1,5m: 3m2. | BK43: 45481 | BL43: =IF(BK43="","",IF(BK43="TBD","TBD",IF(BK43="N/A","N/A","W"&TEXT(WEEKNUM(BK43,21),"00")&" "&YEAR(BK43)))) -> W28 2024 | BM43: Ing Aprobada | BN43: Sin Comentarios | BO43: 45518 | BP43: =IF(BO43="","",IF(BO43="TBD","TBD",IF(BO43="N/A","N/A","W"&TEXT(WEEKNUM(BO43,21),"00")&" "&YEAR(BO43)))) -> W33 2024 | BQ43: Ing Aprobada | BS43: 45495 | BT43: =IF(BS43="","",IF(BS43="TBD","TBD",IF(BS43="N/A","N/A","W"&TEXT(WEEKNUM(BS43,21),"00")&" "&YEAR(BS43)))) -> W30 2024 | BU43: Ing Aprobada | BV43: REV3 06-08-2024 S/E Proyectado de 30KVA Acometida: 25 mts Línea Eléctrica: 115 mts L total: 115 mts | BW43: 45484 | BX43: =IF(BW43="","",IF(BW43="TBD","TBD",IF(BW43="N/A","N/A","W"&TEXT(WEEKNUM(BW43,21),"00")&" "&YEAR(BW43)))) -> W28 2024 | BY43: 45518 | BZ43: =IF(BY43="","",IF(BY43="TBD","TBD",IF(BY43="N/A","N/A","W"&TEXT(WEEKNUM(BY43,21),"00")&" "&YEAR(BY43)))) -> W33 2024 | CA43: Ing Aprobada 4G | CB43: Finalizadas | CC43: Finalizadas | CF43: 45561 | CH43: 45561 | CI43: =IF(CH43="","",IF(CH43="TBD","TBD",IF(CH43="N/A","N/A","W"&TEXT(WEEKNUM(CH43,21),"00")&" "&YEAR(CH43)))) -> W39 2024 | CK43: =IF(CJ43="","",IF(CJ43="TBD","TBD",IF(CJ43="N/A","N/A","W"&TEXT(WEEKNUM(CJ43,21),"00")&" "&YEAR(CJ43)))) | CL43: =+IF(CJ43="",0,(CJ43-CH43)) -> 0 | CM43: As Built Aprobado con Observaciones | CN43: INFORME FOTOGRÁFICO Rev.1 30-09: Aprobado con observaciones 1. Se valida segun plano Asbuilt y fotografias adicionales fuera del informe fotografico. PLANOS AS BUILT Rev.1 30-09: Aprobado 1. Se valida planimetria. | CO43: 45566 | CP43: =IF(CO43="","",IF(CO43="TBD","TBD",IF(CO43="N/A","N/A","W"&TEXT(WEEKNUM(CO43,21),"00")&" "&YEAR(CO43)))) -> W40 2024 | CQ43: As Built Aprobado | CR43: Sin observacion | CS43: 45568 | CT43: =IF(CS43="","",IF(CS43="TBD","TBD",IF(CS43="N/A","N/A","W"&TEXT(WEEKNUM(CS43,21),"00")&" "&YEAR(CS43)))) -> W40 2024 | CU43: As Built Aprobado | CW43: 45568 | CX43: =IF(CW43="","",IF(CW43="TBD","TBD",IF(CW43="N/A","N/A","W"&TEXT(WEEKNUM(CW43,21),"00")&" "&YEAR(CW43)))) -> W40 2024 | CY43: As Built Aprobado | DA43: 45568 | DB43: =IF(DA43="","",IF(DA43="TBD","TBD",IF(DA43="N/A","N/A","W"&TEXT(WEEKNUM(DA43,21),"00")&" "&YEAR(DA43)))) -> W40 2024 | DC43: 45758 | DD43: =IF(DC43="","",IF(DC43="TBD","TBD",IF(DC43="N/A","N/A","W"&TEXT(WEEKNUM(DC43,21),"00")&" "&YEAR(DC43)))) -> W15 2025 | DE43: As Built Aprobado con Observaciones 4G | DG43: Gabinete Huawei | DH43: 0 | DK43: FO | DL43: ODF Instalado | DN43: 45639 | DO43: 45639 | DQ43: Huawei | DV43: 45656 | DW43: On Air | DZ43: Contrato Holistico | EA43: Pagado con OC 4500187147 | EB43: On Air 4G | EC43: Plan 2024 | EI43: 0 | EJ43: =K43&AY43&CA43&DE43&DT43&DW43 -> VigenteTSS Aprobado 4GIng Aprobada 4GAs Built Aprobado con Observaciones 4GOn Air
A44: =IFERROR(IF(VLOOKUP(B44,SEARCH!A:A,1,0)=B44,"OK",""),"") | B44: 07_152 | C44: Linares Avda. Circunvalacion | D44: 7 | E44: -35.8253 | F44: -71.6015 | G44: Maule | H44: Linares | I44: PARCELA VILLA ROSA S/N | J44: No Vigente | K44: No Vigente | L44: No aplica | O44: ATC | P44: Colo | R44: MONOPOSTE | S44: 17 | T44: 152844 | U44: 45131 | V44: =IF(U44="","",IF(U44="TBD","TBD",IF(U44="N/A","N/A","W"&TEXT(WEEKNUM(U44,21),"00")&" "&YEAR(U44)))) -> W30 2023 | W44: 45156 | Y44: =IF(X44="","",IF(X44="TBD","TBD",IF(X44="N/A","N/A","W"&TEXT(WEEKNUM(X44,21),"00")&" "&YEAR(X44)))) | Z44: 45160 | AA44: 45163 | AB44: =+IF(Z44="",0,AA44-Z44) -> 3 | AC44: TSS Aprobado | AE44: 45173 | AF44: =IF(AE44="","",IF(AE44="TBD","TBD",IF(AE44="N/A","N/A","W"&TEXT(WEEKNUM(AE44,21),"00")&" "&YEAR(AE44)))) -> W36 2023 | AG44: TSS Aprobado | AI44: 45160 | AJ44: =IF(AI44="","",IF(AI44="TBD","TBD",IF(AI44="N/A","N/A","W"&TEXT(WEEKNUM(AI44,21),"00")&" "&YEAR(AI44)))) -> W34 2023 | AK44: TSS Aprobado | AM44: 45168 | AN44: =IF(AM44="","",IF(AM44="TBD","TBD",IF(AM44="N/A","N/A","W"&TEXT(WEEKNUM(AM44,21),"00")&" "&YEAR(AM44)))) -> W35 2023 | AO44: TSS Aprobado | AQ44: 45160 | AR44: =IF(AQ44="","",IF(AQ44="TBD","TBD",IF(AQ44="N/A","N/A","W"&TEXT(WEEKNUM(AQ44,21),"00")&" "&YEAR(AQ44)))) -> W34 2023 | AW44: 45177 | AX44: =IF(AW44="","",IF(AW44="TBD","TBD",IF(AW44="N/A","N/A","W"&TEXT(WEEKNUM(AW44,21),"00")&" "&YEAR(AW44)))) -> W36 2023 | AY44: TSS Aprobado 4G | AZ44: FC Enviado a OOII | BA44: Contrato No Firmado | BE44: =IF(BD44="","",IF(BD44="TBD","TBD",IF(BD44="N/A","N/A","W"&TEXT(WEEKNUM(BD44,21),"00")&" "&YEAR(BD44)))) | BG44: =IF(BF44="","",IF(BF44="TBD","TBD",IF(BF44="N/A","N/A","W"&TEXT(WEEKNUM(BF44,21),"00")&" "&YEAR(BF44)))) | BH44: =+IF(BF44="",0,(BF44-BD44)) -> 0 | BI44: Ing No Recibida | BL44: =IF(BK44="","",IF(BK44="TBD","TBD",IF(BK44="N/A","N/A","W"&TEXT(WEEKNUM(BK44,21),"00")&" "&YEAR(BK44)))) | BM44: Ing No Recibida | BP44: =IF(BO44="","",IF(BO44="TBD","TBD",IF(BO44="N/A","N/A","W"&TEXT(WEEKNUM(BO44,21),"00")&" "&YEAR(BO44)))) | BQ44: Ing No Recibida | BT44: =IF(BS44="","",IF(BS44="TBD","TBD",IF(BS44="N/A","N/A","W"&TEXT(WEEKNUM(BS44,21),"00")&" "&YEAR(BS44)))) | BU44: Ing No Recibida | BX44: =IF(BW44="","",IF(BW44="TBD","TBD",IF(BW44="N/A","N/A","W"&TEXT(WEEKNUM(BW44,21),"00")&" "&YEAR(BW44)))) | BZ44: =IF(BY44="","",IF(BY44="TBD","TBD",IF(BY44="N/A","N/A","W"&TEXT(WEEKNUM(BY44,21),"00")&" "&YEAR(BY44)))) | CA44: Ing No Recibida 4G | CB44: No Iniciadas | CC44: No iniciadas | CI44: =IF(CH44="","",IF(CH44="TBD","TBD",IF(CH44="N/A","N/A","W"&TEXT(WEEKNUM(CH44,21),"00")&" "&YEAR(CH44)))) | CK44: =IF(CJ44="","",IF(CJ44="TBD","TBD",IF(CJ44="N/A","N/A","W"&TEXT(WEEKNUM(CJ44,21),"00")&" "&YEAR(CJ44)))) | CL44: =+IF(CJ44="",0,(CJ44-CH44)) -> 0 | CM44: As Built No Recibido | CP44: =IF(CO44="","",IF(CO44="TBD","TBD",IF(CO44="N/A","N/A","W"&TEXT(WEEKNUM(CO44,21),"00")&" "&YEAR(CO44)))) | CQ44: As Built No Recibido | CT44: =IF(CS44="","",IF(CS44="TBD","TBD",IF(CS44="N/A","N/A","W"&TEXT(WEEKNUM(CS44,21),"00")&" "&YEAR(CS44)))) | CU44: As Built No Recibido | CX44: =IF(CW44="","",IF(CW44="TBD","TBD",IF(CW44="N/A","N/A","W"&TEXT(WEEKNUM(CW44,21),"00")&" "&YEAR(CW44)))) | CY44: As Built No Recibido | DB44: =IF(DA44="","",IF(DA44="TBD","TBD",IF(DA44="N/A","N/A","W"&TEXT(WEEKNUM(DA44,21),"00")&" "&YEAR(DA44)))) | DD44: =IF(DC44="","",IF(DC44="TBD","TBD",IF(DC44="N/A","N/A","W"&TEXT(WEEKNUM(DC44,21),"00")&" "&YEAR(DC44)))) | DE44: As Built No Recibido | DG44: Gabinete Huawei | DK44: FO | DL44: Pendiente | DQ44: Huawei | EB44: En Etapa de Ingeniería 4G | EI44: 0 | EJ44: =K44&AY44&CA44&DE44&DT44&DW44 -> No VigenteTSS Aprobado 4GIng No Recibida 4GAs Built No Recibido
A45: =IFERROR(IF(VLOOKUP(B45,SEARCH!A:A,1,0)=B45,"OK",""),"") | B45: 07_708 | C45: Balmaceda Curico | D45: 7 | E45: -34.9942 | F45: -71.2481 | G45: Maule | H45: Curicó | I45: Calle lautaro N# 816 | J45: Fase 1 | K45: Vigente | L45: No aplica | M45: Sitio Recibido | O45: ATC | P45: Colo | R45: MONOPOSTE | S45: 24 | T45: 151240 | U45: 45131 | V45: =IF(U45="","",IF(U45="TBD","TBD",IF(U45="N/A","N/A","W"&TEXT(WEEKNUM(U45,21),"00")&" "&YEAR(U45)))) -> W30 2023 | W45: 45166 | Y45: =IF(X45="","",IF(X45="TBD","TBD",IF(X45="N/A","N/A","W"&TEXT(WEEKNUM(X45,21),"00")&" "&YEAR(X45)))) | AA45: 45168 | AB45: =+IF(Z45="",0,AA45-Z45) -> 0 | AC45: TSS Aprobado | AE45: 45170 | AF45: =IF(AE45="","",IF(AE45="TBD","TBD",IF(AE45="N/A","N/A","W"&TEXT(WEEKNUM(AE45,21),"00")&" "&YEAR(AE45)))) -> W35 2023 | AG45: TSS Aprobado | AI45: 45168 | AJ45: =IF(AI45="","",IF(AI45="TBD","TBD",IF(AI45="N/A","N/A","W"&TEXT(WEEKNUM(AI45,21),"00")&" "&YEAR(AI45)))) -> W35 2023 | AK45: TSS Aprobado | AM45: 45169 | AN45: =IF(AM45="","",IF(AM45="TBD","TBD",IF(AM45="N/A","N/A","W"&TEXT(WEEKNUM(AM45,21),"00")&" "&YEAR(AM45)))) -> W35 2023 | AO45: TSS Aprobado | AQ45: 45170 | AR45: =IF(AQ45="","",IF(AQ45="TBD","TBD",IF(AQ45="N/A","N/A","W"&TEXT(WEEKNUM(AQ45,21),"00")&" "&YEAR(AQ45)))) -> W35 2023 | AW45: 45170 | AX45: =IF(AW45="","",IF(AW45="TBD","TBD",IF(AW45="N/A","N/A","W"&TEXT(WEEKNUM(AW45,21),"00")&" "&YEAR(AW45)))) -> W35 2023 | AY45: TSS Aprobado 4G | AZ45: FC Enviado a OOII | BA45: Contrato Firmado | BB45: 45525 | BD45: 45526 | BE45: =IF(BD45="","",IF(BD45="TBD","TBD",IF(BD45="N/A","N/A","W"&TEXT(WEEKNUM(BD45,21),"00")&" "&YEAR(BD45)))) -> W34 2024 | BG45: =IF(BF45="","",IF(BF45="TBD","TBD",IF(BF45="N/A","N/A","W"&TEXT(WEEKNUM(BF45,21),"00")&" "&YEAR(BF45)))) | BH45: =+IF(BF45="",0,(BF45-BD45)) -> 0 | BI45: Ing Aprobada | BJ45: Rev.1 12-09: Aprobado 1. Area en piso: 2x1,5m 2. Soporte RF: 3 soportes dobles. 3. Soporte MMOO: 1 soporte simple. 4. EPC hasta base de torre -->Porta feeders | BK45: 45547 | BL45: =IF(BK45="","",IF(BK45="TBD","TBD",IF(BK45="N/A","N/A","W"&TEXT(WEEKNUM(BK45,21),"00")&" "&YEAR(BK45)))) -> W37 2024 | BM45: Ing Aprobada | BN45: Sin Comentarios | BO45: 45534 | BP45: =IF(BO45="","",IF(BO45="TBD","TBD",IF(BO45="N/A","N/A","W"&TEXT(WEEKNUM(BO45,21),"00")&" "&YEAR(BO45)))) -> W35 2024 | BQ45: Ing Aprobada | BS45: 45533 | BT45: =IF(BS45="","",IF(BS45="TBD","TBD",IF(BS45="N/A","N/A","W"&TEXT(WEEKNUM(BS45,21),"00")&" "&YEAR(BS45)))) -> W35 2024 | BU45: Ing Aprobada | BV45: REV2 04-09-2024 (Resumen) Área Proyectada 2x1,5 mts Acometida eléctrica BT Trifásica aérea proyectada (L=30 mts) desde poste referencia N° 679528 Línea eléctrica proyectada trifásica adosada a piso (4x4 AWG) (L=170mts) TDAyF + Gabinete PCC + Gabinete Baterías Proyectado Malla Tierra proyectada para sitio | BW45: 45539 | BX45: =IF(BW45="","",IF(BW45="TBD","TBD",IF(BW45="N/A","N/A","W"&TEXT(WEEKNUM(BW45,21),"00")&" "&YEAR(BW45)))) -> W36 2024 | BY45: 45548 | BZ45: =IF(BY45="","",IF(BY45="TBD","TBD",IF(BY45="N/A","N/A","W"&TEXT(WEEKNUM(BY45,21),"00")&" "&YEAR(BY45)))) -> W37 2024 | CA45: Ing Aprobada 4G | CB45: Finalizadas | CC45: Finalizadas | CE45: SI | CF45: 45629 | CH45: 45630 | CI45: =IF(CH45="","",IF(CH45="TBD","TBD",IF(CH45="N/A","N/A","W"&TEXT(WEEKNUM(CH45,21),"00")&" "&YEAR(CH45)))) -> W49 2024 | CJ45: 45632 | CK45: =IF(CJ45="","",IF(CJ45="TBD","TBD",IF(CJ45="N/A","N/A","W"&TEXT(WEEKNUM(CJ45,21),"00")&" "&YEAR(CJ45)))) -> W49 2024 | CL45: =+IF(CJ45="",0,(CJ45-CH45)) -> 2 | CM45: As Built Aprobado | CN45: Informe Fotográfico 04-12: Aprobado 1. Se valida sitio con informe fotografico y fotos sueltas en carpeta. Plano As Built 04-12: Aprobado 1. Se valida planimetria con lo visto en informe fotografico. | CO45: 45630 | CP45: =IF(CO45="","",IF(CO45="TBD","TBD",IF(CO45="N/A","N/A","W"&TEXT(WEEKNUM(CO45,21),"00")&" "&YEAR(CO45)))) -> W49 2024 | CQ45: As Built Aprobado | CR45: Sin Observaciones | CS45: 45639 | CT45: =IF(CS45="","",IF(CS45="TBD","TBD",IF(CS45="N/A","N/A","W"&TEXT(WEEKNUM(CS45,21),"00")&" "&YEAR(CS45)))) -> W50 2024 | CU45: As Built Aprobado | CW45: 45636 | CX45: =IF(CW45="","",IF(CW45="TBD","TBD",IF(CW45="N/A","N/A","W"&TEXT(WEEKNUM(CW45,21),"00")&" "&YEAR(CW45)))) -> W50 2024 | CY45: As Built Aprobado | DA45: 45636 | DB45: =IF(DA45="","",IF(DA45="TBD","TBD",IF(DA45="N/A","N/A","W"&TEXT(WEEKNUM(DA45,21),"00")&" "&YEAR(DA45)))) -> W50 2024 | DC45: 45643 | DD45: =IF(DC45="","",IF(DC45="TBD","TBD",IF(DC45="N/A","N/A","W"&TEXT(WEEKNUM(DC45,21),"00")&" "&YEAR(DC45)))) -> W51 2024 | DE45: As Built Aprobado 4G | DG45: Gabinete Huawei | DH45: 0 | DK45: FO | DL45: ODF Instalado | DN45: 45702 | DO45: 45702 | DQ45: Huawei | DS45: 45723 | DT45: Integrado | DV45: 45723 | DW45: On Air | DZ45: Contrato Holistico | EA45: Pagado con OC 4500187147 | EB45: On Air 4G | EC45: Plan 2024 | EI45: 0 | EJ45: =K45&AY45&CA45&DE45&DT45&DW45 -> VigenteTSS Aprobado 4GIng Aprobada 4GAs Built Aprobado 4GIntegradoOn Air
A46: =IFERROR(IF(VLOOKUP(B46,SEARCH!A:A,1,0)=B46,"OK",""),"") | B46: 07_709 | C46: Linares Sur 2 | D46: 7 | E46: -35.8523 | F46: -71.6088 | G46: Maule | H46: Linares | I46: SALIDA CUELLAR 38 LINARES | J46: On Hold | K46: No Vigente | L46: No aplica | O46: ATC | P46: Colo | R46: TORRE | S46: 32 a 36 m | T46: 152501 | U46: 45131 | V46: =IF(U46="","",IF(U46="TBD","TBD",IF(U46="N/A","N/A","W"&TEXT(WEEKNUM(U46,21),"00")&" "&YEAR(U46)))) -> W30 2023 | W46: 45156 | Y46: =IF(X46="","",IF(X46="TBD","TBD",IF(X46="N/A","N/A","W"&TEXT(WEEKNUM(X46,21),"00")&" "&YEAR(X46)))) | Z46: 45160 | AA46: 45163 | AB46: =+IF(Z46="",0,AA46-Z46) -> 3 | AC46: TSS Aprobado | AE46: 45173 | AF46: =IF(AE46="","",IF(AE46="TBD","TBD",IF(AE46="N/A","N/A","W"&TEXT(WEEKNUM(AE46,21),"00")&" "&YEAR(AE46)))) -> W36 2023 | AG46: TSS Aprobado | AI46: 45160 | AJ46: =IF(AI46="","",IF(AI46="TBD","TBD",IF(AI46="N/A","N/A","W"&TEXT(WEEKNUM(AI46,21),"00")&" "&YEAR(AI46)))) -> W34 2023 | AK46: TSS Aprobado | AM46: 45168 | AN46: =IF(AM46="","",IF(AM46="TBD","TBD",IF(AM46="N/A","N/A","W"&TEXT(WEEKNUM(AM46,21),"00")&" "&YEAR(AM46)))) -> W35 2023 | AO46: TSS Aprobado | AQ46: 45160 | AR46: =IF(AQ46="","",IF(AQ46="TBD","TBD",IF(AQ46="N/A","N/A","W"&TEXT(WEEKNUM(AQ46,21),"00")&" "&YEAR(AQ46)))) -> W34 2023 | AW46: 45177 | AX46: =IF(AW46="","",IF(AW46="TBD","TBD",IF(AW46="N/A","N/A","W"&TEXT(WEEKNUM(AW46,21),"00")&" "&YEAR(AW46)))) -> W36 2023 | AY46: TSS Aprobado 4G | AZ46: FC Enviado a OOII | BA46: Contrato No Firmado | BE46: =IF(BD46="","",IF(BD46="TBD","TBD",IF(BD46="N/A","N/A","W"&TEXT(WEEKNUM(BD46,21),"00")&" "&YEAR(BD46)))) | BG46: =IF(BF46="","",IF(BF46="TBD","TBD",IF(BF46="N/A","N/A","W"&TEXT(WEEKNUM(BF46,21),"00")&" "&YEAR(BF46)))) | BH46: =+IF(BF46="",0,(BF46-BD46)) -> 0 | BI46: Ing No Recibida | BL46: =IF(BK46="","",IF(BK46="TBD","TBD",IF(BK46="N/A","N/A","W"&TEXT(WEEKNUM(BK46,21),"00")&" "&YEAR(BK46)))) | BM46: Ing No Recibida | BP46: =IF(BO46="","",IF(BO46="TBD","TBD",IF(BO46="N/A","N/A","W"&TEXT(WEEKNUM(BO46,21),"00")&" "&YEAR(BO46)))) | BQ46: Ing No Recibida | BT46: =IF(BS46="","",IF(BS46="TBD","TBD",IF(BS46="N/A","N/A","W"&TEXT(WEEKNUM(BS46,21),"00")&" "&YEAR(BS46)))) | BU46: Ing No Recibida | BX46: =IF(BW46="","",IF(BW46="TBD","TBD",IF(BW46="N/A","N/A","W"&TEXT(WEEKNUM(BW46,21),"00")&" "&YEAR(BW46)))) | BZ46: =IF(BY46="","",IF(BY46="TBD","TBD",IF(BY46="N/A","N/A","W"&TEXT(WEEKNUM(BY46,21),"00")&" "&YEAR(BY46)))) | CA46: Ing No Recibida 4G | CB46: No Iniciadas | CC46: No iniciadas | CI46: =IF(CH46="","",IF(CH46="TBD","TBD",IF(CH46="N/A","N/A","W"&TEXT(WEEKNUM(CH46,21),"00")&" "&YEAR(CH46)))) | CK46: =IF(CJ46="","",IF(CJ46="TBD","TBD",IF(CJ46="N/A","N/A","W"&TEXT(WEEKNUM(CJ46,21),"00")&" "&YEAR(CJ46)))) | CL46: =+IF(CJ46="",0,(CJ46-CH46)) -> 0 | CM46: As Built No Recibido | CP46: =IF(CO46="","",IF(CO46="TBD","TBD",IF(CO46="N/A","N/A","W"&TEXT(WEEKNUM(CO46,21),"00")&" "&YEAR(CO46)))) | CQ46: As Built No Recibido | CT46: =IF(CS46="","",IF(CS46="TBD","TBD",IF(CS46="N/A","N/A","W"&TEXT(WEEKNUM(CS46,21),"00")&" "&YEAR(CS46)))) | CU46: As Built No Recibido | CX46: =IF(CW46="","",IF(CW46="TBD","TBD",IF(CW46="N/A","N/A","W"&TEXT(WEEKNUM(CW46,21),"00")&" "&YEAR(CW46)))) | CY46: As Built No Recibido | DB46: =IF(DA46="","",IF(DA46="TBD","TBD",IF(DA46="N/A","N/A","W"&TEXT(WEEKNUM(DA46,21),"00")&" "&YEAR(DA46)))) | DD46: =IF(DC46="","",IF(DC46="TBD","TBD",IF(DC46="N/A","N/A","W"&TEXT(WEEKNUM(DC46,21),"00")&" "&YEAR(DC46)))) | DE46: As Built No Recibido | DG46: Gabinete Huawei | DK46: FO | DL46: Pendiente | DQ46: Huawei | EB46: En Etapa de Ingeniería 4G | EI46: 0 | EJ46: =K46&AY46&CA46&DE46&DT46&DW46 -> No VigenteTSS Aprobado 4GIng No Recibida 4GAs Built No Recibido
